Workbook

Sheet 概要・活用ガイド
A1: 技術士一次試験 衛生工学部門 過去問統合データベース (H23〜R7)
A2: 平成23年度〜令和7年度 (全16回・560問題) / 全問の問題文・選択肢・公式正答を収録したスプレッドシート（v28：問題文・分類の訂正版（区分を15に集約））
A4: 収録試験回数 | C4: 総収録問題数 | E4: 問題文・選択肢の収録範囲 | G4: 3ブロック分類
A5: 16 回分 | C5: 560 問 | E5: 全16回(560問) | G5: 100 %
A6: H23〜R7 (R1本・再含む) | C6: 35問 × 16回 | E6: 問題文・全選択肢付き | G6: 大分類・区分（15区分）＋出題論点（細目）完備
A8: ■ ワークブックの構成と活用方法
A9: シート名 | B9: 内容と目的 | C9: おすすめの活用方法
A10: 概要・活用ガイド | B10: 本データベースの概要、収録範囲、凡例の解説 | C10: 全体の構成把握、学習計画の立案
A11: 各年度シート（R7〜H23） | B11: 各年度の全35問の問題文全文、選択肢①〜⑤、公式正答、分類（R1は本試験・再試験の2シート） | C11: 年度別の本番形式演習、年度単位のチェック
A12: 過去問マスターDB | B12: H23〜R7全560問のテーマ、正答、分類、問題文・選択肢のマスターリスト | C12: オートフィルターによる頻出テーマ・苦手ジャンルの絞り込み
A13: ジャンル別出題傾向 | B13: 15区分別の出題状況（問題数・出題回数・平均問題数は自動集計）と学習優先度（S/A/B） | C13: 出題確率の高い「Sランク分野」からの効率的学習
A14: 正答一覧マトリクス | B14: 問1〜問35 × 16回分の正答番号クロス一覧表 | C14: 自己採点、正答番号の横断確認
A15: 修正履歴 | B15: v15からv28への修正内容（修正前後・根拠） | C15: 修正箇所の確認、今後の更新時の参照

Sheet 図表
A1: 図・表が必要な問題の原本画像（技術士第一次試験 過去問PDFより切り出し）
A3: 問題ID | B3: 内容 | C3: 区分 | D3: 問題文（DB） | E3: 図表
A4: H23-01 | B4: 床断面の熱橋（層構成 d₁・d₂・d₃） | C4: A | D4: 下図に示す外気に接する床断面の熱橋を考慮した熱貫流率の計算方法について，最も適切なものはどれか。ただし，熱伝導率をλ，厚さをdとし，木根太によって生じる熱橋の面積比率（熱橋面積率）を A_HB，室内側熱伝達抵抗を R_i，外気側熱伝達抵抗を R_o とする。また，木根太の厚さ d_3 は，断熱材の厚さ d_2 よりも大きいものとする。
A5: H23-08 | B5: 空調系統図と空気線図 | C5: A | D5: 下図に示すように，外気冷却コイルで室内空気の湿度を満足させるまで冷却し，還気（加熱又は冷却）コイルで室内温度を満足するように制御して，極力再熱負荷を発生させない空調システムを採用した。室内負荷として最も近い値はどれか。ただし，与条件は以下のとおりとする。 空気の比容積：0.83 m³／kg(DA) 空調吹出し風量：30,000 m³／h 外気風量：10,000 m³／h 空調系統：空調系統図参照 空気線図上のポイント：空調系統図参照 システム内発熱（送風機，ダクト断熱）：無視
A6: H24-03 | B6: 図A・図B（開口の位置） | C6: A | D6: 図Aに示す建物の換気量をQとするとき，図Bに示す建物の換気量に最も近いものはどれか。ただし，図A，図Bともに室温は20℃で，建物外部は無風，開口部の流量係数は全て等しいとする。図は，それぞれ建物の鉛直断面を示したものである。
A7: H24-06 | B7: 2層壁体の厚さ | C7: A | D7: 下図に示す2層からなる壁体の熱通過率（熱貫流率）として，最も近い値はどれか。ただし，α_o ＝ 20 W/(m²・K)，α_i ＝ 8 W/(m²・K)，λ_1 ＝ 1.5 W/(m・K)，λ_2 ＝ 0.02 W/(m・K) とする。
A8: H24-09 | B8: ダクト合流部・与条件・局部抵抗係数表 | C8: A | D8: 下図に示す長方形ダクトの合流部（Ⓐ → Ⓑ）の局部圧力損失として，最も近い値はどれか。ただし，与条件は以下の通りとする。
A9: H25-04 | B9: 開口の直列合成 | C9: B | D9: 二面開口住戸の通風性能について，風上開口の相当（有効）開口面積α1A1，風下開口の相当（有効）開口面積α2A2が下図に示す値である場合，それらの直列合成による相当（有効）開口面積（合成αA）の値に最も近いものはどれか。［図：α1A1＝10.0 m²，α2A2＝5.0 m²］
A10: H25-07 | B10: p-h線図と選択肢表 | C10: B | D10: 次の記述の，［ ］に入る記号又は数式の組合せとして最も適切なものはどれか。 下図に示す圧縮式冷凍機の冷凍サイクルにおいて，［A］は圧縮過程を，［B］は蒸発過程をそれぞれ示しており，この冷凍サイクルの成績係数は，［C］で表される。［図：p-h線図。1→2は蒸発，2→3は圧縮，3→4は凝縮，4→1は膨張。エンタルピーはh1，h2，h3］
A11: H26-01 | B11: 点光源（180cd・高さ3m・30°） | C11: B | D11: 下図に示す点光源に照らされたA点の水平面照度に最も近い値はどれか。ただし，点光源の配光特性は一様なものとし，反射は考慮しないものとする。［図：点光源の光度180cd，床面からの高さ3m，A点は点光源から見て水平面に対し30°の位置］
A12: H26-09 | B12: 空調系統図と空気線図 | C12: A | D12: 下図に示すように，外気冷却コイルで室内空気の湿度を満足させるまで冷却し，還気（加熱又は冷却）コイルで室内温度を満足するように制御して，極力再熱負荷を発生させない空調システムを採用し，さらにCO2制御による外気量制御を採用して省エネルギーを図っている。空気線図上に示す運転状態における室内負荷に最も近い値はどれか。ただし，与条件は以下のとおりとする。 空気の比容積：0.83 m³／kg(DA) 空調吹出し風量：20,000 m³／h 外気風量：4,000 m³／h（定格外気風量：6,000 m³／h，CO2制御） 空調系統：空調系統図参照 空気線図上のポイント：空調系統図参照 システム内発熱（送風
A13: H26-23 | B13: 浄化槽フローシートと断面図 | C13: A | D13: 下図に示す嫌気ろ床接触ばっ気方式の小型浄化槽に関する次の記述のうち，最も不適切なものはどれか。
A14: H27-14 | B14: 全圧・静圧分布図（a〜d） | C14: A | D14: 下図は，送風機の吹出し側，吸込み側に，それぞれ円形ダクトを取り付け，送風機を運転している状況におけるダクトの全圧，静圧の分布を示したものである。送風機全圧を図中の矢印で示すa, b, c, dの圧力を用いて表すとすれば，最も適切なものは次のうちどれか。ただし，a, b, c, dの値は絶対値である。
A15: H27-17 | B15: 二面開口住戸（風速・風圧係数） | C15: A | D15: 下図に示す二面開口住戸の風力換気量に最も近い値はどれか。ただし，外部風速（v），各開口部の風圧係数（C），実効面積（αA）は下図に示す値とする。
... A31: R7-02 | B31: 点光源（1000cd・2m・60°） | C31: B | D31: 下図に示す点光源に照らされたＡ点の水平面照度に最も近い値はどれか。ただし，点光源の配光特性は一様なものとし，反射は考慮しないものとする。[点光源(光度1000cd)、高さ2m、照射角60°、A点]

Sheet R7(令和7年度)問題・選択肢
A1: 問題ID | B1: 設問番号 | C1: 大分類(ブロック) | D1: サブジャンル | E1: 公式正答 | F1: 問題のテーマ・内容概要 | G1: 問題文 | H1: 選択肢① | I1: 選択肢② | J1: 選択肢③ | K1: 選択肢④ | L1: 選択肢⑤ | M1: 出題論点（細目）
A2: R7-01 | B2: Ⅲ-1 | C2: 建築環境・設備・建築物衛生管理 | D2: 光・音 | E2: 3 | F2: 垂直ルーバー、太陽放射スペクトル、天空日射と直達日射、南向き外壁日射量、外壁色と日射熱取得 | G2: 日照・日射に関する次の記述のうち，最も不適切なものはどれか。 | H2: ① 垂直ルーバーや縦型ブラインドは角度調整を行わない場合は，建物の東西面などほぼ正面からの日射を遮へいできない。 | I2: ② 大気圏外の太陽放射は，地表面を覆っている大気によって散乱・吸収され，およそ 0.3～2.5μm の範囲のみが地表面に到達する。 | J2: ③ 天空日射の光源は日射の大気による散乱であるため，大気透過率が大きいほど天空日射量は大きくなり，直達日射量は小さくなる。 | K2: ④ 夏至の南向きの外壁の鉛直面は，東西を向いた外壁の鉛直面よりも入射する直達日射量は少ない。 | L2: ⑤ 白やオフホワイトなどの明るい色の外壁は日射吸収率が小さいため，黒色や暗褐色の外壁に比べて壁が吸収する日射熱取得を削減することができる。 | M2: 日照・日射・採光
A3: R7-02 | B3: Ⅲ-2 | C3: 建築環境・設備・建築物衛生管理 | D3: 光・音 | E3: 5 | F3: 点光源（光度1000cd、高さ2m、照射角60°）からのA点における水平面照度の計算 | G3: 下図に示す点光源に照らされたＡ点の水平面照度に最も近い値はどれか。ただし，点光源の配光特性は一様なものとし，反射は考慮しないものとする。[点光源(光度1000cd)、高さ2m、照射角60°、A点] | H3: ① 250 lx | I3: ② 63 lx | J3: ③ 54 lx | K3: ④ 42 lx | L3: ⑤ 31 lx | M3: 照明・光環境
A4: R7-03 | B4: Ⅲ-3 | C4: 建築環境・設備・建築物衛生管理 | D4: 熱・湿気 | E4: 4 | F4: 自然対流熱伝達率（暖房・冷房）、熱伝導率の温度依存性、ニュートンの冷却則、木材と土・しっくいの熱伝導率比較、空気層の熱抵抗 | G4: 伝熱に関する次の記述のうち，最も不適切なものはどれか。 | H4: ① 自然対流熱伝達率は，暖房時の天井面よりも，冷房時の天井面の方が低い値となる。 | I4: ② 熱伝導率の値は温度が上昇するとやや変化するが，建築分野では定数として扱って良い。 | J4: ③ 壁体のような固体表面から空気へ熱が伝えられることを対流熱伝達といい，その伝熱量はニュートンの冷却則で与えられる。 | K4: ④ 木材の熱伝導率は，土やしっくいの熱伝導率よりも大きい。 | L4: ⑤ 壁体内や二重ガラスの空気層の熱抵抗は，空気層の厚さが増すと増大するが，厚さが10cmを超えるとその値はほとんど増えない。 | M4: 伝熱・断熱
A5: R7-04 | B5: Ⅲ-4 | C5: 建築環境・設備・建築物衛生管理 | D5: 光・音 | E5: 2 | F5: コインシデンス効果と壁厚、複層ガラスと一重ガラスの遮音性能比較、二重壁の低音域共鳴透過、板振動型吸音、多孔質型吸音 | G5: 各種材料の遮音性能に関する次の記述のうち，最も不適切なものはどれか。 | H5: ① 壁に音が斜め入射する場合，壁の屈曲波の周波数と一致すると，壁が大きく振動して音が透過する。これをコインシデンス効果といい，壁厚が厚い場合は，その効果の対象となる周波数が中低音域まで下がるので，対策を要する場合がある。 | I5: ② ガラスの厚さを合計して6mmとし，面密度を一定とした場合，複層ガラス窓は同一面密度の一重ガラス窓と比べて遮音性能は高い。 | J5: ③ 二重壁では，低周波部分で透過損失の著しい落ち込みが見られ，この現象を低音域共鳴透過と呼ぶ。 | K5: ④ 板振動型吸音機構では，低音域の共振周波数付近で吸音率は高く，中高音域の吸音率は小さい。 | L5: ⑤ 多孔質型吸音機構では，波長の長い低音に対して吸音率を高めるためには，材料を厚くするか剛壁から離して設置する必要がある。 | M5: 音環境
A6: R7-05 | B6: Ⅲ-5 | C6: 建築環境・設備・建築物衛生管理 | D6: 熱・湿気 | E6: 2 | F6: 北側居室・押入の表面結露、壁体内の防湿層配置（高温・室内側）、通気層の設置、夏型結露、冬季表面結露防止対策 | G6: 建物の結露に関する次の記述のうち，最も不適切なものはどれか。 | H6: ① 家族が集う南側居室から暖房を行っていない北側居室へ水蒸気が拡散した場合，温度が低い外壁内表面や空気流動が少ない押入の中等に結露が生じる恐れが多い。 | I6: ② 内部結露の防止には，壁体内に水蒸気が侵入しないようにすることが第一であり，壁体内に防湿層を入れる場合，温度の高い断熱材の室外側に配置しなければならない。 | J6: ③ 内部結露の防止には，壁体内部の水蒸気を外気に逃がすための通気層を断熱層室外側に設ける構法を採用すると良い。 | K6: ④ 夏型結露とは，高温多湿の空気が低温度の空間に流れ込んで，相対湿度を上昇させることにより，発生する結露である。 | L6: ⑤ 冬季の表面結露の防止には，「室内における水蒸気発生の抑制」，「換気による室内絶対湿度の低下」，「外壁断熱強化による室内側表面温度の上昇」などが考えられる。 | M6: 結露・湿気・湿り空気
A7: R7-06 | B7: Ⅲ-6 | C7: 建築環境・設備・建築物衛生管理 | D7: 光・音 | E7: 1 | F7: 赤外放射の波長定義（780nm以上）、雲と実効放射量、単層壁の熱貫流メカニズム、ステファン・ボルツマンの法則、建材表面の放射率 | G7: 日射・熱移動に関する次の記述のうち，最も不適切なものはどれか。 | H7: ① 波長380nm以下の範囲を赤外放射と呼ぶ。 | I7: ② 実効放射量（夜間放射量）は，雲があるときは，雲がないときに比較して減少する。 | J7: ③ 単層壁の熱貫流は，壁体内部では熱伝導，壁の表面では対流及び放射によって行われている。 | K7: ④ 完全黒体から放出される放射エネルギーは，絶対温度の4乗に比例する。 | L7: ⑤ 多くの建材（灰色体）の表面の放射率は0.9前後を示し，入射する放射エネルギーの9割前後を吸収する。 | M7: 日照・日射・採光
A8: R7-07 | B8: Ⅲ-7 | C8: 建築環境・設備・建築物衛生管理 | D8: 熱・湿気 | E8: 3 | F8: 相当隙間面積値（C値）、外付け・内付けブラインドの日射遮蔽係数SC、コンクリート外断熱・内断熱の熱応答性、コアンダ効果（壁面付着噴流）、通風開口面積比 | G8: 熱環境に関する次の記述のうち，最も不適切なものはどれか。 | H8: ① 総相当隙間面積［cm²］を，外皮内の実質延べ床面積［m²］で除したものを相当隙間面積値（C値）という。 | I8: ② 開口部の日射遮蔽装置として，内付けブラインドを設置するよりも外付けブラインドを設置する方が日射遮蔽係数SCは，小さくなる。 | J8: ③ コンクリート構造の躯体では，外断熱工法の方が内断熱工法よりも熱容量の小さい材料で室内空間が覆われるため，空調や日射受熱による室温の応答性が良い。 | K8: ④ 壁面や天井面に近接した噴流はその面に付着して流れ，自由噴流に比べ流速が減衰しにくく，到達距離が長い傾向にある。 | L8: ⑤ 通風により室内に適当な気流速度を得るためには，風上側の開口を小さめに，風下側の開口を大きめに設定することも重要である。 | M8: 伝熱・断熱
A9: R7-08 | B9: Ⅲ-8 | C9: 建築環境・設備・建築物衛生管理 | D9: 空調 | E9: 2 | F9: 湿り空気の比エンタルピー状態変化計算（乾き空気1000kgの加熱・加湿に必要な熱量MJ） | G9: 湿り空気の比エンタルピーh ［kJ/kg(DA)］は次の式で表せる。 h = 1.0 t + (2500 + 1.8 t) x ［kJ/kg(DA)］ ただし，t：乾球温度［℃］，x：絶対湿度［kg/kg(DA)］。乾き空気1000kg(DA)を含む，乾球温度10℃，絶対湿度0.004 kg/kg(DA)の湿り空気を，蒸気で加熱・加湿し，乾球温度42℃，絶対湿度0.014 kg/kg(DA)としたときの空気の得た熱量の値として，最も適切なものはどれか。 | H9: ① 58 kJ | I9: ② 58 MJ | J9: ③ 78 MJ | K9: ④ 32 MJ | L9: ⑤ 20 kJ | M9: 空調計算（負荷・空気線図・冷凍サイクル）
A10: R7-09 | B10: Ⅲ-9 | C10: 建築環境・設備・建築物衛生管理 | D10: 換気・室内空気 | E10: 4 | F10: 顕熱発熱量（6480W）と室内外温度差（34℃-19℃=15K）からの必要換気量計算（m³/h） | G10: 室内機器の顕熱発熱量が6480 Wのときに，室温を34 ℃に保つための換気量に最も近い値はどれか。ただし，外気温19 ℃，空気密度1.2 kg/m³，乾き空気の定圧比熱は1.0 kJ/(kg・K)とする。 | H10: ① 100 m³/h | I10: ② 360 m³/h | J10: ③ 1023 m³/h | K10: ④ 1296 m³/h | L10: ⑤ 1555 m³/h | M10: 換気・通風
A11: R7-10 | B11: Ⅲ-10 | C11: 建築環境・設備・建築物衛生管理 | D11: 空調 | E11: 3 | F11: パーソナル空調のフレキシビリティ、執務者快適性、タスク・アンビエント空調の制御概念、中央方式空調における個人対応、エネルギー消費制御 | G11: パーソナル空調に関する次の記述のうち，最も不適切なものはどれか。 | H11: ① 什器のレイアウト変更やOA機器の増設など，容易に対処できるフレキシビリティも備えるべき条件である。 | I11: ② 省エネルギー性のほかに，導入で期待される効果として，執務者の快適性の向上があげられる。 | J11: ③ タスク域は緩和した設定で空調を行い，在席時にアンビエント域を通常の空調とすることで，空間全体の空調エネルギーを抑えることが可能になる。 | K11: ④ 従来の中央方式空調システムでも吹出し口の配置・形状などによって，個人ごとの対応が可能である。 | L11: ⑤ 運転方法や制御方法が悪いと，逆にエネルギーを浪費する可能性がある。 | M11: 空調方式・省エネルギー
A12: R7-11 | B12: Ⅲ-11 | C12: 建築環境・設備・建築物衛生管理 | D12: 空調 | E12: 2 | F12: コジェネ部分負荷特性、BEMSとコミッショニング、エアフローウィンドウの目的、全熱交換器と外気冷房、CO2濃度による外気量制御 | G12: 省エネルギーシステムに関する次の記述のうち，最も適切なものはどれか。 | H12: ① コージェネレーション方式では，建物内の電気や熱負荷など，負荷率が下がると発電効率は上昇する。 | I12: ② BEMSは，性能検証（コミッショニング）を助ける手段の1つである。 | J12: ③ エアフローウィンドウ方式は，外壁を二重にしたペリメータ空調を省略する方式である。 | K12: ④ 全熱交換器を用いて換気を行う場合，中間期の外気冷房可能な時期でも，省エネルギー効果が期待できる。 | L12: ⑤ 事務所の場合，給気のCO2濃度をもとに取入れ外気量を制御することで外気負荷の軽減が図れる。 | M12: 空調方式・省エネルギー
A13: R7-12 | B13: Ⅲ-12 | C13: 建築環境・設備・建築物衛生管理 | D13: 給排水・防災 | E13: 2 | F13: 一般給水圧力上限（300〜400kPa）、高置水槽容量と揚水ポンプの相互関係、受水槽有効容量（日予想給水量の1/2程度）、受水槽周囲点検スペース（600mm/1000mm）、クロスコネクションの定義 | G13: 給水設備に関する次の記述のうち，最も適切なものはどれか。 | H13: ① 一般に給水管の給水圧力の上限値は，ホテルやアパートなど人間生活の場においては，400〜500kPa程度として計画する。 | I13: ② 高置水槽方式においては，高置水槽の容量と揚水ポンプの揚水量とは相互に関係を有する。 | J13: ③ 受水槽の有効容量は，水道本管の水圧により引込み水量が変化することと，水道本管の断水なども考慮して，一般に1日予想給水量の60〜80％程度としている。 | K13: ④ 受水槽周囲には，点検スペースとして，300mm以上，上部には600mm以上の空間を設ける。 | L13: ⑤ クロスコネクションとは，水受け容器中に吐き出された水，又はその他の溶液が給水管内に生じた負圧による吸引作用のため，給水管内に逆流することをいう。 | M13: 給水・給湯
... A36: R7-35 | B36: Ⅲ-35 | C36: 廃棄物管理 | D36: 法制度・リサイクル・循環型社会 | E36: 5 | F36: 生活環境影響調査指針（許可要施設での実施義務、地域・構造特性による非該当項目の割愛可能、変更許可時も必要、集合設置時は一括での実施が可能） | G36: 「廃棄物処理施設生活環境影響調査指針（平成18年9月環境省）」に関する次の記述のうち，最も不適切なものはどれか。 | H36: ① 生活環境影響調査は，許可を要するすべての廃棄物処理施設について実施が義務づけられている。 | I36: ② 生活環境影響調査の対象とする調査事項は，廃棄物処理施設の稼働等に伴って生じる生活環境への影響に関するもので，大気質，騒音，振動，悪臭，水質及び地下水である。 | J36: ③ 対象施設の構造上の特性や地域特性からみて，影響が発生することが想定されない調査事項（例えば，排水を排出しない施設の場合の水質汚濁など）については，具体的な調査を実施する必要がない。 | K36: ④ 生活環境影響調査は，廃棄物処理施設の変更の許可を受ける場合にも必要である。 | L36: ⑤ 複数の廃棄物処理施設を集合して設置する場合は，それぞれの施設ごとに生活環境影響調査を実施しなければならない。 | M36: 廃棄物処理法・制度・処理施設・その他

Sheet R6(令和6年度)問題・選択肢
A1: 問題ID | B1: 設問番号 | C1: 大分類(ブロック) | D1: サブジャンル | E1: 公式正答 | F1: 問題のテーマ・内容概要 | G1: 問題文 | H1: 選択肢① | I1: 選択肢② | J1: 選択肢③ | K1: 選択肢④ | L1: 選択肢⑤ | M1: 出題論点（細目）
A2: R6-01 | B2: Ⅲ-1 | C2: 建築環境・設備・建築物衛生管理 | D2: 光・音 | E2: 4 | F2: 室の容積・吸音率変化に伴う残響時間の計算 | G2: 間口5m、奥行き5m、天井高さ3m、吸音率0.1の内装で作られた直方体の室がある。この室の残響時間は1.1秒であった。次に、内装のうち壁のみを吸音率0.25の材料に変更した。変更後の室の残響時間として、最も近い値はどれか。 | H2: ① 3.8秒 | I2: ② 2.4秒 | J2: ③ 0.8秒 | K2: ④ 0.6秒 | L2: ⑤ 0.4秒 | M2: 音環境
A3: R6-02 | B3: Ⅲ-2 | C3: 建築環境・設備・建築物衛生管理 | D3: 熱・湿気 | E3: 3 | F3: 湿気環境、水蒸気発生量、二重サッシおよび乾湿球湿度計に関する記述 | G3: 湿気環境に関する次の記述のうち、最も不適切なものはどれか。 | H3: ① 木材の含水率が20%を超えると腐朽菌が繁殖しやすくなるため、住宅の土台回りは高含水率になりやすいので、床下換気を十分にする必要がある。 | I3: ② 環境温度20℃において、静座時に人体（成人男性）から放出される水蒸気量は、34g/(h・人)程度である。 | J3: ③ 結露を防ぐために二重サッシを使用する場合、外気側のサッシはできるだけ気密にし、室内側は湿気が逃げやすい構造にする必要がある。 | K3: ④ 温度25℃、相対湿度95%が最もカビが発生しやすい条件であるといわれている。 | L3: ⑤ アスマン通風乾湿計において、乾球及び湿球の周辺空気が飽和している状態では、乾球温度と湿球温度の示度は等しくなる。 | M3: 結露・湿気・湿り空気
A4: R6-03 | B4: Ⅲ-3 | C4: 建築環境・設備・建築物衛生管理 | D4: 温熱・省エネ指標 | E4: 5 | F4: 作用温度(OT)、熱中性域、アダプティブモデル、PMVおよびSET*の定義 | G4: 温熱快適性に関する次の記述のうち、最も不適切なものはどれか。 | H4: ① 作用温度（OT）は、静穏な環境では気温と平均放射温度の平均値とみなせる。 | I4: ② 生理的に快適な条件は、体温調節機構が無意識に最小限の努力で血管の収縮、拡張を行い、皮膚表面温度を約33℃に保てる熱中性域と呼ばれる状態にあることである。 | J4: ③ 環境適応モデル（アダプティブモデル）は、中央制御方式の空調を行う建物と、在室者自らが窓の開閉可能な自然換気方式の建物とでは、在室者の快適性が異なることを示したものである。 | K4: ④ ドラフトを防ぐため、作用温度（OT）が22.5℃以下の場合で、予想平均温冷感申告（PMV）が±0.5の範囲では、建物や窓、空調システムに起因する気流は体周囲のどの高さにおいても0.15m/sを超えないことが望ましいとされる。 | L4: ⑤ 新有効温度（ET*）はGaggeらによる理論から導かれた体感温度で、椅座静位、着衣量1.0clo、静穏気流、平均放射温度＝空気温度という標準状態でのET*が標準新有効温度（SET*）とされる。 | M4: 温熱環境・温熱指標
A5: R6-04 | B5: Ⅲ-4 | C5: 建築環境・設備・建築物衛生管理 | D5: 熱・湿気 | E5: 2 | F5: 対流・放射熱伝達、総合熱貫流率、日射熱流および貫流熱抵抗に関する記述 | G5: 熱環境に関する次の記述のうち、最も不適切なものはどれか。 | H5: ① 壁や窓の固体表面からは対流と放射で熱が移動するが、室内側の設計用の熱伝達率は自然対流熱伝達率に放射熱伝達率を加えた9W/(m²・K)が一般に用いられる。 | I5: ② 建物全体の熱損失は、総合熱貫流率に内外の温度差を乗じて求められるが、総合熱貫流率には換気熱損失の影響は考慮されていない。 | J5: ③ 日射が当たる外壁表面から流入する熱流は、相当外気温度と外壁表面温度の差に、屋外側熱伝達率を乗じることで求められるが、建物外壁表面に日射を反射する塗料を用いると相当外気温が下がるため、室内への貫流熱流を小さく抑えることができる。 | K5: ④ 壁の熱貫流抵抗は、壁を構成する各要素の熱抵抗の和に室内側熱伝達抵抗と屋外側熱伝達抵抗を加えた値で求められる。 | L5: ⑤ 外気温度の変化が無視できる状態で、暖房運転開始・停止を同じ条件で行ったとき、断熱性の高い建物の方が低い建物より定常状態の室温は高くなり、熱容量の大きい建物は定常状態に達するまでの温度変化が緩慢になる。 | M5: 伝熱・断熱
A6: R6-05 | B6: Ⅲ-5 | C6: 建築環境・設備・建築物衛生管理 | D6: 換気・室内空気 | E6: 1 | F6: 風圧係数、圧力差、中性帯および流量係数に関する自然換気の基本法則 | G6: 建物の自然換気に関する次の記述のうち、最も不適切なものはどれか。 | H6: ① 2つの開口部があるとき、2つの開口部とも負の風圧係数となる場合、それらの風圧係数に差があっても風力換気は生じない。 | I6: ② 窓を開放した場合などの開口部通過風量は、開口部面積に比例し、圧力差の平方根に比例する。 | J6: ③ 中性帯の位置は、定性的には開口部の大きい方に近づく。 | K6: ④ 高さの異なる2つの開口部があるときの温度差換気量は、直列合成した実効面積αAに比例するとともに、室内外温度差及び開口高さの差の平方根に比例して増加する。 | L6: ⑤ 実効面積αAにおけるαは流量係数であり、開口の形状や寸法で異なるが、通常端部が直角に整形された窓では0.6〜0.7程度となる。 | M6: 換気・通風
A7: R6-06 | B7: Ⅲ-6 | C7: 建築環境・設備・建築物衛生管理 | D7: 光・音 | E7: 3 | F7: 明視の4条件、フリッカー、正反射光・直接グレアおよび設計用全天空照度 | G7: 光環境・視環境に関する次の記述のうち、最も不適切なものはどれか。 | H7: ① 明視の4条件として、対象物の明るさ、視対象と背景の対比、対象物の大きさ、見る時間が挙げられるが、このうち照明が関わるものは「対象物の明るさ」である。 | I7: ② フリッカーは不快感を引き起こす要因となるが、人間は10Hzの光の点滅に対して最も反応し、60〜70Hzで感じなくなるとされる。 | J7: ③ 視対象が高輝度ではなくても表面が光沢面で、視線と光源の位置によっては正反射した光によって視対象が見えにくくなる場合があり、これを直接グレアという。 | K7: ④ 昼光照明においては、最低照度の確保のために、設計用全天空照度として「暗い日」に当たる5000lxを用いるのが一般的である。 | L7: ⑤ 昼光照明の計算で用いる昼光率には直射日光が考慮されていないが、近年、光ダクトなど直射日光を活用する昼光利用システムがみられるようになっている。 | M7: 日照・日射・採光
A8: R6-07 | B8: Ⅲ-7 | C8: 建築環境・設備・建築物衛生管理 | D8: 空調 | E8: 5 | F8: 回転型・静止型全熱交換器の特徴および外気取入系統の計画 | G8: 全熱交換器に関する次の記述のうち、最も不適切なものはどれか。 | H8: ① 回転型は、ロータの回転に伴って排気の一部が給気側に移行することがある。 | I8: ② 静止型の給排気を隔てる仕切り板は、伝熱性と透湿性を持つ材料である。 | J8: ③ 静止型は、回転型よりも目詰まりを起こしやすい。 | K8: ④ 中間期の運転には注意が必要な場合もある。 | L8: ⑤ 空調システムに全熱交換器を使用する場合、別に外気取入用系統が必要である。 | M8: 空調方式・省エネルギー
A9: R6-08 | B9: Ⅲ-8 | C9: 建築環境・設備・建築物衛生管理 | D9: 給排水・防災 | E9: 2 | F9: シャワー給湯時の給湯量（混合湯量）計算 | G9: シャワーヘッドから給湯量（混合湯量）16L/min、使用温度（混合湯温度）40℃のお湯を出す場合、給湯温度を60℃、給水温度を15℃とすると、給湯すべき給湯量として、最も近い値はどれか。ただし、配管などの熱損失はないものとする。 | H9: ① 8.2 L/min | I9: ② 8.9 L/min | J9: ③ 10.0 L/min | K9: ④ 10.7 L/min | L9: ⑤ 11.6 L/min | M9: 給水・給湯
A10: R6-09 | B10: Ⅲ-9 | C10: 建築環境・設備・建築物衛生管理 | D10: 給排水・防災 | E10: 3 | F10: 防火ダンパのヒューズ溶融温度および鋼板厚さの規格値の組合せ | G10: 防火ダンパに関する次の記述の、[ ア ]〜[ ウ ]に入る語句の組合せとして、最も適切なものはどれか。 「ダクトに設置される防火ダンパの温度ヒューズ型の溶融温度は、一般換気用 [ ア ] 程度、排煙用 [ イ ] 程度であり、羽根及びケーシングは [ ウ ] 以上の鋼板でつくる。」 | H10: ① ア: 72℃, イ: 270℃, ウ: 1.2mm | I10: ② ア: 72℃, イ: 280℃, ウ: 1.2mm | J10: ③ ア: 72℃, イ: 280℃, ウ: 1.5mm | K10: ④ ア: 120℃, イ: 270℃, ウ: 1.5mm | L10: ⑤ ア: 120℃, イ: 280℃, ウ: 1.5mm | M10: 防災・排煙・消火
A11: R6-10 | B11: Ⅲ-10 | C11: 建築環境・設備・建築物衛生管理 | D11: 給排水・防災 | E11: 4 | F11: スイベルジョイント、ベローズ型継手、循環ポンプおよびガス給湯器能力表示 | G11: 給湯設備に関する次の記述のうち、最も不適切なものはどれか。 | H11: ① スイベルジョイント工法とは、配管の分岐部に複数のエルボを組合せて用い、可とう性を持たせた配管工法である。 | I11: ② ベローズ型伸縮継手とは、波形状に加工した管が軸方向に伸縮する構造の継手である。 | J11: ③ 強制循環方式における循環ポンプは、一般に貯湯槽の直前の返湯管部分に設置する。 | K11: ④ 給湯栓を開いて即座に湯が必要になるホテルなどでは、湯を供給する往管だけが設置された単管式が多く用いられる。 | L11: ⑤ ガス給湯器では能力表示に「号」を用いるが、1号は流量1 [L/min] の水の温度を25℃上昇させる能力である。 | M11: 給水・給湯
A12: R6-11 | B12: Ⅲ-11 | C12: 建築環境・設備・建築物衛生管理 | D12: 空調 | E12: 1 | F12: デシカント空調、エアフローウィンドウ、氷蓄熱およびパッケージ型空調の特性 | G12: 空気調和設備に関する次の記述のうち、最も不適切なものはどれか。 | H12: ① デシカント空調における除湿は、空気を冷却することで、水を凝縮して分離している。 | I12: ② エアフローウィンドウは、従来のファンコイルユニット方式と異なり、水損リスクを減らし、保守管理の省力化が可能となる。 | J12: ③ 熱源によって生成された冷温熱を蓄える蓄熱槽のうち、氷蓄熱では、同じ熱量なら水蓄熱より容積が小さくてすむ。 | K12: ④ スクリュー式冷凍機は、中規模の建物用空調及び産業用に用いられる。 | L12: ⑤ パッケージ型空調機方式では、特殊なユニットを除き、通常は外気処理機能を持たないため、室内空気質確保のための対策が必要である。 | M12: 空調方式・省エネルギー
A13: R6-12 | B13: Ⅲ-12 | C13: 建築環境・設備・建築物衛生管理 | D13: 空調 | E13: 1 | F13: 吸収式、冷却式、吸着式および圧縮式除湿装置の作動原理と用途比較 | G13: 除湿装置に関する次の記述のうち、最も不適切なものはどれか。 | H13: ① 吸収式除湿装置は、家庭用途向けであり、幅広く使用されている。 | I13: ② 冷却式除湿装置は、処理空気の温度低下と相対湿度の上昇を伴うため、これらが問題となる場合は、冷却除去後の空気を加熱（再熱）する必要がある。 | J13: ③ 吸着式除湿装置は、水分を吸着する性質を持つシリカゲル、活性アルミナ、合成ゼオライト、活性炭などの吸着剤を利用したものである。 | K13: ④ 圧縮式除湿装置は、空気を圧縮することによって水蒸気の分圧を増加させ、水蒸気の飽和点を超えさせて凝縮分離する方式であり、設備費及び運転費が高くなる。 | L13: ⑤ 冷却式除湿装置は、機構が簡単で、設備費が安く、空気の露点温度が高い場合に有利である。 | M13: 空調機器・ダクト・熱源
... A36: R6-35 | B36: Ⅲ-35 | C36: 廃棄物管理 | D36: 最終処分場・浸出水 | E36: 5 | F36: 最終処分場の廃止基準（ガス発生、内部温度、悪臭）および廃止後の指定区域指定 | G36: 一般廃棄物最終処分場及び産業廃棄物管理型最終処分場の廃止に関する次の記述のうち、最も不適切なものはどれか。 | H36: ① 廃止の基準として、埋立地からガスの発生がほとんど認められないこと又はガスの発生量の増加が2年以上にわたり認められないことが定められている。 | I36: ② 廃止の基準として、埋立地の内部が周辺の地中の温度に比して異常な高温になっていないことが定められている。 | J36: ③ 廃止の基準として、最終処分場の外に悪臭が発散しないように必要な措置が講じられていることが定められている。 | K36: ④ 廃止後は、廃棄物が地下にある土地であって土地の形質の変更により生活環境保全上の支障が生じるおそれがある区域として、指定区域に指定される。 | L36: ⑤ 廃止後は、浸出液処理施設の機能の状態を定期的に点検し、異常を認めた場合には、速やかに必要な措置を講じる必要がある。 | M36: 最終処分場・浸出水

Sheet R5(令和5年度)問題・選択肢
A1: 問題ID | B1: 設問番号 | C1: 大分類(ブロック) | D1: サブジャンル | E1: 公式正答 | F1: 問題のテーマ・内容概要 | G1: 問題文 | H1: 選択肢① | I1: 選択肢② | J1: 選択肢③ | K1: 選択肢④ | L1: 選択肢⑤ | M1: 出題論点（細目）
A2: R5-01 | B2: Ⅲ-1 | C2: 建築環境・設備・建築物衛生管理 | D2: 光・音 | E2: 4 | F2: 北緯35度の日射及び日射調整に関する記述 | G2: 北緯35度の地点の日射及び日射調整に関する次の記述のうち，最も不適切なものはどれか。 | H2: ① 冬至の水平面の終日日射量は，夏至の南鉛直面の終日日射量に比較して多い。 | I2: ② 大気透過率が大きいほど，直達日射が強く，逆に天空日射が弱くなる。 | J2: ③ 東西鉛直面の日射は，日の出・日没付近の，太陽高度の低い状況に対応しているので，日射の調整には庇以外のブラインドなどが必要となる。 | K2: ④ 北鉛直面は，年間を通じて直達日射を受けない。 | L2: ⑤ 南鉛直面の終日日射量は，日射を遮蔽したい夏至のときに最小となる。 | M2: 日照・日射・採光
A3: R5-02 | B3: Ⅲ-2 | C3: 建築環境・設備・建築物衛生管理 | D3: 熱・湿気 | E3: 3 | F3: 建物の伝熱（熱伝導率・断熱材・対流熱伝達率等）に関する記述 | G3: 建物の伝熱に関する次の記述のうち，最も不適切なものはどれか。 | H3: ① 鋼，コンクリートなど密度が1,000kg／m³以上の大きい建築材料は，構造部材として使用される例が多いが，これらの熱伝導率は概ね1W／（m・K）以上で大きく，熱を通しやすい。 | I3: ② 性能の高い断熱材を作るには，固体内部に大量の気体を含み，それらをなるべく微細な空隙に封じ込めるなどして，その流動を抑制する必要がある。 | J3: ③ 屋外風速が3ｍ／ｓの場合，外壁の屋外側の対流熱伝達率は，室内側の対流熱伝達率の値よりも小さい。 | K3: ④ 日射遮蔽係数は，厚さ3ｍｍの透明ガラスの日射熱取得率を基準に各種材料の日射熱取得率を表した値であるため，この値が小さい方が日射遮蔽効果は高い。 | L3: ⑤ 中空層の熱抵抗は，その厚さが2〜5ｃｍ程度までは，厚さを増すほど熱抵抗は増大するが，それ以上ではほとんど変化しない。 | M3: 伝熱・断熱
A4: R5-03 | B4: Ⅲ-3 | C4: 建築環境・設備・建築物衛生管理 | D4: 光・音 | E4: 1 | F4: 視覚・採光基準・直接グレア・明視条件に関する記述 | G4: 光環境に関する次の記述のうち，最も不適切なものはどれか。 | H4: ① ヒトの視覚において，暗所視では，比視感度が最大になる波長が長い方にずれる。 | I4: ② ヒトの視覚において，明順応に比べて，暗順応は時間がかかる。 | J4: ③ 建築基準法における教室及び保育室の採光に有効な窓の基準開口率は，1／5である。 | K4: ④ 直接グレアの防止の基本は，前方視野角の60°以内に高輝度光源を露出させないことである。 | L4: ⑤ 照明設計における明視の条件には，対象の大きさ，対比の大きさ，明るさが含まれる。 | M4: 照明・光環境
A5: R5-04 | B5: Ⅲ-4 | C5: 建築環境・設備・建築物衛生管理 | D5: 光・音 | E5: 5 | F5: 点光源による水平面照度の計算（EA／EBの比） | G5: 下図に示すように光度1,000cdの点光源がある。その直下2ｍの位置にある床上の点Ａの水平面照度をEA［lx］とする。また，点Ａから水平に２ｍ離れた位置の点Ｂの水平面照度をEB［lx］とする。このとき，EA／EBの値に最も近いものはどれか。ただし，この点光源の配光特性は一様であり，水平面照度は壁面等の反射の影響は受けないものとする。 | H5: ① 0.35 | I5: ② 0.71 | J5: ③ 1.00 | K5: ④ 1.41 | L5: ⑤ 2.83 | M5: 照明・光環境
A6: R5-05 | B6: Ⅲ-5 | C6: 建築環境・設備・建築物衛生管理 | D6: 換気・室内空気 | E6: 3 | F6: 室内空気汚染（粉じん・CO2許容濃度・CO発生等）に関する記述 | G6: 室内の空気汚染に関する次の記述のうち，最も不適切なものはどれか。 | H6: ① 粉じんは１〜２μm以下のものが肺胞内に留まって健康被害を及ぼすと考えられていることから，直径10μm以下の粉塵が規制対象となっている。 | I6: ② 必要換気量は室内の汚染物質発生量に対して比例するので，１人当たりm³/hや床面積１m²当たりm³/hのように表示されることが多い。 | J6: ③ 建築基準法や建築物環境衛生管理基準では室内環境における二酸化炭素の許容濃度は1,000ppmであるのに対して，労働環境における二酸化炭素の許容濃度は1,500ppmである。 | K6: ④ 石油ストーブでは，酸素濃度が21%から19%に低下すると，不完全燃焼により急速に一酸化炭素が発生する。 | L6: ⑤ 建材に示されるホルムアルデヒド放散速度とは，建材1m²から１時間当たり放散されるホルムアルデヒド重量を意味する。 | M6: 室内空気質・健康影響・衛生動物
A7: R5-06 | B7: Ⅲ-6 | C7: 建築環境・設備・建築物衛生管理 | D7: 光・音 | E7: 5 | F7: 騒音（屈曲振動・NC値・環境基準・SN比）に関する記述 | G7: 騒音に関する次の記述のうち，最も不適切なものはどれか。 | H7: ① 単一壁に斜めに入射する音波によって，壁体が屈曲振動を起こして透過損失が低下することがある。 | I7: ② 室内騒音の許容値は，騒音レベルLpA［dB］で表した場合の値は，NC値より５〜10大きい。 | J7: ③ 主として住居の用に供せられる地域に対する騒音の環境基準は，昼間55dB以下，夜間45dB以下とされている。 | K7: ④ SN比は，測定対象音のレベル（S［dB］）と暗騒音のレベル（N［dB］）の差（S−N）によって求めることができる。 | L7: ⑤ 室内騒音の許容値は，レストラン，美術館，音楽教室の順で大きくなる。 | M7: 音環境
A8: R5-07 | B8: Ⅲ-7 | C8: 建築環境・設備・建築物衛生管理 | D8: 給排水・防災 | E8: 1 | F8: 水配管システム（三方弁制御・直管圧力損失・ポンプ揚程等）に関する記述 | G8: 水配管システムに関する次の記述のうち，最も不適切なものはどれか。 | H8: ① 三方弁による負荷制御は，負荷が減少すると配管水流量も減少するため，ポンプ動力を節減できる。 | I8: ② 流体が管の断面を充満して流れる場合の直管の圧力損失は，摩擦係数，管の長さ，流体の密度及び流速の２乗に比例し，管の内径に反比例する。 | J8: ③ 開放回路のポンプ揚程は，循環の摩擦損失のほかに押し上げ揚程が加わるので，密閉式に比べてポンプ動力が大きくなる。 | K8: ④ リバースリターン方式は，ファンコイルユニットや放熱器など，同一機種が広い区域に多数連続して設置されるような場合に有効である。 | L8: ⑤ 普通の屋内配管では，浸食による腐食を防ぐための管内流速を一般に2.0m／s以下としている。 | M8: 給水・給湯
A9: R5-08 | B9: Ⅲ-8 | C9: 建築環境・設備・建築物衛生管理 | D9: 空調 | E9: 2 | F9: 外気負荷（顕熱負荷および潜熱負荷）の計算 | G9: 次の条件で冷房している室の外気負荷に関して，顕熱負荷と潜熱負荷の組合せとして，最も適切なものはどれか。 条件： 空気密度：1.2 kg/m³，乾き空気の定圧比熱：1.0 kJ/(kg・K) 外気導入量：400 m³/h，水の蒸発潜熱：2,500 kJ/kg 外気温度：34.0 ℃，室内空気温度：26.0 ℃ 外気絶対湿度：24 g/kg(DA)，室内絶対湿度：12 g/kg(DA) | H9: ① 1,067 W 1,112 W | I9: ② 1,067 W 4,000 W | J9: ③ 3,840 W 14,400 W | K9: ④ 4,000 W 1,067 W | L9: ⑤ 4,000 W 1,112 W | M9: 空調計算（負荷・空気線図・冷凍サイクル）
A10: R5-09 | B10: Ⅲ-9 | C10: 建築環境・設備・建築物衛生管理 | D10: 空調 | E10: 4 | F10: 除湿装置（冷却式・吸収式・吸着式・圧縮式）の原理に関する記述 | G10: 除湿装置に関する次の記述のうち，最も不適切なものはどれか。 | H10: ① 冷却式除湿装置は，処理空気の温度低下と相対湿度の上昇を伴うため，これらが問題となる場合は，冷却除湿後の空気を加熱（再熱）する必要がある。 | I10: ② 吸収式（湿式）除湿装置は，近年は殺菌性を要求される一部食品用途以外はあまり使用されない。 | J10: ③ 吸着式除湿装置は，水分を吸着する性質を持つシリカゲル，活性アルミナ，合成ゼオライト，活性炭などの吸着剤を利用したものである。 | K10: ④ 吸収式（湿式）除湿装置は，ほかの方式に比べて機構が簡単で，安全で金属腐食の問題も少ない。 | L10: ⑤ 圧縮式除湿装置は，空気を圧縮することによって水蒸気の分圧を増加させ，水蒸気の飽和点を超えさせて凝縮分離する方式であり，設備費及び運転費が高くなる。 | M10: 空調機器・ダクト・熱源
A11: R5-10 | B11: Ⅲ-10 | C11: 建築環境・設備・建築物衛生管理 | D11: 給排水・防災 | E11: 3 | F11: 給水方式（直結直圧・直結増圧・圧力水槽・高置水槽・ポンプ直送）に関する記述 | G11: 給水方式に関する次の記述のうち，最も不適切なものはどれか。 | H11: ① 水道直結直圧方式の採用は，夏場など水圧が低くなる時期の水道本管の圧力で決定する必要がある。 | I11: ② 水道直結増圧方式は，供給される水道水の水質劣化や水槽清掃等の衛生上の問題がない上に，省エネルギー効果も期待できる。 | J11: ③ 圧力水槽方式は，水道本管の圧力により圧力水槽内の空気を圧縮・加圧して給水する方式である。 | K11: ④ 高置水槽方式は，給水圧力がほとんど一定である。 | L11: ⑤ ポンプ直送方式は，ポンプやポンプ制御の費用を考えると，小規模建築では設備費が割高になる。 | M11: 給水・給湯
A12: R5-11 | B12: Ⅲ-11 | C12: 建築環境・設備・建築物衛生管理 | D12: 空調 | E12: 4 | F12: 吹出口（スロット型・アネモ型・パン型・ノズル型等）の特性に関する記述 | G12: 吹出口に関する次の記述のうち，最も適切なものはどれか。 | H12: ① スロット型吹出口からの気流は，線源から三次元的に広がる噴流となる。 | I12: ② アネモ型吹出口は，誘引比が小さく拡散性が低いため，コールドドラフトが生じやすい。 | J12: ③ パン型吹出口は，冷房時は下向き吹き出し，暖房時は水平吹き出しが一般的である。 | K12: ④ ノズル型吹出口で，側壁上部から水平に吹き出す場合，暖房時は居住域に滞留域が生じやすい。 | L12: ⑤ 長方形の吹出口からの気流は，アスペクト比（縦横比）が大きいときは円状から円すい状に広がる。 | M12: 空調機器・ダクト・熱源
A13: R5-12 | B13: Ⅲ-12 | C13: 建築環境・設備・建築物衛生管理 | D13: 給排水・防災 | E13: 5 | F13: 大便器の給水方式（洗浄弁・ロータンク）および洗浄方式に関する記述 | G13: 大便器に関する次の記述のうち，最も不適切なものはどれか。 | H13: ① 洗浄弁方式による給水は，最低必要水圧が70kPaである。 | I13: ② ロータンク方式による給水は，最低必要水圧が30kPaである。 | J13: ③ 洗浄方式の分類におけるサイホン式は，洋風便器のみで使用されており，溜水面が広く，汚れにつきにくい。 | K13: ④ 洗浄弁方式は，連続して頻繁に使用される建物に最適である。 | L13: ⑤ 洗浄方式の分類における洗落とし式は，主に和風便器に使用されており，便鉢の水がたまるところに汚物を一時ためて流し出すが，水たまりが浅いため臭気の発散が多い。 | M13: 排水・通気・衛生器具
... A36: R5-35 | B36: Ⅲ-35 | C36: 廃棄物管理 | D36: 最終処分場・浸出水 | E36: 4 | F36: 最終処分場の浸出水処理に関する処理項目と処理方式の組合せ | G36: 最終処分場の浸出水処理に関する処理項目と処理方式の組合せとして，最も不適切なものはどれか。 | H36: ① カルシウムイオン − アルカリ凝集沈殿法 | I36: ② SS − 凝集沈殿法 | J36: ③ ダイオキシン類 − 砂ろ過法 | K36: ④ 塩化物イオン − 精密ろ過法 | L36: ⑤ ふっ素・ほう素 − キレート吸着法 | M36: 最終処分場・浸出水

Sheet R4(令和4年度)問題・選択肢
A1: 問題ID | B1: 設問番号 | C1: 大分類(ブロック) | D1: サブジャンル | E1: 公式正答 | F1: 問題のテーマ・内容概要 | G1: 問題文 | H1: 選択肢① | I1: 選択肢② | J1: 選択肢③ | K1: 選択肢④ | L1: 選択肢⑤ | M1: 出題論点（細目）
A2: R4-01 | B2: Ⅲ-1 | C2: 建築環境・設備・建築物衛生管理 | D2: 光・音 | E2: 4 | F2: 天空日射、日照率、南中時、低鉄分ガラスおよび温室効果に関する記述 | G2: 日照・日射に関する次の記述のうち、最も不適切なものはどれか。 | H2: ① 日射が大気中で散乱されたのち、全天空から地表に到達する成分を天空日射量又は拡散日射量という。 | I2: ② 日照時間の可照時間に対する比を百分率で表したものを日照率という。 | J2: ③ 日本では東経135°（明石）を日本中央標準時の拠点に定めているが、東京は明石よりも早く南中時を迎える。 | K2: ④ 低鉄分ガラスは日射透過率が低い。 | L2: ⑤ 大気中の水蒸気や炭酸ガス、雲などの長波長放射を吸収する特性が、大気の温室効果の原因となっている。 | M2: 日照・日射・採光
A3: R4-02 | B3: Ⅲ-2 | C3: 建築環境・設備・建築物衛生管理 | D3: 光・音 | E3: 5 | F3: 光束法による机上面照度500lx確保のための必要灯数計算 | G3: 床面積が50m²で、机上面照度500lxを確保するには、1灯当たりの光束が2,500lmのランプが何灯必要か。光束法により求めた灯数で最も近い値はどれか。ただし、保守率0.7、照明率0.7とする。 | H3: ① 8灯 | I3: ② 11灯 | J3: ③ 14灯 | K3: ④ 15灯 | L3: ⑤ 21灯 | M3: 照明・光環境
A4: R4-03 | B4: Ⅲ-3 | C4: 建築環境・設備・建築物衛生管理 | D4: 熱・湿気 | E4: 3 | F4: 建築材料の熱伝導率の大きさ順並べ替え | G4: 次のa〜eの建築材料の熱伝導率 [W/(m・K)] について、値の大きいものから順に並べたものはどれか。 a 土壁 b ステンレス鋼 c せっこうボード d グラスウール断熱材16K相当 e コンクリート | H4: ① b, a, c, d, e | I4: ② b, a, e, c, d | J4: ③ b, e, a, c, d | K4: ④ e, b, a, c, d | L4: ⑤ e, b, a, d, c | M4: 伝熱・断熱
A5: R4-04 | B5: Ⅲ-4 | C5: 建築環境・設備・建築物衛生管理 | D5: 温熱・省エネ指標 | E5: 2 | F5: PMV、PPD、新有効温度(ET*)、体温調節機構および不感蒸せつ | G5: 人体の熱収支及び温熱感覚指標に関する次の記述のうち、最も不適切なものはどれか。 | H5: ① 予測平均温冷感申告PMVと予測不満足率PPDはISOにおける標準的温熱感覚指標として採用されており、−0.5≦PMV≦0.5、PPD≦10%が推奨範囲とされている。 | I5: ② 予測平均温冷感申告PMVは新有効温度ET*よりも暑熱環境評価を正確に行うことができると考えられている。 | J5: ③ 体温調整機構において、皮膚血流の調整によるコア・シェル部の大きさ変化で体温調整が可能な領域を中性温域という。 | K5: ④ 各種作業時の代謝量はmetを単位として表すが、1metは体表面積当たりの椅座安静状態での代謝量であり58.2W/m²である。 | L5: ⑤ 発汗していない状態でも、絶えず人体の皮膚や粘膜からは水分蒸発による放熱が起きており、これを「不感蒸せつ」という。 | M5: 温熱環境・温熱指標
A6: R4-05 | B6: Ⅲ-5 | C6: 建築環境・設備・建築物衛生管理 | D6: 光・音 | E6: 2 | F6: 残響時間、音波の回折、音調(pitch)、可聴周波数範囲およびマスキング効果 | G6: 音波と聴覚に関する次の記述のうち、最も不適切なものはどれか。 | H6: ① 残響時間は室の容積が大きいほど長くなり、吸音する材料や物体が多いほど短くなる。 | I6: ② 音波の回折による減衰は波長が物体の寸法に比べ、長い場合は大きく、短い場合は小さい。 | J6: ③ 連続音の調子（pitch）は主として周波数に関係し、周波数の小さい音は低く感じる。 | K6: ④ 音として聞こえる周波数の範囲は、その強さによって変わるが、大体20〜20,000Hzである。 | L6: ⑤ ある音を聞こうとするとき、騒音が同時に存在すると、非常に聞きにくくなることをマスキング効果と呼ぶ。 | M6: 音環境
A7: R4-06 | B7: Ⅲ-6 | C7: 建築環境・設備・建築物衛生管理 | D7: 熱・湿気 | E7: 3 | F7: 結露の定義、断熱材の配置、防湿層の位置、絶対湿度および二重ガラスサッシ | G7: 結露とその対策に関する次の記述のうち、最も不適切なものはどれか。 | H7: ① 室内の温度の高い湿り空気が、その空気の露点温度以下の冷たい壁や天井に触れ、水蒸気が凝集する現象のことを結露という。 | I7: ② 断熱材貼付により断熱材の高温側は結露しにくくなり、低温側は結露しやすくなる。 | J7: ③ 外壁において、防湿層を断熱層の屋外側に設けることは、内部結露を防止する効果がある。 | K7: ④ 絶対湿度は気密に仕切られていない限り、暖房室、非暖房室で同じになる傾向にあるので、室温の低い室内で結露が発生しやすい。 | L7: ⑤ 窓ガラスの室内側にカーテンを設けることは、冬期におけるガラス面の結露の防止対策として期待できない。 | M7: 結露・湿気・湿り空気
A8: R4-07 | B8: Ⅲ-7 | C8: 建築環境・設備・建築物衛生管理 | D8: 換気・室内空気 | E8: 2 | F8: トレーサーガス法（定常放出法、減衰法）の原理および適用条件 | G8: 室内空間において、瞬間一様拡散が仮定できる状況下で人為的にガスを発生させ、その濃度を測定するトレーサーガス法に関する次の記述のうち、最も不適切なものはどれか。 | H8: ① トレーサーガス法は、トレーサーガスが空間の壁などに吸われやすかったり、吸着したりしないことを仮定している。 | I8: ② トレーサーガス法は、空間の開口部や隙間が数多く分散しており、そこでの空気の流出入が不明確であるような自然換気の測定には用いることができない。 | J8: ③ トレーサーガスには、空気と比重が比較的近く、濃度測定が簡易なガスが用いられる。 | K8: ④ トレーサーガスを空間内に一定割合で人為的に連続放出し、その定常状態の濃度を測定することで、換気量を得ることができる。 | L8: ⑤ トレーサーガスを空間内に放出し、均一な濃度分布を達成した後の濃度変化を測定することで、換気量を得ることができる。 | M8: 換気・通風
A9: R4-08 | B9: Ⅲ-8 | C9: 建築環境・設備・建築物衛生管理 | D9: 換気・室内空気 | E9: 1 | F9: 定常状態の質量流量、温度差換気、風圧換気および中性帯位置の基本特性 | G9: 空気流動に関する次の記述のうち、最も適切なものはどれか。 | H9: ① 定常状態において、外部から室内に流入する空気の質量流量は、室内から外部へ流出する空気の質量流量と同じである。 | I9: ② 冬期において、室内の温度より外気温の方が低い場合、屋内外の温度差によって、上部には外気が流入する力が生じ、下部には室内の空気が流出する力が生じる。 | J9: ③ 風圧力によって換気される場合、その換気量は、外部風向と開口条件が一定ならば、外部風速の平方根に比例する。 | K9: ④ 外気に面して異なる高さに同じ大きさの2つの開口部がある室において、無風の条件で温度差換気を行う場合、換気量は内外温度差の2乗に比例する。 | L9: ⑤ 大きさの異なる上下の2つの開口部を用いて、無風の条件で温度差換気を行う場合、中性帯の位置は、有効開口面積の小さい方の開口部に近づく。 | M9: 換気・通風
A10: R4-09 | B10: Ⅲ-9 | C10: 建築環境・設備・建築物衛生管理 | D10: 温熱・省エネ指標 | E10: 5 | F10: 相当外気温度、ナイトパージ、内耐熱、局所空調および放射熱移動の絶対温度依存性 | G10: 建物の温熱環境に関する次の記述のうち、最も不適切なものはどれか。 | H10: ① 定常状態を想定した日射が当たる外壁では、外気温を相当外気温度に置き換えて計算すれば、日射の影響を考慮した貫流熱量が求められる。 | I10: ② ナイトパージにより冷気を室内に導入し、外気が保持する冷熱を躯体に蓄熱させ、昼間の冷房の用に供することができる。 | J10: ③ 内断熱は蓄熱負荷を小さく抑え、予熱時には、室温及び壁体の室内表面温度を速やかに所定のレベルに到達させることができる。 | K10: ④ アトリウムや大空間などでは、人間が居住する範囲だけを局所的・効果的に空調することが望まれる。 | L10: ⑤ 物体間の放射による熱移動量は、それぞれの物体表面の絶対温度の3乗の差に比例する。 | M10: 温熱環境・温熱指標
A11: R4-10 | B11: Ⅲ-10 | C11: 建築環境・設備・建築物衛生管理 | D11: 給排水・防災 | E11: 4 | F11: 大便器フラッシュバルブ必要圧力、受水槽スペース、逆サイホン防止およびトラップ封水深 | G11: 給排水設備に関する次の記述のうち、最も不適切なものはどれか。 | H11: ① 大便器に使用する洗浄弁（フラッシュバルブ）の必要圧力は、ゲージ圧で0.07MPa以上である。 | I11: ② 受水槽は保守・点検のため、標準的には上部に1m以上、周囲・下部に0.6m以上のスペースを設けなくてはならない。 | J11: ③ 給水系統への逆サイホン作用による汚水の逆流を防止するために、洗面器に吐水口空間（エアギャップ）を設ける。 | K11: ④ 排水トラップの最大封水深は50mmである。 | L11: ⑤ 給水管の圧力損失には、直管による摩擦損失以外に、継手や弁類などによる圧力損失があるが、これらの圧力損失はいずれも流速の2乗に比例して増大する。 | M11: 排水・通気・衛生器具
A12: R4-11 | B12: Ⅲ-11 | C12: 建築環境・設備・建築物衛生管理 | D12: 空調 | E12: 1 | F12: 圧縮式冷凍機のモリエル線図における圧縮過程・蒸発過程および成績係数(COP) | G12: 次の記述の、[ ア ]〜[ ウ ]に入る記号又は数式の組合せとして、最も適切なものはどれか。 「下図のモリエ（モリエル）線図に示す圧縮式冷凍機の冷凍サイクルにおいて、[ ア ] は蒸発過程を、[ イ ] は圧縮過程をそれぞれ示しており、この冷凍機としての理論成績係数は [ ウ ] で表される。」 | H12: ① ア: 1→2, イ: 2→3, ウ: (h2-h1)/(h3-h2) | I12: ② ア: 4→1, イ: 3→4, ウ: (h3-h2)/(h2-h1) | J12: ③ ア: 3→4, イ: 1→2, ウ: (h3-h1)/(h3-h2) | K12: ④ ア: 1→2, イ: 3→4, ウ: (h2-h1)/(h3-h1) | L12: ⑤ ア: 4→1, イ: 2→3, ウ: (h3-h2)/(h3-h1) | M12: 空調計算（負荷・空気線図・冷凍サイクル）
A13: R4-12 | B13: Ⅲ-12 | C13: 建築環境・設備・建築物衛生管理 | D13: 給排水・防災 | E13: 3 | F13: 防煙区画、自然排煙、水平区画面積上限（500㎡）および排煙ダクト工事 | G13: 排煙設備に関する次の記述のうち、最も不適切なものはどれか。 | H13: ① 防煙区画は、煙感知器の作動を確実にするような効果も期待できる。 | I13: ② 自然排煙は、一般の事務室のように天井高さが低く、換気経路も明確でない場合には有効な排煙効果は期待できない。 | J13: ③ 防煙区画（水平区画）の面積は、最大100m²である。 | K13: ④ 機械排煙設備の手動開放装置を壁面に設ける場合は、床面より0.8〜1.5mの高さとする。 | L13: ⑤ 天井チャンバ方式の排煙設備は、同一排煙区画内であれば、間仕切り変更に対して排煙ダクト工事が不要となる。 | M13: 防災・排煙・消火
A14: R4-13 | B14: Ⅲ-13 | C14: 建築環境・設備・建築物衛生管理 | D14: 空調 | E14: 5 | F14: 室内の顕熱負荷6.6kWにおける空調機吹出し風量[m³/h]および除湿量[kg/h]計算 | G14: 室内空気を空調機の熱交換器に通して冷却・減湿（除湿）した。室内の顕熱負荷が6.6kWのとき、空調機の吹出し風量と除湿量との組合せとして、最も適切なものは次のうちどれか。ただし、与条件は以下とする。 室内空気（空調機の入口）条件：温度26℃、絶対湿度0.011 kg/kg(DA) 吹出し（空調機の出口）条件：温度15℃、絶対湿度0.009 kg/kg(DA) 空気の比熱：1.2 kJ/(m³・K) 空気の比体積（比容積）：0.83 m³/kg(DA) | H14: ① 吹出し風量: 550 m³/h, 除湿量: 1.2 kg/h | I14: ② 吹出し風量: 1320 m³/h, 除湿量: 2.2 kg/h | J14: ③ 吹出し風量: 1320 m³/h, 除湿量: 3.2 kg/h | K14: ④ 吹出し風量: 1800 m³/h, 除湿量: 3.0 kg/h | L14: ⑤ 吹出し風量: 1800 m³/h, 除湿量: 4.3 kg/h | M14: 空調計算（負荷・空気線図・冷凍サイクル）
A15: R4-14 | B15: Ⅲ-14 | C15: 建築環境・設備・建築物衛生管理 | D15: 換気・室内空気 | E15: 5 | F15: 越冬昆虫侵入メカニズム、クマネズミ駆除、コナヒョウヒダニおよびゴキブリ体内時計 | G15: 建築物におけるねずみ・害虫対策に関する次の記述のうち、最も不適切なものはどれか。 | H15: ① 外気温が低くなると、外壁に内部から伝わる熱や、隙間から漏れる熱を感じて、越冬等の目的で昆虫等が侵入しやすくなる。 | I15: ② ねずみの駆除は、餌を断つこと、通路を遮断すること、巣を作らせないことを基本に進める。 | J15: ③ 居住環境で見られるコナヒョウヒダニやヤケヒョウヒダニは、ヒトを刺したり吸血したりすることはないが、そのふんや死骸は喘息やアトピー性皮膚炎の原因となることがある。 | K15: ④ ゴキブリは、夜間、潜伏場所から出現し、摂食、摂水行動を起こし、体内に組み込まれた体内時計により、約24時間を周期とする行動が見られる。 | L15: ⑤ イエバエ、クロバエ、ニクバエ類等の中・大型のハエ類は、厨芥等の処理がきちんと行われていても、幼虫が発生する。 | M15: 室内空気質・健康影響・衛生動物
A16: R4-15 | B16: Ⅲ-15 | C16: 建築環境・設備・建築物衛生管理 | D16: 換気・室内空気 | E16: 2 | F16: 二面開口住戸における風力換気量[m³/s]の計算 | G16: 下図に示す二面開口住戸の風力換気量に最も近い値はどれか。ただし、外部風速（v）、各開口部の風圧係数（C）、実効面積（αA）は下図に示す値とする。 外部風速 v＝4 m/s 開口部1: α1A1＝2 m², C1＝＋0.6 開口部2: α2A2＝2 m², C2＝−0.3 | H16: ① 5.1 m³/s | I16: ② 5.4 m³/s | J16: ③ 7.6 m³/s | K16: ④ 20.4 m³/s | L16: ⑤ 21.5 m³/s | M16: 換気・通風
A17: R4-16 | B17: Ⅲ-16 | C17: 建築環境・設備・建築物衛生管理 | D17: 建築物衛生法・レジオネラ | E17: 4 | F17: 保健所の役割、免状交付、特定建築物定義および所有者の受任義務 | G17: 建築物における衛生的な環境の確保に関する法律（建築物衛生法）に関する次の記述のうち、最も不適切なものはどれか。 | H17: ① 保健所は、多数の者が使用し、又は利用する建築物の維持管理について、環境衛生上の正しい知識の普及に努めるとともに、環境衛生上の相談に応じ、必要な指導を行う。 | I17: ② 建築物環境衛生管理技術者免状は、厚生労働大臣の登録を受けた者が行う講習会の課程を修了したもの又は、建築物環境衛生管理技術者試験に合格した者に対し、厚生労働大臣が交付する。 | J17: ③ 建築物衛生法が定める「特定建築物」に、病院の用に供される建築物は含まれない。 | K17: ④ 建築物衛生法が定める「特定建築物」は、定められた用途の用に供される部分の延べ面積が2,000平方メートル以上の建築物である。 | L17: ⑤ 特定建築物所有者等は、建築物環境衛生管理技術者免状を有する者を建築物環境衛生管理技術者に選任しなければならない。 | M17: 建築物衛生法・衛生基準
A18: R4-17 | B18: Ⅲ-17 | C18: 建築環境・設備・建築物衛生管理 | D18: 換気・室内空気 | E18: 1 | F18: スギ花粉の粒子径（30μm）、飛散量と気温・湿度の相関、床材の清掃性 | G18: スギ花粉に関する次の記述のうち、最も不適切なものはどれか。 | H18: ① スギ花粉として認識される粒子の大きさは直径約3μmで、ほぼ球状の粒子である。 | I18: ② 花粉飛散数は気温との相関が高く、また、湿度が低下するに従い飛散数は増加し、風速が強くなれば多数の花粉が飛散する。 | J18: ③ 花粉の室内における高さ別落下量は、床面に近いほど多い。 | K18: ④ 床材は堆積花粉の除去のしやすさを考慮すると、毛足の長いカーペットよりフローリングの方が望ましい。 | L18: ⑤ 空中花粉の捕集方法は、単位面積・単位時間内に自然落下する花粉を捕集する「落下法」と 定量の空気中に含まれる花粉を捕集する「体積法」に大別される。 | M18: 室内空気質・健康影響・衛生動物
A19: R4-18 | B19: Ⅲ-18 | C19: 建築環境・設備・建築物衛生管理 | D19: 換気・室内空気 | E19: 3 | F19: 住宅内のカビ栄養源、夏季換気制限、カビの好むpH(酸性〜中性)およびCFU単位 | G19: 室内におけるカビに関する次の記述のうち、最も不適切なものはどれか。 | H19: ① 住宅内の壁紙、塗料、木材のほとんどはカビの栄養源となり、温度、特に湿度条件が整えば増殖する。 | I19: ② 外気の湿度条件としてすでにカビの発生可能な夏期は、換気しても室内はカビの発生可能な状態が続くので、カビの防止には室内の絶対湿度を下げる必要がある。 | J19: ③ カビはpH（水素イオン濃度）では、酸性や中性を好み、アルカリ性では生育しない。 | K19: ④ カビの測定は、培地の準備、捕集（サンプリング）、培養及び計数などを経てカビの汚染度合いを評価する。 | L19: ⑤ カビの数を表す単位としては、CFU（colony forming unit）が用いられ、捕集されたカビが培地の表面で一定の温湿度条件と培養期間において増殖し、肉眼で確認できるような1つの集落（コロニー）を1CFUという。 | M19: 室内空気質・健康影響・衛生動物
... A36: R4-35 | B36: Ⅲ-35 | C36: 廃棄物管理 | D36: 最終処分場・浸出水 | E36: 4 | F36: 最終処分場埋立終了後の維持管理継続（水処理・ガス抜き）および跡地利用 | G36: 一般廃棄物最終処分場及び産業廃棄物管理型最終処分場の埋立終了後の扱いに関する次の記述のうち、最も不適切なものはどれか。 | H36: ① 跡地利用として、太陽光発電を導入した事例がある。 | I36: ② 公園・スポーツ広場・農園等として跡地利用されている。 | J36: ③ 埋立終了後においても、排水処理やガス抜き等の維持管理を継続する必要がある。 | K36: ④ 埋立終了した埋立地は、厚さがおおむね1m以上の土砂及び遮水シートにより開口部を閉鎖する必要がある。 | L36: ⑤ 廃止された最終処分場は、廃棄物処理施設として維持管理を行わなくとも、そのまま生活環境保全上の問題が生じるおそれがない状態である。 | M36: 最終処分場・浸出水

Sheet R3(令和3年度)問題・選択肢
A1: 問題ID | B1: 設問番号 | C1: 大分類(ブロック) | D1: サブジャンル | E1: 公式正答 | F1: 問題のテーマ・内容概要 | G1: 問題文 | H1: 選択肢① | I1: 選択肢② | J1: 選択肢③ | K1: 選択肢④ | L1: 選択肢⑤ | M1: 出題論点（細目）
A2: R3-01 | B2: Ⅲ-1 | C2: 建築環境・設備・建築物衛生管理 | D2: 熱・湿気 | E2: 4 | F2: 湿り空気の全圧、露点温度、絶対湿度、相対湿度および平衡状態に関する正誤判定 | G2: 湿り空気に関する次の記述のうち，最も不適切なものはどれか。 | H2: ① 乾き空気の分圧と水蒸気分圧を加算したものが湿り空気の全圧となる。 | I2: ② 水蒸気の多く含まれている空気ほど，露点温度は高くなる。 | J2: ③ 相対湿度は温度変化の影響を受けるが，絶対湿度は温度変化の影響を受けない。 | K2: ④ 空気中の相対湿度が50%のとき，湿球温度は乾球温度と同じ値になる。 | L2: ⑤ 一定時間に水面から飛び出す水蒸気分子の数と，湿り空気から水面に飛び込む水蒸気分子の数が同数になるとき，これを平衡状態という。 | M2: 結露・湿気・湿り空気
A3: R3-02 | B3: Ⅲ-2 | C3: 建築環境・設備・建築物衛生管理 | D3: 熱・湿気 | E3: 5 | F3: 放射エネルギー、対流熱伝達率、キルヒホッフの法則、水蒸気拡散およびルイスの法則に関する正誤判定 | G3: 伝熱・物質伝達に関する次の記述のうち，最も不適切なものはどれか。 | H3: ① 全ての物体は，絶対温度でない限りその温度に応じた放射エネルギーを出しており，その放射量は絶対温度の4乗に比例する。 | I3: ② 室内の対流熱伝達率は，暖房時の天井面と冷房時の床面は大きく，冷房時の天井面と暖房時の床面は小さい値が用いられる。 | J3: ③ 同一波長に対して放射率と吸収率が等しくなる性質を，キルヒホッフの法則という。 | K3: ④ ドアや襖で仕切られていても水蒸気は容易に隣室に拡散するため，住戸内はほぼ一様な絶対湿度になる。 | L3: ⑤ 濡れた物体表面から周囲空気へ水が蒸発するプロセスは対流熱伝達と相似性があり，これをフィックの法則という。 | M3: 伝熱・断熱
A4: R3-03 | B4: Ⅲ-3 | C4: 建築環境・設備・建築物衛生管理 | D4: 光・音 | E4: 5 | F4: 残響時間、障壁の回折効果、コインシデンス効果、重量床衝撃音および多孔質吸音材に関する正誤判定 | G4: 音環境に関する次の記述のうち，最も不適切なものはどれか。 | H4: ① 音響エネルギー密度が60dBだけ減衰するのに要する時間を残響時間という。 | I4: ② 障壁は，回折による高音域の遮断に対する効果が大きい。 | J4: ③ コインシデンス効果は，音が様々な方向から壁面に入射する場合には広い周波数で発生する。 | K4: ④ 重量衝撃音の低減に対しては，床構造の曲げ剛性や質量が重要で，木造などの軽量床の場合，必要な性能を得ることは困難である。 | L4: ⑤ 多孔質材の吸音機構において，剛壁に直貼りしたときの吸音率は，吸音材の材厚を厚くしても，低音域の吸音率は向上しない。 | M4: 音環境
A5: R3-04 | B5: Ⅲ-4 | C5: 建築環境・設備・建築物衛生管理 | D5: 換気・室内空気 | E5: 2 | F5: 吸込み気流の指向性、換気回数計算、空気寿命・空気余寿命、重力換気および第1種・第2種換気に関する正誤判定 | G5: 換気に関する次の記述のうち，最も不適切なものはどれか。 | H5: ① 給気口周りの気流と排気口周りの気流の様子は大きく異なり，吹出し気流には指向性があるが，吸込み気流には指向性がない。 | I5: ② 30分毎に一度窓を開けて換気を行う場合，換気回数は2回／hとなる。 | J5: ③ 給気口から出た新鮮空気が室内のある点Pに到達するまでの時間を空気齢，ある点Pの空気が排気口に至るまでの時間を空気余命，空気齢と空気余命の和を空気寿命と呼ぶ。 | K5: ④ 重力換気を行う場合，上部と下部の開口のレベル差と建物内外の温度差が大きいほど，換気量は大きくなる。 | L5: ⑤ 手術室やクリーンルームなどのように，周囲から汚染空気が流入してはならない室では，室内圧を周囲より高く保つように第2種機械換気とするか，給気量より排気量の少ない第1種機械換気とする。 | M5: 換気・通風
A6: R3-05 | B6: Ⅲ-5 | C6: 建築環境・設備・建築物衛生管理 | D6: 熱・湿気 | E6: 1 | F6: 各種建築材料（押出発泡ポリスチレン、合板、ガラス、コンクリート、ステンレス鋼）の熱伝導率比較順序の判定 | G6: 次の (a) 〜 (e) の建築材料の熱伝導率 [W/m・K] について，値の小さいものから順に並べたものはどれか。 (a) ガラス (b) コンクリート (c) 合板 (d) ステンレス鋼 (e) 押出発泡ポリスチレン | H6: ① e, c, a, b, d | I6: ② e, a, c, b, d | J6: ③ e, a, c, d, b | K6: ④ c, e, b, a, d | L6: ⑤ c, e, b, d, a | M6: 伝熱・断熱
A7: R3-06 | B7: Ⅲ-6 | C7: 建築環境・設備・建築物衛生管理 | D7: 光・音 | E7: 3 | F7: 日射の波長区分、散乱・天空放射、CO2による吸収、短波長・長波長透過性および実効放射に関する正誤判定 | G7: 日射に関する次の記述のうち，最も不適切なものはどれか。 | H7: ① 日射はその波長によって，200〜380nmの紫外線，380〜780nmの可視線，780〜10⁵nmの赤外線に大別される。 | I7: ② 散乱は放射線が空気粒子により散乱させられる現象で，散乱されたものの約半分は地表に到達し，天空放射と呼ばれる。 | J7: ③ 大気中での日射の吸収は主としてCO2により行われ，水蒸気もわずかながら吸収する。 | K7: ④ 大気は直達・天空放射のような比較的短波長の放射はよく透過するが，地面放射のような長波長の放射はほとんど吸収する。 | L7: ⑤ 地面放射と大気放射の差を実効放射又は夜間放射と呼ぶ。 | M7: 日照・日射・採光
A8: R3-07 | B8: Ⅲ-7 | C8: 建築環境・設備・建築物衛生管理 | D8: 給排水・防災 | E8: 4 | F8: 排煙方式、泡消火設備、補助散水栓、建築基準法・消防法における排煙目的およびスプリンクラー設備に関する正誤判定 | G8: 建物の防災設備に関する次の記述のうち，最も適切なものはどれか。 | H8: ① 特別避難階段の付室の排煙は，自然排煙方式でなければならない。 | I8: ② 泡消火設備は，泡消火剤と水の混合液を泡ヘッドなどの発泡器に送り，空気を吸引して発生させた泡を放射して，泡の冷却作用により消火する設備である。 | J8: ③ 補助散水栓は，消防法によりスプリンクラーヘッドの設置を免除されている未警戒部分を防護するために設置されるもので，アラーム弁の一次側配管から分岐する。 | K8: ④ 建築基準法上の排煙設備は避難安全確保を主目的とし，消防法上の排煙設備は消火活動支援を主目的としている。 | L8: ⑤ スプリンクラー設備では，天井面や壁面に取り付けたヘッドから散水し，その窒息作用により消火する。 | M8: 防災・排煙・消火
A9: R3-08 | B9: Ⅲ-8 | C9: 建築環境・設備・建築物衛生管理 | D9: 換気・室内空気 | E9: 4 | F9: 換気・除湿・室内外温湿度条件に基づく室内水蒸気発生量の定型計算 | G9: 室内外の換気量が50m³/hのときに，室内の絶対湿度が8g/kg(DA)に保たれている状態での室内水蒸気発生量に最も近い値はどれか。ただし，室内は除湿器によって50g/hの除湿がなされており，室温と外気温度は共に20℃，外気絶対湿度が3g/kg(DA)，空気密度 ρ = 1.2 kg(DA)/m³ とする。 | H9: ① 250 [g/h] | I9: ② 258 [g/h] | J9: ③ 300 [g/h] | K9: ④ 350 [g/h] | L9: ⑤ 530 [g/h] | M9: 換気・通風
A10: R3-09 | B10: Ⅲ-9 | C10: 建築環境・設備・建築物衛生管理 | D10: 空調 | E10: 3 | F10: 風量制御、床吹出し空調、Low-eガラスの配置、ヒートポンプ加熱および全熱交換器に関する正誤判定 | G10: 省エネルギーに関する次の記述のうち，最も不適切なものはどれか。 | H10: ① 変風量方式の風量制御は，ダンパ制御より回転数制御の方が省エネルギー効果が大きい。 | I10: ② 床吹出し空調方式では，冷房運転時の吹出し温度が天井吹出し方式より高いので，冷熱源の運転や外気冷房などが効率的に行える。 | J10: ③ 近代的なオフィスビルで，冷房負荷軽減のためLow-eガラスを複層ガラスの室内側に採用することが多い。 | K10: ④ ヒートポンプ加熱は熱源から得た熱を利用し，暖房負荷より少ない投入エネルギーで暖房ができる。 | L10: ⑤ 全熱交換器は，空調の外気負荷のピークロードの減少により，冷凍機・ボイラ・付属機器の容量を小さくできる。 | M10: 空調方式・省エネルギー
A11: R3-10 | B11: Ⅲ-10 | C11: 建築環境・設備・建築物衛生管理 | D11: 給排水・防災 | E11: 5 | F11: 配管流速、ポンプ全揚程、高層建築の圧力ゾーニング、水道直結直圧方式および飲料用開放水槽の保有距離に関する正誤判定 | G11: 給水設備に関する次の記述のうち，最も不適切なものはどれか。 | H11: ① 配管に流れる流量から，流水音やウォーターハンマーを生じさせないため，管内の流速は1.5〜2.0m/s以下が望ましい。 | I11: ② 揚水ポンプの全揚程は，実揚程と摩擦損失水頭と速度水頭の総和以上となる必要がある。 | J11: ③ 高層建築では，低層の各階の分岐管に減圧弁を設置する各階減圧弁方式と呼ばれる圧力ゾーニングの方式がある。 | K11: ④ 水道直結直圧方式は，高圧配水システムを採用している水道事業体では，4〜5階程度の建物まで採用されている。 | L11: ⑤ 飲料用開放水槽の設置においては，隣接する他の機器や壁との距離は30cm以上確保する必要がある。 | M11: 給水・給湯
A12: R3-11 | B12: Ⅲ-11 | C12: 建築環境・設備・建築物衛生管理 | D12: 空調 | E12: 2 | F12: エアフロー・ウィンドウ、デシカント空調、スクリュー式冷凍機、ビル用マルチパッケージおよび氷蓄熱に関する正誤判定 | G12: 空気調和設備に関する次の記述のうち，最も不適切なものはどれか。 | H12: ① エアフローウィンドウは，ペリメータ処理方式と異なりファンコイルユニットや水配管を室内に持ち込まないので，施工や維持管理の面でメリットがある。 | I12: ② デシカント空調における除湿は，空気を冷却することで，水を凝縮して分離している。 | J12: ③ 中小規模の建物ではスクリュー式冷凍機が多く用いられる。 | K12: ④ ビル用マルチパッケージ方式において外調機を設ける場合，適用するフィルタの性能は，目的とする室の空気質，室の発じん量，外気の空気質から決定する。 | L12: ⑤ 熱源によって生成された冷温熱を蓄える蓄熱槽のうち，氷蓄熱では，同じ熱量なら水蓄熱より容積が小さくて済む。 | M12: 空調方式・省エネルギー
A13: R3-12 | B13: Ⅲ-12 | C13: 建築環境・設備・建築物衛生管理 | D13: 給排水・防災 | E13: 1 | F13: バリアフリー新法における衛生器具設置基準、小便器節水量、大便器洗浄弁最高給水圧力、ハンドシャワーのバキュームブレーカーおよび耐圧試験水圧に関する正誤判定 | G13: 衛生器具に関する次の記述のうち，最も不適切なものはどれか。 | H13: ① バリアフリー新法により，デパートなど不特定多数の者が利用する施設等では，オストメイトと床置き，又は受け口の高さが500mm以下の壁掛け式の小便器を1つずつ以上設ける必要がある。 | I13: ② 小便器は，従来4L/回の洗浄水量であったが，近年は1.2L/回程度に節水されている。 | J13: ③ 大便器洗浄弁を使用する際の最高給水圧力は，400kPaまでとすることが望ましい。 | K13: ④ 浴室のハンドシャワーが浴槽内に水没した場合に，浴槽内等の汚れた水が逆流して上水を汚染しないよう，必ずバキュームブレーカーを取り付ける。 | L13: ⑤ JISによる給水栓の場合，1.75MPaの試験水圧に耐えるものでなければならない。 | M13: 排水・通気・衛生器具
... A36: R3-35 | B36: Ⅲ-35 | C36: 廃棄物管理 | D36: 災害廃棄物・事業方式・統計・管理票 | E36: 1 | F36: 災害廃棄物の定義・処理主体（市町村が主体）、災害廃棄物対策指針、処理計画、仮置場確保および災害廃棄物処理支援ネットワークに関する正誤判定 | G36: 災害廃棄物に関する次の記述のうち，最も不適切なものはどれか。 | H36: ① 災害廃棄物は，自然災害に直接起因して発生する廃棄物のうち，自然環境保全上の支障へ対処するため，市区町村等がその処理を実施するものである。 | I36: ② 災害廃棄物対策指針は，環境省が災害廃棄物処理計画の策定及び災害廃棄物対策を実施する際の参考となる災害廃棄物対策の基本的事項を取りまとめたものである。 | J36: ③ 災害廃棄物処理計画は，地方公共団体が災害廃棄物を適正かつ円滑・迅速に処理するために必要な事項を整理したものである。 | K36: ④ 災害廃棄物処理計画には，発災時における仮置場の確保，分別自体の徹底，処理先の確保等の必要事項を取りまとめる。 | L36: ⑤ 災害廃棄物処理支援ネットワークは，我が国の災害廃棄物対応力を向上させるため，災害廃棄物対策のエキスパートで構成される組織である。 | M36: 災害廃棄物・指定廃棄物

Sheet R2(令和2年度)問題・選択肢
A1: 問題ID | B1: 設問番号 | C1: 大分類(ブロック) | D1: サブジャンル | E1: 公式正答 | F1: 問題のテーマ・内容概要 | G1: 問題文 | H1: 選択肢① | I1: 選択肢② | J1: 選択肢③ | K1: 選択肢④ | L1: 選択肢⑤ | M1: 出題論点（細目）
A2: R2-01 | B2: Ⅲ-1 | C2: 建築環境・設備・建築物衛生管理 | D2: 換気・室内空気 | E2: 4 | F2: 二向開口住戸における風上・風下開口部の合成相当開口面積計算 | G2: 二面開口住戸の通風・換気性能について，風上開口の相当開口面積 α1A1，風下開口の相当開口面積 α2A2, α3A3 が下図に示す値である場合，これらを合成した相当開口面積（合成 αA）に最も近い値はどれか。［図：α1A1＝100cm²，α2A2＝50cm²，α3A3＝50cm²］ | H2: ① 14 [cm²] | I2: ② 24 [cm²] | J2: ③ 33 [cm²] | K2: ④ 71 [cm²] | L2: ⑤ 135 [cm²] | M2: 換気・通風
A3: R2-02 | B3: Ⅲ-2 | C3: 建築環境・設備・建築物衛生管理 | D3: 光・音 | E3: 5 | F3: 明順応・暗順応、直接グレア防止、教室の採光有効面積および暗所視の比視感度最大波長に関する正誤判定 | G3: 光環境に関する次の記述のうち，最も不適切なものはどれか。 | H3: ① ヒトの視覚において，明順応に比べて，暗順応は時間がかかる。 | I3: ② 直接グレアの防止の基本は，前方視野角の30°以内に高輝度光源を露出させないことである。 | J3: ③ 建築基準法における教室（幼稚園・小学校・中学校・高等学校又は中等教育学校）の採光のための窓，その他の開口部の採光に有効な部分の面積は，床面積の1／5以上である。 | K3: ④ 照明設計における明視の条件は，視角が大きいこと，対比の大きいこと，動きのないこと，明るいことであるが，特に明るさが重要である。 | L3: ⑤ ヒトの視覚において，暗所視では，比視感度が最大になる波長が長い方にずれる。 | M3: 照明・光環境
A4: R2-03 | B4: Ⅲ-3 | C4: 建築環境・設備・建築物衛生管理 | D4: 温熱・省エネ指標 | E4: 2 | F4: 居室の断熱性能、暖房時の室内空気・壁表面温度差および外断熱蓄熱効果に関する正誤判定 | G4: 住宅の居室の冬期室内温熱環境及び間欠暖房に関する次の記述のうち，最も不適切なものはどれか。 | H4: ① 同じ熱容量の場合，断熱性能を向上させると，暖房停止後の室温低下が穏やかとなる。 | I4: ② 居室の断熱性能が低いと，暖房時の室内空気温度と壁の室内側表面温度の差が小さくなる。 | J4: ③ 同じ熱容量の場合，断熱性能を向上させると，立上り負荷が小さくなる。 | K4: ④ 居室の断熱性能が低いと，より多量の熱量を投入する必要が生じ，天井付近に高温の空気が停滞して上下温度差がつきやすくなる。 | L4: ⑤ コンクリートなどの熱容量の大きな材料で作られた構造体の蓄熱効果を活用するためには，外断熱でなければならない。 | M4: 温熱環境・温熱指標
A5: R2-04 | B5: Ⅲ-4 | C5: 建築環境・設備・建築物衛生管理 | D5: 光・音 | E5: 3 | F5: 板振動型・多孔質型吸音機構、複層ガラスの遮音特性およびコインシデンス効果に関する正誤判定 | G5: 各種材料の遮音性能に関する次の記述のうち，最も不適切なものはどれか。 | H5: ① 板振動型吸音機構では，低音域の共振周波数付近で吸音率は高く，中高音域の吸音率は小さい。 | I5: ② 多孔質型吸音機構では，波長の長い低音に対して吸音率を高めるためには，材料を厚くするか剛壁から離して設置する必要がある。 | J5: ③ ガラスの厚さを合計して6mmとし，面密度を一定とした場合，複層ガラス窓は同一面密度の一重ガラス窓と比べて遮音性能が高い。 | K5: ④ 壁に音が斜め入射する場合，壁の屈曲波の周波数と一致すると，壁が大きく振動して音が透過する。これをコインシデンス効果といい，壁厚が厚い場合は，その効果の対象となる周波数が中低音域まで下がるので，対策を要する場合がある。 | L5: ⑤ 二重壁では，低周波部分で透過損失の著しい落ち込みが見られ，この現象を低音域共鳴透過と呼ぶ。 | M5: 音環境
A6: R2-05 | B6: Ⅲ-5 | C6: 建築環境・設備・建築物衛生管理 | D6: 熱・湿気 | E6: 1 | F6: 夏型結露、北側非暖房室への水蒸気拡散、内部結露・表面結露の発生防止対策に関する正誤判定 | G6: 建物の結露に関する次の記述のうち，最も不適切なものはどれか。 | H6: ① 夏型結露とは，高温多湿の空気が低温度の空間に流れ込んで，相対湿度を上昇させることにより，発生する結露であるため，換気を十分にとることが望ましい。 | I6: ② 家族が集う南側居室から暖房を行っていない北側居室へ水蒸気が拡散した場合，温度が低い外壁内表面や空気流動が少ない押入の中や壁に密着した家具の裏面等に結露が生じる恐れが多い。 | J6: ③ 内部結露の防止には，壁体内に水蒸気が侵入しないようにすることが第一であり，壁体内に防湿層を入れる場合には，温度の高い断熱材の室内側に配置しなければならない。 | K6: ④ 内部結露の防止には，壁体内部の水蒸気を外気に逃がすための通気層を断熱層外側に設ける構法を採用するとよい。 | L6: ⑤ 表面結露の防止には，「室内における水蒸気発生の抑制」，「換気による室内絶対湿度の低下」，「外断熱強化による室内側表面温度の上昇」，「非暖房室などへの水蒸気侵入の抑制」などが考えられる。 | M6: 結露・湿気・湿り空気
A7: R2-06 | B7: Ⅲ-6 | C7: 建築環境・設備・建築物衛生管理 | D7: 換気・室内空気 | E7: 5 | F7: 定常状態における汚染物質濃度式、環境衛生基準数値（CO2, ホルムアルデヒド, CO）および必要換気量基準に関する正誤判定 | G7: 室内の空気汚染に関する次の記述のうち，最も不適切なものはどれか。 | H7: ① 汚染物質が瞬時に一様に拡散する場合の定常状態における室内空気汚染物質気中濃度は，その部屋の汚染物質の発生量，換気量及び外気に含まれる汚染物質濃度によって決まり，部屋の容積には関係しない。 | I7: ② 二酸化炭素濃度基準は，建築物環境衛生管理基準では，1,000ppm以下である。 | J7: ③ シックハウス症候群を防止することを目的に，その原因とされる化学物質について，厚生労働省が定めたホルムアルデヒド室内濃度指針値は，100 μg／m³である。 | K7: ④ 一酸化炭素濃度基準は，建築物環境衛生管理基準では，10ppmを許容濃度としており，不完全燃焼に伴って発生することがあるため，中毒事故防止のために室内酸素濃度を下げないことが大切である。 | L7: ⑤ 居室の必要換気量は，一般に室内の酸素濃度を基準にして決められる。 | M7: 室内空気質・健康影響・衛生動物
A8: R2-07 | B8: Ⅲ-7 | C8: 建築環境・設備・建築物衛生管理 | D8: 空調 | E8: 4 | F8: BEMS、コージェネレーション、全熱交換器外気負荷軽減およびエアフローウィンドウ方式に関する正誤判定 | G8: 省エネルギーシステムに関する次の記述のうち，最も不適切なものはどれか。 | H8: ① BEMSとは室内環境とエネルギー性能の最適化を図るためのビル管理システムである。 | I8: ② コージェネレーション方式を採用する際，熱エネルギー消費量と電力消費量のバランスを年間を通じて図る必要がある。 | J8: ③ 全熱交換器を用いて換気を行う場合，外気負荷は全熱交換器の熱回収効率に応じて軽減することができる。 | K8: ④ 事務所の場合，給気のCO2濃度をもとに取入れ外気量を制御することで外気負荷の軽減を図れる。 | L8: ⑤ エアフローウィンドウ方式は，ペリメーターゾーン専用の空調系統が不要で，混合損失がないため，省エネルギー性能が高い。 | M8: 空調方式・省エネルギー
A9: R2-08 | B9: Ⅲ-8 | C9: 建築環境・設備・建築物衛生管理 | D9: 空調 | E9: 2 | F9: 冷房時におけるすきま換気量、温湿度差に基づく顕熱負荷・潜熱負荷計算 | G9: 以下の条件で冷房している室のすきま換気による顕熱負荷，潜熱負荷に最も近い組合せはどれか。 空気密度：1.2 kg/m³，空気定圧比熱：1,000 J/kg・K すきま換気量：36.0 m³/h，水の蒸発熱：2,500 J/g 外気温度：34.3 ℃，外気絶対湿度：0.022 kg/kg(DA) 室内空気温度：26.0 ℃，室内絶対湿度：0.012 kg/kg(DA) | H9: ① 83W / 250W | I9: ② 100W / 300W | J9: ③ 312W / 360W | K9: ④ 412W / 660W | L9: ⑤ 359kW / 1,080kW | M9: 空調計算（負荷・空気線図・冷凍サイクル）
A10: R2-09 | B10: Ⅲ-9 | C10: 建築環境・設備・建築物衛生管理 | D10: 空調 | E10: 5 | F10: 冷却式・吸着式・圧縮式・吸収式除湿装置の特徴と原理比較に関する正誤判定 | G10: 除湿装置に関する次の記述のうち，最も不適切なものはどれか。 | H10: ① 冷却式除湿装置は，機構が簡単で，設備費が安く，空気の露点温度が高い場合に有利である。 | I10: ② 吸着式除湿装置は，水分を吸着する性質をもつシリカゲル，活性アルミナ，合成ゼオライト，活性炭などの吸着剤を利用したものである。 | J10: ③ 圧縮式除湿装置は，空気を圧縮することによって水蒸気の分圧を増加させ，水蒸気の飽和点を超えさせて凝縮分離する方式であり，設備費及び運転費が高くなる。 | K10: ④ 冷却式除湿装置は，処理空気の温度低下と相対湿度の上昇を伴うため，これらが問題となる場合は，冷却除湿後の空気を加熱（再熱）する必要がある。 | L10: ⑤ 吸収式除湿装置は，大がかりな装置になるが，制御しやすいため幅広く使用されている。 | M10: 空調機器・ダクト・熱源
A11: R2-10 | B11: Ⅲ-10 | C11: 建築環境・設備・建築物衛生管理 | D11: 空調 | E11: 2 | F11: 床吹出し空調、ファンコイルユニット、天井放射空調、パッケージ空調および単ダクトVAV方式の比較と正誤判定 | G11: 空調方式に関する次の記述のうち，最も不適切なものはどれか。 | H11: ① 床吹出し空調方式は，床吹出し口の移設・増設を比較的容易に行えるため，パーソナル性に優れている。 | I11: ② ファンコイルユニットは，一般的に除湿と加湿能力を有し，温度と湿度の個別制御性に優れている。 | J11: ③ 天井放射空調方式は，外調システムと組合せて利用される場合が多い。 | K11: ④ パッケージ空調方式は，外気負荷削減のために全熱交換ユニットなどの機器と組合せて用いられる場合が多い。 | L11: ⑤ 単ダクト変風量空調方式は，原則として給気温湿度を一定として，分岐ダクトに設置したVAVユニットにより風量が各々調整される。 | M11: 空調方式・省エネルギー
A12: R2-11 | B12: Ⅲ-11 | C12: 建築環境・設備・建築物衛生管理 | D12: 給排水・防災 | E12: 3 | F12: 通気管の最小管径（30mm/50mm）、伸頂通気管径、排水立管径および地中埋設管径の技術基準に関する正誤判定 | G12: 給排水に関する次の記述のうち，最も不適切なものはどれか。 | H12: ① 通気管の最小管径は30mmとする。ただし，排水槽に設ける通気管の最小管径は50mmとする。 | I12: ② 伸頂通気管の管径を排水立て管の管径よりも小さくしてはならない。 | J12: ③ 排水立て管は，管の上下方向で負担する排水負荷を考慮し，下階ほど管径を大きくする。 | K12: ④ 地中埋設の排水管の管径は50mm以上とすることが望ましい。 | L12: ⑤ 排水管は，立て管・横管いずれの場合でも，排水の流下方向で管径を縮小してはならない。 | M12: 排水・通気・衛生器具
A13: R2-12 | B13: Ⅲ-12 | C13: 建築環境・設備・建築物衛生管理 | D13: 給排水・防災 | E13: 4 | F13: 排煙設備の法根拠、火災時の煙の2層流動、竪穴区画・避難区画の目的および加圧防煙方式の正誤判定 | G13: 排煙設備に関する次の記述のうち，最も不適切なものはどれか。 | H13: ① 排煙設備の設置義務と技術基準は，建築基準法及び消防法に定められている。 | I13: ② 火災が拡大して火災室より廊下へ流出した煙は，煙と空気の2層を形成しながら流動する。 | J13: ③ 竪穴区画は，煙の侵入を防止することが重要であり，排煙する設備は設けない。 | K13: ④ 避難区画は，居室・廊下・階段の間に間仕切りを設け，在室者がより安全度の高い所に避難できるようにするための区画である。 | L13: ⑤ 加圧防煙方式とは，避難計画上の重要な空間に新鮮空気を供給して内圧を高め，煙の侵入を防ぐ方式である。 | M13: 防災・排煙・消火
... A36: R2-35 | B36: Ⅲ-35 | C36: 廃棄物管理 | D36: 災害廃棄物・事業方式・統計・管理票 | E36: 2 | F36: 大規模災害発生時の二次仮置場運搬、コンクリートくず処理柔軟性、選別方針、行動指針目的および市町村固有事務位置付けの正誤判定 | G36: 「大規模災害発生時における災害廃棄物対策行動指針（平成27年11月 環境省大臣官房廃棄物・リサイクル対策部）」に関する次の記述のうち，最も不適切なものはどれか。 | H36: ① 大規模災害発生時に道路際や空地等に集積された廃棄物は，可能な限り分別した上で速やかに一次仮置場へ運搬，撤去する。 | I36: ② 災害廃棄物の処理期間は，地域及び災害廃棄物の特性に応じて柔軟に設定すべきものであるが，特にコンクリートくずは早期に処理すべきものである。 | J36: ③ 災害廃棄物の選別に当たっては，後工程となる焼却処理や再生利用を効率的に行う観点から処理方針を検討する。 | K36: ④ この指針は，大規模災害発生時においても災害廃棄物を適正かつ円滑・迅速に処理するための基本的考え方，対応方針を整理するものである。 | L36: ⑤ 災害廃棄物の処理は市町村が行う固有事務として位置付けられている。 | M36: 災害廃棄物・指定廃棄物

Sheet R1再(令和元年再試験)問題・選択肢
A1: 問題ID | B1: 設問番号 | C1: 大分類(ブロック) | D1: サブジャンル | E1: 公式正答 | F1: 問題のテーマ・内容概要 | G1: 問題文 | H1: 選択肢① | I1: 選択肢② | J1: 選択肢③ | K1: 選択肢④ | L1: 選択肢⑤ | M1: 出題論点（細目）
A2: R1再-01 | B2: Ⅲ-1 | C2: 建築環境・設備・建築物衛生管理 | D2: 光・音 | E2: 4 | F2: 照明方式、照度計算、ランプ効率および演色評価数に関する正誤判定 | G2: 照明に関する次の記述のうち，最も不適切なものはどれか。 | H2: ① 出射する光束の密度を光束発散度[rlx]という。 | I2: ② 光束は，単位時間当たりの光の放射エネルギーに，波長ごとの人間の視覚の感度である標準比視感度を乗じて求めた値である。 | J2: ③ 窓や照明器具など光源からの直接光による直接照度と，壁や家具での反射を経た間接光による間接照度をそれぞれ計算し，両者の和を全照度とする計算方法を逐点法という。 | K2: ④ メタルハライドランプのランプ効率[lm/W]は，ハロゲンランプのランプ効率[lm/W]よりも低い。 | L2: ⑤ 平均演色評価数Raは，15試験色のうち1から8番目の試験色に関する特殊演色評価数の平均値で表される。 | M2: 照明・光環境
A3: R1再-02 | B3: Ⅲ-2 | C3: 建築環境・設備・建築物衛生管理 | D3: 光・音 | E3: 2 | F3: 光の性質、マンセル表色系、加法混色および演色性に関する正誤判定 | G3: 光・色彩に関する次の記述のうち，最も不適切なものはどれか。 | H3: ① 長年紫外線を浴び続けた結果，高齢者の水晶体は特に500nm以下の短波長である青色光領域の透過率の低下が著しくなる。 | I3: ② 加法混色の三原色は，青緑，赤紫，黄である。 | J3: ③ JISに採用されているマンセル表色系は，ヒュー（Hue），バリュー（Value），クロマ（Chroma）の3属性で表される。 | K3: ④ 色票を用いた視感による測色は，光源に対する注意や面積効果を排除するなどの配慮が必要である。 | L3: ⑤ 赤と緑のように色相が相反していても，明度が同程度に見えにくくなる現象をリープマン効果という。 | M3: 照明・光環境
A4: R1再-03 | B4: Ⅲ-3 | C4: 建築環境・設備・建築物衛生管理 | D4: 熱・湿気 | E4: 1 | F4: 完全黒体放射、熱貫流、熱伝達率および表面放熱特性に関する正誤判定 | G4: 熱移動に関する次の記述のうち，最も不適切なものはどれか。 | H4: ① 完全黒体から放射される熱線のエネルギーは，絶対温度に比例する。 | I4: ② 単層壁の熱貫流は，壁体内部では熱伝導，壁の表面では対流及び放射によって行われている。 | J4: ③ 放射熱伝達率は，固体表面の性質に影響を受ける。 | K4: ④ 床面の対流熱伝達率は，暖房時の方が冷房時よりも小さい。 | L4: ⑤ 壁の対流熱伝達率は，外気側の方が室内側よりも大きい。 | M4: 伝熱・断熱
A5: R1再-04 | B5: Ⅲ-4 | C5: 建築環境・設備・建築物衛生管理 | D5: 換気・室内空気 | E5: 5 | F5: 全般換気、置換換気、必要換気量、給排気口位置および空気齢の定義に関する正誤判定 | G5: 換気に関する次の記述のうち，最も不適切なものはどれか。 | H5: ① 全般換気は，室内全体の空気を稀釈しながら入れ換えるものであり，住宅の居室や事務所ビルの執務室などに多く用いられる。 | I5: ② 置換換気システムは室温より低温の空調空気を気流による不快感が問題とならない低風速で室下部の居住域に直接供給し，室上部で排気するシステムである。 | J5: ③ ある汚染物質が瞬時に一様に拡散とした場合，汚染物質を許容濃度に維持するための必要換気量は汚染物質の発生量と外気濃度で決定され，室容積は関係しない。 | K5: ④ 新鮮外気取入れ口は，道路など建物周辺の状況や排気口の位置も考慮して，清浄な空気が常に確保できるような位置に設け，排気口は，周辺の建物などに支障のない位置に設けなければならない。 | L5: ⑤ 空気齢とは，1つの室に1つずつ吹出し口と排気口がある場合において，空気が吹出し口から排気口に至るまでの時間のことを指す。 | M5: 換気・通風
A6: R1再-05 | B6: Ⅲ-5 | C6: 建築環境・設備・建築物衛生管理 | D6: 光・音 | E6: 3 | F6: 北緯35度の日射・日射調整 | G6: 北緯35度の地点の日射及び日射調整に関する次の記述のうち，最も不適切なものはどれか。 | H6: ① 南鉛直面の終日日射量は日射を遮蔽したい夏至のときに最小となる。 | I6: ② 大気透過率が大きいほど，直達日射が強く，逆に天空日射が弱くなる。 | J6: ③ 北鉛直面は，年間を通じて日照を受けない。 | K6: ④ 東西鉛直面の日射は日の出・日没付近の，太陽高度の低い状況に対応しているので，日射の調整には庇以外のブラインドなどが必要となる。 | L6: ⑤ 冬至の水平面の終日日射量は，夏至の南鉛直面の終日日射量に比較して多い。 | M6: 日照・日射・採光
A7: R1再-06 | B7: Ⅲ-6 | C7: 建築環境・設備・建築物衛生管理 | D7: 光・音 | E7: 4 | F7: 点音源の距離減衰（距離2倍）と音響出力変化（出力2倍）に伴う音圧レベル変化の計算 | G7: 次の図（a）に示すように，音響出力W[W]の点音源から2m離れたA点の音圧レベルが65dBであった。図（b）に示すように，この音源の音響出力が2倍（2W[W]）になった場合，音源から4m離れたB点の音圧レベルに最も近い値は次のうちどれか。 | H7: ① 56dB | I7: ② 57dB | J7: ③ 59dB | K7: ④ 62dB | L7: ⑤ 65dB | M7: 音環境
A8: R1再-07 | B8: Ⅲ-7 | C8: 建築環境・設備・建築物衛生管理 | D8: 温熱・省エネ指標 | E8: 1 | F8: 平均日射熱取得率ηA、UA値、PAL*および一次エネルギー消費量の正誤判定 | G8: 建築物の省エネルギー性能指標に関する次の記述のうち，最も不適切なものはどれか。 | H8: ① 住宅における冷房期の平均日射熱取得率（ηA）は，冷房期の総日射熱取得量を床面積で除して算出される。 | I8: ② 外皮平均熱貫流率（UA）は，室内外の温度差が1℃のときの建物全体の外皮で生じる総熱損失量を外皮（外壁や窓等）の表面積の合計で除して算出される。 | J8: ③ 外皮基準の指標である従来の年間熱負荷係数（PAL）に対し，年間熱負荷係数（PAL*）は潜熱負荷を含めて評価している。 | K8: ④ 非住宅建築物の暖冷房負荷の算出においては，取入外気の熱についても勘案する必要がある。 | L8: ⑤ 一次エネルギーとは，化石燃料，原子力燃料，水力，太陽光など自然から得られるエネルギーのことをいう。 | M8: 省エネ性能指標・都市建築環境
A9: R1再-08 | B9: Ⅲ-8 | C9: 建築環境・設備・建築物衛生管理 | D9: 空調 | E9: 3 | F9: ノズル形、アネモ形、パン形、スロット形吹出口の構造特性と用途比較の正誤判定 | G9: 吹出口及び吸込口に関する次の記述のうち，最も不適切なものはどれか。 | H9: ① ノズル形吹出口は，フェースのまったくない形で劇場などにおいて到達距離をふやすために吹出風速を 5 m/s 以上にして用いることができる。 | I9: ② アネモスタット形吹出口は，吹出口の中で最も大きな誘引性能を有しており，吹出温度差をきわめて大きくとることができる。 | J9: ③ パン形吹出口は，吹出口の方向を左右，上下に変えることができる首振り形のノズル形吹出口の1つで，厨房などのスポット冷房に適している。 | K9: ④ スロット形吹出口は，著しくアスペクト比の大きい吹出口で，体裁がよいので意匠を重視する室に多く使用されている。 | L9: ⑤ 固定羽根型吸込口又はユニバーサル型吸込口は，壁付及び天井付の吸込口として最も多く用いられている。 | M9: 空調機器・ダクト・熱源
A10: R1再-09 | B10: Ⅲ-9 | C10: 建築環境・設備・建築物衛生管理 | D10: 給排水・防災 | E10: 2 | F10: 給湯配管（複管式）、ガス給湯器「号」定義、ポンプ配置、スイベルジョイントおよびベローズ継手の正誤判定 | G10: 給湯設備に関する次の記述のうち，最も不適切なものはどれか。 | H10: ① 給湯栓を開けて即座に湯が必要になるホテルなどでは返湯管を設け，管内の湯を循環させて湯温を一定に保つことで湯待ち時間を小さくする複管式が用いられる。 | I10: ② ガス給湯器では能力表示に「号」を用いるが，1号は流量 1 [L/min] の水の温度を 20℃上昇させる能力である。 | J10: ③ 強制循環方式における循環ポンプは，一般に貯湯槽の直前の返湯管部分に設置する。 | K10: ④ スイベルジョイント工法とは，配管の分岐部に複数のエルボを組合せて用い，可とう性を持たせた配管工法である。 | L10: ⑤ ベローズ型伸縮継手とは，波型の管が伸縮動作を吸収する形式の継手である。 | M10: 給水・給湯
A11: R1再-10 | B11: Ⅲ-10 | C11: 建築環境・設備・建築物衛生管理 | D11: 給排水・防災 | E11: 4 | F11: オフセット配管、伸頂通気管、掃除口間隔、各個通気立ち上げ高さおよびループ通気方式の正誤判定 | G11: 排水・通気配管に関する次の記述のうち，最も不適切なものはどれか。 | H11: ① 建物の最下階にピロティや駐車場があり，そこに排水立て管が通過する際，水平移動して経路を変更する配管部をオフセットという。 | I11: ② 伸頂通気管とは排水立て管の頂部に設置する通気管であり，原則としてその端部を大気に開放する。 | J11: ③ 掃除口は，排水管径が100mm以下の場合は15m以内ごと，100mmを超える場合は30m以内ごとに設置する。 | K11: ④ 各個通気管は，各衛生器具の器具排水管にそれぞれ設置する通気管で，その器具にあふれ縁より50mm以上立ち上げて通気横枝管等に接続する。 | L11: ⑤ ループ通気管を用いるループ通気方式は，排水横枝管に複数接続された衛生器具のトラップを保護する効果的な方法である。 | M11: 排水・通気・衛生器具
A12: R1再-11 | B12: Ⅲ-11 | C12: 建築環境・設備・建築物衛生管理 | D12: 換気・室内空気 | E12: 1 | F12: エアフィルタ・電気集じん器 | G12: 空気調和設備におけるエアフィルタ及び電気集じん器に関する次の記述のうち，最も不適切なものはどれか。 | H12: ① 粉じん保持容量は，エアフィルタの空気抵抗が最初の1.5倍になるまでフィルタ面に捕集されたじんあい量であり，高性能のものほど大きくなる。 | I12: ② エアフィルタの効率の測定方法を大別すると重量法，変色度法及びDOP法の3方法があり，DOP法が最も厳格なテストになる。 | J12: ③ エアフィルタの乾性ろ過式は，ふるいのようにフィルタの目より大きいごみをこして除去するもので，中性能・高性能はほとんどこの方式である。 | K12: ④ エアフィルタの粘性式は，フィルタ中を通る気流がろ材の繊維を避けながらジグザグに進む間にごみがろ材表面（油塗布）に付着し，除去されるものである。 | L12: ⑤ 静電式（電気集じん器）は，ごみを含む空気を放電現場に通してごみに帯電させ，この帯電したごみを陽極板に吸引し，除去するものである。 | M12: 室内空気質・健康影響・衛生動物
A13: R1再-12 | B13: Ⅲ-12 | C13: 建築環境・設備・建築物衛生管理 | D13: 給排水・防災 | E13: 2 | F13: 洗浄弁方式・ロータンク方式給水管径・圧力要件、洗い出し式便器および節水型JIS規格の正誤判定 | G13: 大便器に関する次の記述のうち，最も不適切なものはどれか。 | H13: ① 望ましい大便器の条件としては，乾燥面が少なく留水面が広いこと，排水路内径が大きいことなどが挙げられる。 | I13: ② 洗浄弁方式による給水は，給水管の管径が25mm以上，必要給水圧力が30kPa以上必要である。 | J13: ③ ロータンク式による給水は，給水管の管径が13mm程度，必要給水圧力は一般水栓と同じ30kPaと低くてよい。 | K13: ④ 洗浄方式の分類における洗い出し式は，和風便器に使われ，汚物を一時便器の上にためるので臭気が強いが，安価である。 | L13: ⑤ 節水形大便器の洗浄水量はJIS規格において，節水Ⅰ形でおよそ8.5リットル以下，節水Ⅱ形でおよそ6.5リットル以下と規定されている。 | M13: 排水・通気・衛生器具
... A36: R1再-35 | B36: Ⅲ-35 | C36: 廃棄物管理 | D36: 最終処分場・浸出水 | E36: 5 | F36: オープン型処分場（面積5.0ha、降水量2000mm/年、蒸発散量2.0mm/日）における日平均浸出水量（175m³/日）と浸出係数（0.6）計算 | G36: 最終処分場の浸出水量に関する次の記述の，［ ］に入る数値の組合せとして，最も適切なものはどれか。 「表面遮水工が設置されているオープン型最終処分場において，埋立面積が 5.0ha，年間降水量が 2000mm／年，蒸発散量が 2.0mm／日の場合，日平均浸出水発生量は［ A ］m³／日，浸出係数は［ B ］である。ただし，埋立地に降った雨水が表流水として外部へ排除されることはないものとする。」 | H36: ① A: 100 / B: 0.4 | I36: ② A: 100 / B: 0.6 | J36: ③ A: 140 / B: 0.5 | K36: ④ A: 175 / B: 0.4 | L36: ⑤ A: 175 / B: 0.6 | M36: 最終処分場・浸出水

Sheet R1本(令和元年本試験)問題・選択肢
A1: 問題ID | B1: 設問番号 | C1: 大分類(ブロック) | D1: サブジャンル | E1: 公式正答 | F1: 問題のテーマ・内容概要 | G1: 問題文 | H1: 選択肢① | I1: 選択肢② | J1: 選択肢③ | K1: 選択肢④ | L1: 選択肢⑤ | M1: 出題論点（細目）
A2: R1本-01 | B2: Ⅲ-1 | C2: 建築環境・設備・建築物衛生管理 | D2: 光・音 | E2: 1 | F2: 点光源の水平面照度(200cd,2m,60°) | G2: 下図に示す点光源に照らされたA点の水平面照度に最も近い値はどれか。ただし，点光源の配光特性は一様なものとし，反射は考慮しないものとする。［図：点光源の光度200cd，点光源は床面から高さ2m，A点は点光源の真下から見て鉛直方向60°の位置］ | H2: ① 6.3 lx | I2: ② 8.3 lx | J2: ③ 10.8 lx | K2: ④ 12.5 lx | L2: ⑤ 50.0 lx | M2: 照明・光環境
A3: R1本-02 | B3: Ⅲ-2 | C3: 建築環境・設備・建築物衛生管理 | D3: 温熱・省エネ指標 | E3: 1 | F3: 室内の温度分布 | G3: 室内の温度分布に関する次の記述のうち，最も不適切なものはどれか。 | H3: ① 良好な温熱環境を実現するためには，極端な室内温度分布が生じるのは好ましくないため，床上0.1mから1.1m間の上下温度差分布は5℃以内に抑えるのが好ましい。 | I3: ② 夏期に日射熱が室内へ侵入する場合や外気温が高い場合は，窓側の空気温度は室の奥よりも高くなり，冬期に隙間風が侵入する場合や外気温が低い場合は，窓側の空気温度は低くなる傾向にある。 | J3: ③ 室内には種々の発熱体が存在し，近傍の空気温度を上昇させる。この高温空気は密度が小さいため，浮力により上昇気流を発生させる場合がある。 | K3: ④ 空調・換気設備は，床面より1.8m程度までの居住域を良好な温熱空気環境に保つことが目的であるが，室内に温度分布を生じさせる原因でもある。 | L3: ⑤ エアフローウィンドウは，2枚のガラスの間にブラインドを設けたもので，窓枠下部から室内空気を吸引し，これを窓上部から排気するものである。 | M3: 温熱環境・温熱指標
A4: R1本-03 | B4: Ⅲ-3 | C4: 建築環境・設備・建築物衛生管理 | D4: 熱・湿気 | E4: 2 | F4: 材料の熱定数 | G4: 材料の熱定数に関する次の記述のうち，最も不適切なものはどれか。 | H4: ① 中空層の熱抵抗は，熱流方向が下向きの方が上向きより大きい。 | I4: ② グラスウールの熱伝導率は，かさ比重が小さいほど小さくなる傾向がある。 | J4: ③ 畳の熱伝導率は，木材と同程度である。 | K4: ④ ALCの熱伝導率は，普通コンクリートの1／10程度である。 | L4: ⑤ 二重ガラスなど密閉中空層の熱抵抗は，壁の中空層など半密閉中空層の2倍程度である。 | M4: 伝熱・断熱
A5: R1本-04 | B5: Ⅲ-4 | C5: 建築環境・設備・建築物衛生管理 | D5: 光・音 | E5: 1 | F5: 日照・日射 | G5: 日照・日射に関する次の記述のうち，最も不適切なものはどれか。 | H5: ① 実効放射量（夜間放射量）は，雲があるときは，雲がないときに比較して増加する。 | I5: ② 東西に長い集合住宅において，東京で日照時間を4時間確保するための隣棟間隔係数（隣棟間隔d／建物高さh）は，2程度となる。 | J5: ③ 熱線吸収ガラスは，冷房時に効果がある。 | K5: ④ 対向建物などがない場合は，ガラスのない開放された窓では，近似的に直接昼光率と立体角投射率［%］は一致する。 | L5: ⑤ 頂側窓は，昼光によって展示品を鑑賞したい美術館の展示室や面積の大きい工場に用いられる。 | M5: 日照・日射・採光
A6: R1本-05 | B6: Ⅲ-5 | C6: 建築環境・設備・建築物衛生管理 | D6: 光・音 | E6: 3 | F6: 音環境 | G6: 音環境に関する次の記述のうち，最も不適切なものはどれか。 | H6: ① 障壁は，回折による高音域の遮断に対する効果が大きい。 | I6: ② 音響エネルギー密度が60dBだけ減衰するのに要する時間を残響時間という。 | J6: ③ 多孔質材の吸音機構において，剛壁に直貼りしたときの吸音率は，吸音材の材厚を厚くしても，低音域の吸音率は向上しない。 | K6: ④ 重量衝撃音の低減に対しては，床構造の曲げ剛性や質量が重要で，木造などの軽量床の場合，必要な性能を得ることは困難である。 | L6: ⑤ コインシデンス効果は，音がさまざまな方向から壁面に入射する場合には広い周波数で発生する。 | M6: 音環境
A7: R1本-06 | B7: Ⅲ-6 | C7: 建築環境・設備・建築物衛生管理 | D7: 換気・室内空気 | E7: 4 | F7: 自然換気 | G7: 自然換気に関する次の記述のうち，最も不適切なものはどれか。 | H7: ① 窓を開放した場合などの開口部通過風量は，開口部面積に比例し，圧力差の平方根に比例する。 | I7: ② 実効面積αAにおけるαは流量係数であり，開口の形状や寸法で異なるが，通常端部が直角に整形された窓では0.6～0.7程度となる。 | J7: ③ 中性帯の位置は，定性的には開口部の大きい方に近づく。 | K7: ④ 2つの開口部があるとき，2つの開口部とも負の風圧係数となる場合，それらの風圧係数に差があっても風力換気は生じない。 | L7: ⑤ 高さの異なる2つの開口部があるときの温度差換気量は，直列合成した実効面積αAに比例するとともに，室内外温度差及び開口高さの差の平方根に比例して増加する。 | M7: 換気・通風
A8: R1本-07 | B8: Ⅲ-7 | C8: 建築環境・設備・建築物衛生管理 | D8: 給排水・防災 | E8: 3 | F8: 水配管 | G8: 水配管に関する次の記述のうち，最も不適切なものはどれか。 | H8: ① 開放式は必ず摩擦抵抗のほかに押し上げ揚程が加わり，密閉式に比べてポンプ動力が大きくなる。 | I8: ② 二方弁制御は三方弁制御に比べて一般に制御性が良く，ポンプの台数制御などによりポンプの消費電力を節約できる。 | J8: ③ 満水状態で流体が流れる場合の直管部摩擦抵抗は，管の長さと流体の密度及び流速の2乗に比例し，管の内径と管摩擦係数に反比例する。 | K8: ④ リバースリターン方式では，各機器を通る配管長さが等しく，抵抗が同じとなるために，流量が自然に均一になるという特徴がある。 | L8: ⑤ 普通の屋内配管では，浸食を防ぐための管内流速を一般に2.0m／s以下としている。 | M8: 給水・給湯
A9: R1本-08 | B9: Ⅲ-8 | C9: 建築環境・設備・建築物衛生管理 | D9: 空調 | E9: 5 | F9: 省エネ設備機器 | G9: 省エネルギー設備機器に関する次の記述のうち，最も不適切なものはどれか。 | H9: ① 空気調和機に使用する全熱交換器では，外気冷房が可能なときに給排気バイパスなどにより熱交換を回避する。 | I9: ② 夜間電力利用の蓄熱槽システムでは，熱源の夜間運転時間が長いほど，熱源容量は小さくて済む。 | J9: ③ コージェネレーションシステムは，ガスタービンやガスエンジン，燃料電池などを用いて電力エネルギーと熱エネルギーの両者を同時に供給するシステムであり，総合効率は最大80%程度まで期待することができる。 | K9: ④ 多結晶シリコン太陽電池は，単結晶シリコン太陽電池と比較して変換効率が低いが，製造が容易で効率とコストのバランスが良いため，よく普及している太陽電池である。 | L9: ⑤ ヒートポンプの冷房時の成績係数（COP）は，圧縮仕事に対する凝縮熱量の比で表す。 | M9: 空調方式・省エネルギー
A10: R1本-09 | B10: Ⅲ-9 | C10: 建築環境・設備・建築物衛生管理 | D10: 給排水・防災 | E10: 1 | F10: 給水設備 | G10: 給水設備に関する次の記述のうち，最も不適切なものはどれか。 | H10: ① 高置水槽容量は，揚水ポンプの能力との関係によっても異なるが，一般に1日の使用水量の1／3程度とすることが多い。 | I10: ② 受水槽の有効容量は，水道事業者が断水を考慮して指定要綱などで設計用給水量の4／10～6／10程度の容量を確保するところが多く，概算で1日の使用水量の1／2程度としている。 | J10: ③ 貯水槽はすべての面から点検できるように水槽の上面に1.0m以上，側面と下面に0.6m以上の空間を確保して設置する。 | K10: ④ 井戸を使っている住宅などで，井戸水の配管と水道配管を接続させることはクロスコネクションとなる。 | L10: ⑤ 一般に給水管の給水圧力の上限値は，ホテル・集合住宅で300～400kPa程度，事務所・工場では400～500kPa程度として計画する。 | M10: 給水・給湯
A11: R1本-10 | B11: Ⅲ-10 | C11: 建築環境・設備・建築物衛生管理 | D11: 空調 | E11: 5 | F11: ポンプ及びファン | G11: ポンプ及びファンに関する次の記述のうち，最も不適切なものはどれか。 | H11: ① ラインポンプは小規模な冷温水循環用として配管途中に直接取り付けられるものである。 | I11: ② クロスフローファンはエアコン，ファンコイルユニット，室内空気のサーキュレータなど機器組込みの低圧ファンとして利用されている。 | J11: ③ 遠心ポンプの流量と揚程は羽根車の毎分回転数で変化するが，流量は回転数に比例し，揚程は回転数の2乗に比例する。また，軸動力は回転数の3乗に比例する。 | K11: ④ 空調用の送風機は高い省エネルギー性を求める場合，多翼型のシロッコファンよりも効率の高い後曲型のターボファンを使用する例が増えている。 | L11: ⑤ 渦巻きポンプには羽根車の外に流れの乱れを防ぎポンプ効率を改善するための固定案内羽根がある。 | M11: 空調機器・ダクト・熱源
A12: R1本-11 | B12: Ⅲ-11 | C12: 建築環境・設備・建築物衛生管理 | D12: 空調 | E12: 4 | F12: ボイラー | G12: ボイラーに関する次の記述のうち，最も不適切なものはどれか。 | H12: ① ボイラーの容量は，定格出力すなわち最大連続負荷における毎時出力によって表され，蒸気ボイラーの場合は換算蒸発量［kg／h］又は実際蒸発量［kg／h］，温水ボイラーの場合は熱出力［kW］で表すのが通常である。 | I12: ② 真空式温水機は，鋼板製若しくは鋳鉄製のボイラーの大きな蒸気室に熱交換用のコイルをいくつか配置し，ボイラー内部の蒸気で間接的に暖房用水，給湯用水，プールの水などいくつかの系統の温水を1つのボイラーで加熱するものである。 | J12: ③ 貫流式ボイラーは，燃焼室を取り巻く水管を給水が通過する間に，完全に蒸発する比較的小容量の蒸気ボイラーで，構造が簡単で効率も高く，安価なためにビルや工場などで用いられる。 | K12: ④ 鋳鉄製ボイラーは大容量の高圧型ボイラーで，排気ガスによる給水予熱器又は燃焼空気予熱器などを用いるためボイラー効率は高く，大規模ビルや地域冷暖房プラントなどで用いられる。 | L12: ⑤ ボイラーの排気ガスは地方自治体によってSOx，NOx，煤塵量などが規制されており，市街地でのボイラーの燃料は都市ガスを採用することが多い。 | M12: 空調機器・ダクト・熱源
A13: R1本-12 | B13: Ⅲ-12 | C13: 建築環境・設備・建築物衛生管理 | D13: 給排水・防災 | E13: 3 | F13: 消火設備 | G13: 消火設備に関する次の記述のうち，最も不適切なものはどれか。 | H13: ① 火災は，A火災（普通火災），B火災（油火災），C火災（電気火災），D火災（金属火災）に区分される。 | I13: ② 消防の用に供する設備は，消火設備，警報設備，避難設備の3つに分類される。 | J13: ③ 屋内消火栓設備のホース先端における放水圧力は7MPaを超えないように規定されている。 | K13: ④ 屋外消火栓設備は，1階及び2階の床面積の広い建物に設置し，屋外から屋内に向けて放水によって消火する設備であり，1階及び2階の部分に限って有効な消火設備である。 | L13: ⑤ ドレンチャー消火設備は，建物外部の火災に対し外壁，屋根，開口部に水幕をつくって延焼を防ぐための設備である。 | M13: 防災・排煙・消火
... A36: R1本-35 | B36: Ⅲ-35 | C36: 廃棄物管理 | D36: 災害廃棄物・事業方式・統計・管理票 | E36: 5 | F36: 指定廃棄物 | G36: 指定廃棄物に関する次の記述の，［ ］に入る数値の組合せとして，最も適切なものはどれか。 2011年3月に発生した原子力発電所の事故により放射性物質により汚染された廃棄物のうち，［A］ベクレル／kgを超えるものを指定廃棄物とし，国の責任のもと，適切な方法で処理することとなっている。また，福島県内で除染に伴い発生した除染土壌や［B］ベクレル／kgを超える指定廃棄物等を安全に集中的に管理・保管するために中間貯蔵施設の整備が進められている。 | H36: ① A：100 B：8,000 | I36: ② A：100 B：5万 | J36: ③ A：1,000 B：10万 | K36: ④ A：8,000 B：5万 | L36: ⑤ A：8,000 B：10万 | M36: 災害廃棄物・指定廃棄物

Sheet H30(平成30年度)問題・選択肢
A1: 問題ID | B1: 設問番号 | C1: 大分類(ブロック) | D1: サブジャンル | E1: 公式正答 | F1: 問題のテーマ・内容概要 | G1: 問題文 | H1: 選択肢① | I1: 選択肢② | J1: 選択肢③ | K1: 選択肢④ | L1: 選択肢⑤ | M1: 出題論点（細目）
A2: H30-01 | B2: Ⅲ-1 | C2: 建築環境・設備・建築物衛生管理 | D2: 光・音 | E2: 1 | F2: 床衝撃音（LH/LL）対策、二重窓の空気層、コインシデンス効果、質量則および遮音等級（D値）に関する正誤判定 | G2: 遮音に関する次の記述のうち，最も不適切なものはどれか。 | H2: ① 床の重量衝撃音に対する対策は，床仕上げ材であるカーペットや畳などの緩衝性の材料が効果的である。 | I2: ② 透明ガラスを2重〜3重にはめ殺しにした遮音窓は，できるだけ空気層を厚くとり，その吸音特性を空気層の共鳴周波数に同調させるとよい。 | J2: ③ コインシデンス効果を生じる周波数は，入射波の角度が90°のときに最小となる。 | K2: ④ 壁体の面密度が2倍あるいは周波数が2倍になるごとに，透過損失は6dB増加する。 | L2: ⑤ JIS A1419-1に定める遮音等級において，D-55はD-40よりも遮音性能が高い。 | M2: 音環境
A3: H30-02 | B3: Ⅲ-2 | C3: 建築環境・設備・建築物衛生管理 | D3: 光・音 | E3: 1 | F3: 直射日光と曇天光の色温度、昼光率の安定性、高圧水銀ランプ効率および作業面照度基準の正誤判定 | G3: 採光・照明に関する次の記述のうち，最も不適切なものはどれか。 | H3: ① 直射日光の色温度より，曇天光の色温度の方が低い。 | I3: ② 昼光率は，正確には天空輝度分布の形によって異なるが，屋外の昼光の変動に関わらず，ほぼ一定と考えてよい。 | J3: ③ 蛍光高圧水銀ランプは，白熱電球よりも一般に効率が高い。 | K3: ④ 750 lx以上の作業面照度を必要とするとき，作業周辺部の照度は500 lxとする。 | L3: ⑤ 出射する光束の，反射面の単位面積当たり，単位立体角当たりの大きさを，輝度という。 | M3: 日照・日射・採光
A4: H30-03 | B4: Ⅲ-3 | C4: 建築環境・設備・建築物衛生管理 | D4: 熱・湿気 | E4: 2 | F4: 熱移動 | G4: 熱移動に関する次の記述のうち，最も不適切なものはどれか。 | H4: ① 壁の熱貫流は，壁内部では熱伝導，壁の表面では対流及び放射によって行われている。 | I4: ② 完全黒体から放射される熱線のエネルギーは，絶対温度に比例する。 | J4: ③ 放射熱伝達率は，物体表面が艶消しで真っ黒いほど大きくなる。 | K4: ④ 床面の対流熱伝達率は，暖房時の方が冷房時よりも小さい。 | L4: ⑤ 壁の対流熱伝達率は，外気側の方が室内側よりも大きい。 | M4: 伝熱・断熱
A5: H30-04 | B5: Ⅲ-4 | C5: 建築環境・設備・建築物衛生管理 | D5: 熱・湿気 | E5: 3 | F5: 複層壁体における断熱材（材料2）厚み変更に伴う熱貫流抵抗の倍率計算 | G5: 下図に示すように材料1，材料2から構成される壁体がある。材料2の厚みを2倍にしたとき，壁体の熱貫流抵抗の変更前に対する変更後の比として，最も近い値はどれか。ただし，計算条件は以下のとおりである。 外気側表面熱伝達抵抗 Ro ＝ 0.04 [m²・K/W] 室内側表面熱伝達抵抗 Ri ＝ 0.11 [m²・K/W] 材料1の熱伝導率 λ1 ＝ 1.5 [W/(m・K)]，厚さ 150 mm 材料2の熱伝導率 λ2 ＝ 0.03 [W/(m・K)]，厚さ 30 mm | H5: ① 0.6 | I5: ② 1.0 | J5: ③ 1.8 | K5: ④ 1.9 | L5: ⑤ 2.0 | M5: 伝熱・断熱
A6: H30-05 | B6: Ⅲ-5 | C6: 建築環境・設備・建築物衛生管理 | D6: 熱・湿気 | E6: 1 | F6: 相対湿度・乾球温度・湿球温度・露点温度の関係、水蒸気圧および空気の全圧（ドルトンの法則）に関する正誤判定 | G6: 湿り空気に関する次の記述のうち，最も不適切なものはどれか。 | H6: ① 空気中の相対湿度が50%のとき，湿球温度は乾球温度と同じ値になる。 | I6: ② 水蒸気の多く含まれている空気ほど，露点温度は高くなる。 | J6: ③ 相対湿度は温度変化の影響を受けるが，絶対湿度は温度変化の影響を受けない。 | K6: ④ 一定時間に水面から飛び出す水蒸気分子の数と，湿り空気から水面に飛び込む水蒸気分子の数が同数になるとき，これを平衡状態という。 | L6: ⑤ 乾き空気の分圧と水蒸気分圧を加算したものが湿り空気の全圧となる。 | M6: 結露・湿気・湿り空気
A7: H30-06 | B7: Ⅲ-6 | C7: 建築環境・設備・建築物衛生管理 | D7: 温熱・省エネ指標 | E7: 2 | F7: 温熱快適性(エネルギー代謝・PMV・作用温度) | G7: 温熱快適性に関する次の記述のうち，最も不適切なものはどれか。 | H7: ① 人体のエネルギー代謝は，身体の表面積に比例する。 | I7: ② 人体からの放熱量は，室内温度が上がるにつれて顕熱分の割合が増加する。 | J7: ③ 予測平均温冷感申告の値が −0.5 の場合，予測不満足者率は10%となる。 | K7: ④ 標準新有効温度は，椅座静位状態を前提とした温熱感評価指標である。 | L7: ⑤ 作用温度は静穏気流下ではほぼ空気温度と平均放射温度の相加平均となる。 | M7: 温熱環境・温熱指標
A8: H30-07 | B8: Ⅲ-7 | C8: 建築環境・設備・建築物衛生管理 | D8: 空調 | E8: 5 | F8: 比エンタルピー算出式を用いた乾き空気1,000kg(DA)の蒸気加熱加湿に伴う獲得熱量計算 | G8: 湿り空気の比エンタルピーhは次の式で表せる。 h ＝ 1.0 t ＋ (2500 ＋ 1.8 t) x [kJ/kg(DA)] ただし，t : 乾球温度 [℃]，x : 絶対湿度 [kg/kg(DA)]，kg(DA) : 乾き空気の質量 乾き空気1000 kg(DA)を含む，乾球温度7 ℃，絶対湿度0.004 kg/kg(DA)の湿り空気を，蒸気で加熱・加湿し，乾球温度42 ℃，絶対湿度0.014 kg/kg(DA)としたときの空気の得た熱量として，最も近い値はどれか。 | H8: ① 26 kJ | I8: ② 35 kJ | J8: ③ 61 kJ | K8: ④ 26 MJ | L8: ⑤ 61 MJ | M8: 空調計算（負荷・空気線図・冷凍サイクル）
A9: H30-08 | B9: Ⅲ-8 | C9: 建築環境・設備・建築物衛生管理 | D9: 空調 | E9: 4 | F9: 各種冷凍機（電動・水冷/空冷、吸収式、ターボ、レシプロ）の原理、特徴および構造に関する正誤判定 | G9: 熱源装置に関する次の記述のうち，最も不適切なものはどれか。 | H9: ① 各種電動冷凍機の定格時成績係数は，水冷式の方が空冷式よりも大きい。 | I9: ② 吸収冷凍機では一般に冷媒として水，吸収剤として臭化リチウム溶液が用いられている。 | J9: ③ 遠心冷凍機はターボ冷凍機とも呼ばれ，羽根車の回転による遠心力で冷媒を圧縮するもので，空調用としては大容量の場合に多く用いられている。 | K9: ④ レシプロ冷凍機は回転型圧縮機の一種で，中・大容量のヒートポンプなどに多く用いられている。 | L9: ⑤ 吸収式冷凍の特徴は圧縮機能に比べて電力消費量が少なく，騒音・振動も小さいことである。しかし，形状や重量は大きく，冷却塔の容量も大きくなる。 | M9: 空調機器・ダクト・熱源
A10: H30-09 | B10: Ⅲ-9 | C10: 建築環境・設備・建築物衛生管理 | D10: 換気・室内空気 | E10: 2 | F10: 風力換気力、平均空気齢・平均滞留時間の定義、建築基準法換気基準（20m3/h・人）、CO2発生量および第一種〜第三種換気分類に関する正誤判定 | G10: 換気に関する次の記述のうち，最も不適切なものはどれか。 | H10: ① 風による換気力は，空気自体の持つ運動エネルギーに建物の形状により決まる風圧係数を乗じて求めることができる。 | I10: ② 平均空気齢とは，空気が吹出口から排気口に至るまでの平均時間である。 | J10: ③ 建築物における衛生的な環境の確保に関する法律が適用されない建物での在室人員に必要な新鮮空気を導入する換気は，建築基準法に規定される20 [m³/(h・人)] が一般的に用いられる。 | K10: ④ 人体からのCO₂発生量は安静時で0.013 [m³/(h・人)] 程度，事務作業時で0.02 [m³/(h・人)] 程度である。 | L10: ⑤ 第三種換気とは自然給気と機械排気による換気であり，直接的に外気を自然給気する場合を第三種換気の甲種，間接的に外気を自然給気する場合を第三種換気の乙種と分類する。 | M10: 換気・通風
A11: H30-10 | B11: Ⅲ-10 | C11: 建築環境・設備・建築物衛生管理 | D11: 給排水・防災 | E11: 2 | F11: 受水槽有効容量（1/2日分）、高置水槽容量（1/10日分）、点検空間寸法（上1m/周0.6m）、クロスコネクションおよび適正給水圧力の正誤判定 | G11: 給水設備に関する次の記述のうち，最も不適切なものはどれか。 | H11: ① 受水槽の有効容量は，水道事業者が断水時を考慮して指定要綱などで設計用給水量の 4/10〜6/10 程度の容量を確保するところが多く，概算で1日の使用水量の 1/2 程度としている。 | I11: ② 高置水槽容量は，揚水ポンプの能力との関係によっても異なるが，一般に1日の使用水量の 1/3 程度とすることが多い。 | J11: ③ 貯水槽はすべての面から点検できるように水槽の上面に1.0m以上，側面と下面に0.6m以上の空間を確保して設置する。 | K11: ④ 井戸を使っている住宅などで，井戸水の配管と水道配管を接続させることはクロスコネクションとなる。 | L11: ⑤ 一般に給水管の給水圧力の上限値は，ホテル・集合住宅で300〜400 kPa程度，事務所・工場では400〜500 kPa程度として計画する。 | M11: 給水・給湯
A12: H30-11 | B12: Ⅲ-11 | C12: 建築環境・設備・建築物衛生管理 | D12: 給排水・防災 | E12: 5 | F12: 通気管最小管径（30mm/排水槽50mm）、伸頂通気管径、地中埋設管径、流下方向管径維持および排水立て管径固定法則の正誤判定 | G12: 排水通気設備に関する次の記述のうち，最も不適切なものはどれか。 | H12: ① 通気管の最小管径は30mmとする。ただし，排水槽に設ける通気管の最小管径は50mmとする。 | I12: ② 伸頂通気管の管径を排水立て管の管径よりも小さくしてはならない。 | J12: ③ 地中埋設の排水管の管径は50mm以上とすることが望ましい。 | K12: ④ 排水管は，立て管・横管いずれの場合でも，排水の流下方向で管径を縮小してはならない。 | L12: ⑤ 排水立て管は，管の上下方向で負担する排水負荷を考慮し，下階ほど管径を大きくする。 | M12: 排水・通気・衛生器具
A13: H30-12 | B13: Ⅲ-12 | C13: 建築環境・設備・建築物衛生管理 | D13: 給排水・防災 | E13: 3 | F13: 排煙設備の根拠法令、火災室廊下の2層流動、防煙区画の定義、竪穴区画および加圧防煙方式の正誤判定 | G13: 排煙設備に関する次の記述のうち，最も不適切なものはどれか。 | H13: ① 排煙設備の設置義務や技術基準は，建築基準法及び消防法に定められている。 | I13: ② 火災が拡大して火災室より廊下へ流出した煙は，煙と空気の2層を形成しながら流動する。 | J13: ③ 用途区画は，居室・廊下・階段の間に防煙区画を設け，在室者がより安全度の高い所に避難できるようにするための区画である。 | K13: ④ 竪穴区画は，煙の侵入を防止することが重要であり，排煙する設備は設けない。 | L13: ⑤ 加圧防煙方式とは，避難計画上の重要な空間に新鮮空気を供給して内圧を高め，煙の侵入を防ぐ方式である。 | M13: 防災・排煙・消火
... A36: H30-35 | B36: Ⅲ-35 | C36: 廃棄物管理 | D36: 災害廃棄物・事業方式・統計・管理票 | E36: 4 | F36: 原発事故汚染廃棄物（指定廃棄物8,000Bq/kg超、除染土壌10万Bq/kg超、中間貯蔵施設推計量2,200万m3）数値穴埋め問題 | G36: 指定廃棄物に関する次の記述の，[ ] に入る数値の組合せとして，最も適切なものはどれか。 「2011年3月に発生した原子力発電所の事故で放射性物質により汚染された廃棄物のうち，[ A ] ベクレル/kgを超えるものを指定廃棄物とし，国の責任のもと，適切な方法で処理することとなっている。また，福島県内で除染に伴い発生した除染土壌や [ B ] ベクレル/kgを超える指定廃棄物等を安全に集中的に管理・保管するために中間貯蔵施設の整備が進められており，その対象量は，最大 [ C ] 万m³（2013年7月時点の除染実施計画等に基づく推計値）と推計されている。」 | H36: ① A: 100 / B: 8,000 / C: 220 | I36: ② A: 100 / B: 8,000 / C: 2,200 | J36: ③ A: 8,000 / B: 10万 / C: 220 | K36: ④ A: 8,000 / B: 10万 / C: 2,200 | L36: ⑤ A: 1万 / B: 10万 / C: 220 | M36: 災害廃棄物・指定廃棄物

Sheet H29(平成29年度)問題・選択肢
A1: 問題ID | B1: 設問番号 | C1: 大分類(ブロック) | D1: サブジャンル | E1: 公式正答 | F1: 問題のテーマ・内容概要 | G1: 問題文 | H1: 選択肢① | I1: 選択肢② | J1: 選択肢③ | K1: 選択肢④ | L1: 選択肢⑤ | M1: 出題論点（細目）
A2: H29-01 | B2: Ⅲ-1 | C2: 建築環境・設備・建築物衛生管理 | D2: 熱・湿気 | E2: 2 | F2: 建築材料の熱伝導率比較（グラスウール、合板、軽量コンクリート、ガラス、ステンレス鋼） | G2: 次の (a) 〜 (e) の建築材料の熱伝導率 [W/(m・K)] について，値の小さいものから順に並べたものはどれか。 (a) 軽量コンクリート（軽量1種） (b) ガラス (c) 合板 (d) 高性能グラスウール断熱材16K相当 (e) ステンレス鋼 | H2: ① d, a, b, c, e | I2: ② d, c, a, b, e | J2: ③ d, a, c, e, b | K2: ④ c, a, d, b, e | L2: ⑤ c, a, d, e, b | M2: 伝熱・断熱
A3: H29-02 | B3: Ⅲ-2 | C3: 建築環境・設備・建築物衛生管理 | D3: 換気・室内空気 | E3: 3 | F3: 二面開口住戸の通風・換気における相当開口面積（風上・風下の直列・並列開口の合成）の定型計算 | G3: 二面開口住戸の通風・換気性能について，風上開口の相当開口面積α1A1，風下開口の相当開口面積α2A2, α3A3が下図に示す値である場合，これらを合成した相当開口面積（合成αA）に最も近い値はどれか。 ただし，風上開口α1A1＝100 cm²，風下開口α2A2＝50 cm²，α3A3＝50 cm²とする。 | H3: ① 24 [cm²] | I3: ② 33 [cm²] | J3: ③ 71 [cm²] | K3: ④ 135 [cm²] | L3: ⑤ 141 [cm²] | M3: 換気・通風
A4: H29-03 | B4: Ⅲ-3 | C4: 建築環境・設備・建築物衛生管理 | D4: 熱・湿気 | E4: 1 | F4: 木材腐朽菌の生理特性（好気性）、人体水蒸気放出量、全熱/顕熱交換器および二重サッシ気密性の正誤判定 | G4: 湿気・結露や材料劣化に関する次の記述のうち，最も不適切なものはどれか。 | H4: ① 木材腐朽菌は，酸素の存在しない環境でしか生育できない嫌気性菌である。 | I4: ② 自然界では，褐色腐朽菌は針葉樹を侵すものが多く，白色腐朽菌は広葉樹を侵すものが多い。 | J4: ③ 環境温度20℃において，静座時に人体（成人男性）から放出される水蒸気量は，34 g/h・人程度である。 | K4: ④ 熱回収用熱交換器型換気装置は，水蒸気排出のためには全熱交換型よりも顕熱交換型の方がよい。 | L4: ⑤ 二重サッシを使用する場合，室内側のサッシができるだけ気密に，外気側は湿気が逃げやすい構造にする必要がある。 | M4: 結露・湿気・湿り空気
A5: H29-04 | B5: Ⅲ-4 | C5: 建築環境・設備・建築物衛生管理 | D5: 光・音 | E5: 4 | F5: 光束発散度、標準比視感度、逐点法、高圧水銀ランプ効率（ハロゲンより高効率）およびRaの正誤判定 | G5: 照明に関する次の記述のうち，最も不適切なものはどれか。 | H5: ① 出射する光束の密度を光束発散度 [rlx] という。 | I5: ② 光束は，単位時間当たりの光の放射エネルギーに，波長ごとの人間の視覚の感度である標準比視感度を乗じて求めた値である。 | J5: ③ 窓や照明器具など光源からの直接光による直接照度と，壁や家具での反射を経た間接光による間接照度をそれぞれ計算し，両者の和を全照度とする計算方法を逐点法という。 | K5: ④ 高圧水銀ランプのランプ効率 [lm/W] は，ハロゲンランプのランプ効率 [lm/W] よりも低い。 | L5: ⑤ 平均演色評価数Raは，15試験色のうち，1から8番目の試験色に関する特殊演色評価数の平均値で表される。 | M5: 照明・光環境
A6: H29-05 | B6: Ⅲ-5 | C6: 建築環境・設備・建築物衛生管理 | D6: 光・音 | E6: 4 | F6: 音速の温度依存、点音源の逆二乗則、オクターブ、壁透過損失と音響透過率および最適残響時間の正誤判定 | G6: 音に関する次の記述のうち，最も不適切なものはどれか。 | H6: ① 空気中の音速は，温度が高くなるにつれて速くなる。 | I6: ② 無指向性の点音源から発生する音の強さは，距離の2乗に逆比例する。 | J6: ③ 周波数が2倍の音は，元の音より1オクターブ音程が高く感じる。 | K6: ④ 透過率の高い壁の音響透過損失は大きい。 | L6: ⑤ 最適残響時間は，室の容積が大きいと一般に長くなる。 | M6: 音環境
A7: H29-06 | B7: Ⅲ-6 | C7: 建築環境・設備・建築物衛生管理 | D7: 温熱・省エネ指標 | E7: 1 | F7: 睡眠時代謝量（約70〜80W）、ウェーバー・フェヒナー法則、タバコ副流煙、clo値およびホルムアルデヒド指針値の正誤判定 | G7: 室内の熱・空気環境に関する次の記述のうち，最も不適切なものはどれか。 | H7: ① 睡眠時における体表面積1.7m²の成人男子の代謝率は100W程度である。 | I7: ② 人間の感覚を表す量（感覚量）は，もととなっているものの濃度やエネルギー量（物理量）と対数の関係にあることが多い。これをウェーバー・フェヒナーの法則という。 | J7: ③ タバコ煙は，主流煙，副流煙，吐出煙の3つに分類され，受動喫煙のもととなる副流煙と吐出煙を合わせて環境タバコ煙という。 | K7: ④ 衣服による断熱力（熱抵抗）として，clo（クロ）値が用いられ，その値は 1 [clo] ＝ 0.155 [m²・K/W] である。 | L7: ⑤ ホルムアルデヒドの室内許容濃度の指針値は，0.1mg/m³である。 | M7: 温熱環境・温熱指標
A8: H29-07 | B8: Ⅲ-7 | C8: 建築環境・設備・建築物衛生管理 | D8: 空調 | E8: 2 | F8: 吹出口・吸込口形状（ノズル形、パン形全周吹き、アネモスタット形、スロット形、ユニバーサル型）の原理判定 | G8: 吹出口及び吸込口に関する次の記述のうち，最も不適切なものはどれか。 | H8: ① ノズル形吹出口は，フェースのまったくない形で劇場などにおいて到達距離をふやすために吹出風速を 5 m/s 以上にして用いることができる。 | I8: ② パン形吹出口は，吹出口の方向を左右，上下に変えることができる首振り形のノズル形吹出口の1つで，厨房などのスポット冷房に適している。 | J8: ③ アネモスタット形吹出口は，吹出口の中で最も大きな誘引性能を有しており，吹出温度差をきわめて大きくとることができる。 | K8: ④ スロット形吹出口は，著しくアスペクト比の大きい吹出口で，体裁がよいので意匠を重視する室に多く使用されている。 | L8: ⑤ 固定羽根型吸込口又はユニバーサル型吸込口は，壁付及び天井付の吸込口として最も多く用いられている。 | M8: 空調機器・ダクト・熱源
A9: H29-08 | B9: Ⅲ-8 | C9: 建築環境・設備・建築物衛生管理 | D9: 換気・室内空気 | E9: 2 | F9: 室内の除湿器稼働・外気量・内外絶対湿度差条件に基づく室内水蒸気発生量W[g/h]の定型計算 | G9: 室内外の換気量が 100 m³/h のときに，室内の絶対湿度が 8 g/kg(DA) に保たれている状態での室内水蒸気発生量に最も近い値はどれか。ただし，室内は除湿器によって 50 g/h の除湿がなされており，室温と外気温度は共に20℃，外気絶対湿度が 3 g/kg(DA)，空気密度ρ＝1.2 kg(DA)/m³とする。 | H9: ① 1010 [g/h] | I9: ② 650 [g/h] | J9: ③ 600 [g/h] | K9: ④ 550 [g/h] | L9: ⑤ 470 [g/h] | M9: 換気・通風
A10: H29-09 | B10: Ⅲ-9 | C10: 建築環境・設備・建築物衛生管理 | D10: 空調 | E10: 2 | F10: モリエル（p-h）線図における圧縮式冷凍サイクルの各過程（圧縮・蒸発）識別と成績係数（COP）算定式 | G10: 次の記述の，[ ] に入る記号又は数式の組合せとして，最も適切なものはどれか。 下図のモリエ（モリエル）線図に示す圧縮式冷凍機の冷凍サイクルにおいて [ A ] は圧縮過程を [ B ] は蒸発過程をそれぞれ示しており，この冷凍サイクルの成績係数は [ C ] で表される。 | H10: ① A: 1 → 2 / B: 2 → 3 / C: (h3 - h2)/(h2 - h1) | I10: ② A: 2 → 3 / B: 1 → 2 / C: (h2 - h1)/(h3 - h2) | J10: ③ A: 2 → 3 / B: 3 → 4 / C: (h3 - h1)/(h3 - h2) | K10: ④ A: 3 → 4 / B: 1 → 2 / C: (h2 - h1)/(h3 - h1) | L10: ⑤ A: 3 → 4 / B: 2 → 3 / C: (h3 - h2)/(h3 - h1) | M10: 空調計算（負荷・空気線図・冷凍サイクル）
A11: H29-10 | B11: Ⅲ-10 | C11: 建築環境・設備・建築物衛生管理 | D11: 空調 | E11: 2 | F11: 除湿装置の方式分類（冷却式、吸着式（シリカゲル等）、圧縮式、吸収式）と原理・特徴の正誤判定 | G11: 除湿装置に関する次の記述のうち，最も不適切なものはどれか。 | H11: ① 冷却式除湿装置は機構が簡単で，設備費が安く，空気の露点温度が高い場合に有利である。 | I11: ② 吸収式除湿装置は，水分を吸着する性質を持つシリカゲル，活性アルミナ，合成ゼオライト，活性炭などの吸着剤を利用したものである。 | J11: ③ 圧縮式除湿装置は，空気を圧縮することによって水蒸気の分圧を増加させ，水蒸気の飽和点を超えさせて凝縮分離する方式であり，設備費及び運転費が高くなる。 | K11: ④ 冷却式除湿装置は，処理空気の温度低下と相対湿度の上昇を伴うため，これらが問題となる場合は，冷却除湿後の空気を加熱（再熱）する必要がある。 | L11: ⑤ 吸収式除湿装置は，大がかりな装置になることから特殊用途向けである。 | M11: 空調機器・ダクト・熱源
A12: H29-11 | B12: Ⅲ-11 | C12: 建築環境・設備・建築物衛生管理 | D12: 給排水・防災 | E12: 3 | F12: 給湯設備（返湯管複管式、ガス給湯器「号」定義、循環ポンプ設置位置（戻り配管）、スイベルジョイント、ベローズ型） | G12: 給湯設備に関する次の記述のうち，最も不適切なものはどれか。 | H12: ① 給湯栓を開けて即座に湯が必要になるホテルなどでは返湯管を設け，管内の湯を循環させて湯温を一定に保つことで湯待ち時間を小さくする複管式が用いられる。 | I12: ② ガス給湯器では能力表示に「号」を用いるが，1号は流量 1 [l/min] の水の温度を 25℃上昇させる能力である。 | J12: ③ 強制循環方式における循環ポンプは，一般に貯湯槽の直後の給湯管部分に設置する。 | K12: ④ スイベルジョイント工法とは，配管の分岐部に複数のエルボを組合せて用い，可とう性を持たせた配管工法である。 | L12: ⑤ ベローズ型伸縮継手とは，波型の管が伸縮動作を吸収する形式の継手である。 | M12: 給水・給湯
A13: H29-12 | B13: Ⅲ-12 | C13: 建築環境・設備・建築物衛生管理 | D13: 空調 | E13: 1 | F13: 風力発電出力（風速の3乗比例）、廃棄物発電、コージェネレーション、地域冷暖房(半径1km)および燃料電池の正誤判定 | G13: 省エネルギーシステムに関する次の記述のうち，最も不適切なものはどれか。 | H13: ① 風力発電システムの発電量は風速の2乗に比例し，年平均風速が 5 〜 6 m/s 以上あれば，経済的に引き合うとされている。 | I13: ② 家庭やビルから出るごみの焼却熱を利用して蒸気を発生させ，蒸気タービンなどの蒸気機関で発電するのが廃棄物発電である。 | J13: ③ ビルや工場などに都市ガスなどを燃料とするエンジン発電機を設置し，電気とともにエンジンの排熱を有効利用するのがコージェネレーションシステムである。 | K13: ④ 日本の地域冷暖房の熱供給エリアは，その配管コストや熱搬送動力の制約により，供給プラントから半径 1 km 程度以内に限られる。 | L13: ⑤ 燃料電池は，天然ガスなどの燃料の化学エネルギーを直接，電気エネルギーに変換する一次電池であり，その排熱も利用できる効率的な発電装置として注目されている。 | M13: 空調方式・省エネルギー
... A36: H29-35 | B36: Ⅲ-35 | C36: 廃棄物管理 | D36: 災害廃棄物・事業方式・統計・管理票 | E36: 5 | F36: ごみ処理施設整備におけるPFI事業手法（PFI推進法、PPP概念、BOO/BOT/BTO/DBO方式、官民リスク分担）の正誤判定 | G36: ごみ処理施設の施設整備事業方式であるPFI（Private Finance Initiative）事業方式に関する次の記述のうち，最も不適切なものはどれか。 | H36: ① 日本では，平成 9 年の緊急経済対策でPFIについて言及され，平成11年7月「民間資金等の活用による公共施設等の整備等の促進に関する法律（PFI推進法）」が成立した。 | I36: ② PFI事業は，公共事業を包括的に民間に委ね，長期的な契約の中で発生するリスクを官民で適切に分担し，良質で低廉な公共サービスを提供するという，新しいパートナーシップ（PPP：Public Private Partnership）の構築を前提とした事業手法である。 | J36: ③ PFIの事業方式には，BOO（Build Own Operate）方式やBOT（Build Operate Transfer）方式，BTO（Build Transfer Operate）方式等がある。 | K36: ④ DBO（Design Build Operate）方式は，自治体が民間資金によらず従来のような，公共側の財源によって施設を建設・所有する方式である。この方式は準PFI事業ともいわれている。 | L36: ⑤ PFI事業では，事業関係者のリスク分担を適切かつ明確に決めておく必要がある。住民問題リスクや法令変更リスクは，民の分担となる。 | M36: 施設整備事業方式（PFI・DBO）

Sheet H28(平成28年度)問題・選択肢
A1: 問題ID | B1: 設問番号 | C1: 大分類(ブロック) | D1: サブジャンル | E1: 公式正答 | F1: 問題のテーマ・内容概要 | G1: 問題文 | H1: 選択肢① | I1: 選択肢② | J1: 選択肢③ | K1: 選択肢④ | L1: 選択肢⑤ | M1: 出題論点（細目）
A2: H28-01 | B2: Ⅲ-1 | C2: 建築環境・設備・建築物衛生管理 | D2: 温熱・省エネ指標 | E2: 5 | F2: 室内上下温度差、PMV・PPD関係、不均一放射上限および床暖房表面温度上限に関する正誤判定 | G2: 温熱環境の評価に関する次の記述のうち，最も不適切なものはどれか。 | H2: ① 室内上下温度差は，床上1.1mと0.1mとの温度差を3℃以内に収めることが推奨されている。 | I2: ② PMV（予想平均温冷感申告）が -0.5 < PMV < +0.5 となる場合，PPD（予想不満足者率）については PPD < 10% となる。 | J2: ③ 不均一放射環境に関する許容範囲として，冷たい天井に対する不快感は少ないが，暖かい天井に対する不均一限界は5℃以内とされている。 | K2: ④ ドラフトによる不快感については，乱れの強さが大きければ，低い平均風速でも不快に感じるとしている。 | L2: ⑤ 床暖房では低温やけどを防止するため，床表面温度の上限は体表面温度に近い35℃とすることが望ましい。 | M2: 温熱環境・温熱指標
A3: H28-02 | B3: Ⅲ-2 | C3: 建築環境・設備・建築物衛生管理 | D3: 光・音 | E3: 2 | F3: 明順応・暗順応、暗所視比視感度シフト（プルキンエ現象）、直接グレアおよび基準開口率の正誤判定 | G3: 光環境に関する次の記述のうち，最も不適切なものはどれか。 | H3: ① ヒトの視覚において，明順応に比べて，暗順応は時間がかかる。 | I3: ② ヒトの視覚において，暗所視では，比視感度が最大になる波長が長い方にずれる。 | J3: ③ 直接グレアの防止の基本は，前方視野角の30°以内に高輝度光源を露出させないことである。 | K3: ④ 建築基準法における教室（幼稚園・小学校・中学校・高等学校又は中等教育学校）の採光のための窓その他の開口部の採光に有効な部分の面積は，床面積の1／5以上である。 | L3: ⑤ 照明設計における明視の条件は，視角が大きいこと，対比の大きいこと，動きのないこと，明るいことであるが，特に明るさが重要である。 | M3: 照明・光環境
A4: H28-03 | B4: Ⅲ-3 | C4: 建築環境・設備・建築物衛生管理 | D4: 熱・湿気 | E4: 2 | F4: 自然対流熱伝達率、窓ガラスの放射透過・反射特性、総合熱伝達率および相当外気温度に関する正誤判定 | G4: 熱移動に関する次の記述のうち，最も不適切なものはどれか。 | H4: ① 建築室内における自然対流熱伝達率は，壁表面と室内空気温の温度差によって変化する。 | I4: ② 通常の窓ガラスは日射の大部分を透過し，常温放射の大部分を反射する。 | J4: ③ 室内側総合熱伝達率と外気側総合熱伝達率の差は，主に対流熱伝達率の違いによる。 | K4: ④ 放射は電磁波によるエネルギー移動の1プロセスであり，絶対温度以上の物体はすべて放射エネルギーを放出している。 | L4: ⑤ 外壁面の相当外気温度は，外壁面の実効（夜間）放射量が大きいほど低下する。 | M4: 伝熱・断熱
A5: H28-04 | B5: Ⅲ-4 | C5: 建築環境・設備・建築物衛生管理 | D5: 光・音 | E5: 4 | F5: コインシデンス周波数、質量則（6dB法則）、床衝撃音レベルL値および重量/軽量床衝撃音対策の正誤判定 | G5: 遮音に関する次の記述のうち，最も不適切なものはどれか。 | H5: ① コインシデンス効果を生じる周波数は，入射波の角度が90°のときに最小となる。 | I5: ② 壁体の面密度が2倍あるいは周波数が2倍になるごとに，透過損失は6dB増加する。 | J5: ③ 床衝撃音レベルL-45の床は，L-60の床よりも床衝撃に対する遮音性能は高い。 | K5: ④ 重量床衝撃音に対する対策には，カーペットや畳などの緩衝性の材料が効果的である。 | L5: ⑤ 透明ガラスを2重〜3重にはめ殺しにした遮音窓は，できるだけ空気層を厚くとり，その吸音特性を空気層の共鳴周波数に同調させるとよい。 | M5: 音環境
A6: H28-05 | B6: Ⅲ-5 | C6: 建築環境・設備・建築物衛生管理 | D6: 光・音 | E6: 2 | F6: 温室効果ガス、日本標準時・東京の南中時、日照率定義、天空日射量および低鉄分ガラス透過率の正誤判定 | G6: 日照・日射に関する次の記述のうち，最も不適切なものはどれか。 | H6: ① 大気中の水蒸気や炭酸ガス，雲などの長波長放射を吸収する特性が，大気の温室効果の原因となっている。 | I6: ② 日本では東経135°（明石）を日本中央標準時の拠点に定めているが，東京は明石よりも遅く南中時を迎える。 | J6: ③ 日照時間の可照時間に対する比を百分率で表したものを日照率という。 | K6: ④ 日射が大気中で散乱されたのち，全天空から地表に到達する成分を天空日射量又は拡散日射量という。 | L6: ⑤ 低鉄分ガラスは日射透過率が大きい。 | M6: 日照・日射・採光
A7: H28-06 | B7: Ⅲ-6 | C7: 建築環境・設備・建築物衛生管理 | D7: 換気・室内空気 | E7: 1 | F7: 有効開口面積αA1・αA2が異なる2つの開口部を持つ単室建物の中性帯距離比H1:H2計算 | G7: 下図に示すように単室の建物に2つの開口がある。各々の有効開口面積を αA₁ = 0.1m², αA₂ = 0.05m², この2つの開口以外に隙間も含めて開口はないものとする。中性帯の位置からの距離 H₁, H₂ の比（H₁ : H₂）は次のうちどれか。 | H7: ① 1 : 4 | I7: ② 1 : 2 | J7: ③ 1 : 1 | K7: ④ 2 : 1 | L7: ⑤ 4 : 1 | M7: 換気・通風
A8: H28-07 | B8: Ⅲ-7 | C8: 建築環境・設備・建築物衛生管理 | D8: 温熱・省エネ指標 | E8: 2 | F8: 外皮平均熱貫流率UA、平均日射熱取得率ηA（外皮面積除算）、PAL*（潜熱評価）および一次エネルギーの正誤判定 | G8: 建築物の省エネルギー性能指標に関する次の記述のうち，最も不適切なものはどれか。 | H8: ① 外皮平均熱貫流率（UA）は，室内外の温度差が1℃のときの建物全体の外皮で生じる総熱損失量を外皮（外壁や窓等）の表面積の合計で除して算出される。 | I8: ② 住宅における冷房期の平均日射熱取得率（ηA）は，冷房期の総日射熱取得量を床面積で除して算出される。 | J8: ③ 外皮基準の指標である従来の年間熱負荷係数（PAL）に対し，新しい年間熱負荷係数（PAL*）は潜熱負荷を含めて評価している。 | K8: ④ 非住宅建築物の暖冷房負荷の算出においては，取入外気の熱についても勘案する必要がある。 | L8: ⑤ 一次エネルギーとは，化石燃料，原子力燃料，水力，太陽光など自然から得られるエネルギーのことをいう。 | M8: 省エネ性能指標・都市建築環境
A9: H28-08 | B9: Ⅲ-8 | C9: 建築環境・設備・建築物衛生管理 | D9: 給排水・防災 | E9: 5 | F9: 水道の定義、給水装置、給水方式区分、水道の三要素および末端遊離残留塩素基準(0.1mg/L)の正誤判定 | G9: 上水道に関する次の記述のうち，最も不適切なものはどれか。 | H9: ① 水道は，水を人の飲用に適する水として供給する施設の総称である。 | I9: ② 配水管から分岐した給水管，止水栓，量水器及びこれに直結する給水栓などの給水用具を給水装置と呼ぶ。 | J9: ③ 給水方式は，水道直結方式と受水槽方式の2つに区分される。 | K9: ④ 需要者が満足する水量，飲料水の水質基準への適合，適度な水圧の保持を水道に求められる三要素という。 | L9: ⑤ 水道水は，末端給水栓において0.01mg/L以上の遊離残留塩素を保持していなくてはならない。 | M9: 給水・給湯
A10: H28-09 | B10: Ⅲ-9 | C10: 建築環境・設備・建築物衛生管理 | D10: 空調 | E10: 4 | F10: 静圧再取得法、ダクト摩擦抵抗線図、アスペクト比影響および等摩擦法での抵抗調整の正誤判定 | G10: 空調ダクトに関する次の記述のうち，最も不適切なものはどれか。 | H10: ① ダクトが分岐するごとに風速が減少し，それによって再生される静圧を次の区間の圧力損失に利用する方法を静圧再取得法という。 | I10: ② ダクト風量［m³/h］，目標摩擦損失［Pa/m］を設定すれば，ダクトの摩擦抵抗線図を用いて必要な円ダクトの直径［mm］と断面風速［m/s］を知ることができる。 | J10: ③ 空調換気用ダクトの断面積が等しくても，アスペクト比が異なれば，ダクトの摩擦抵抗は異なる。 | K10: ④ 等摩擦法では送風機から各吹出し口までの経路の長さが異なる場合は，長さの短いダクト断面の縦又は横の寸法を大きくするなどして抵抗を調整する必要がある。 | L10: ⑤ ダクトの断面積の変化に応じて生じる動圧の変化量の絶対値は，静圧の変化量の絶対値に等しい。 | M10: 空調機器・ダクト・熱源
A11: H28-10 | B11: Ⅲ-10 | C11: 建築環境・設備・建築物衛生管理 | D11: 換気・室内空気 | E11: 5 | F11: 建築基準法必要換気量(20m3/h・人)、風による換気力、CO2発生量、第3種換気甲/乙種および平均空気齢定義の正誤判定 | G11: 換気に関する次の記述のうち，最も不適切なものはどれか。 | H11: ① 建築物における衛生的な環境の確保に関する法律が適用されない建物での在室人員に必要な新鮮空気を導入する換気は，建築基準法において20［m³／（h・人）］以上と規定されている。 | I11: ② 風による換気力は，空気自体の持つ運動エネルギーに建物の形状により決まる風圧係数を乗じて求めることができる。 | J11: ③ 人体からのCO₂発生量は安静時で0.013［m³／（h・人）］程度，事務作業時で0.02［m³／（h・人）］程度である。 | K11: ④ 第三種換気とは自然給気と機械排気による換気であり，自然給気が直接的に外気を導入する場合を第三種換気の甲種，自然給気が間接的に外気を導入する場合を第三種換気の乙種と分類する。 | L11: ⑤ 平均空気齢とは，空気が吹出口から排気口に至るまでの平均時間である。 | M11: 換気・通風
A12: H28-11 | B12: Ⅲ-11 | C12: 建築環境・設備・建築物衛生管理 | D12: 空調 | E12: 5 | F12: 水冷式/空冷式COP比較、吸収冷凍機（水/臭化リチウム）、ターボ冷凍機、吸収冷凍メリットおよびレシプロ冷凍機の正誤判定 | G12: 熱源装置に関する次の記述のうち，最も不適切なものはどれか。 | H12: ① 各種電動冷凍機の定格時成績係数は，水冷式の方が空冷式よりも大きい。 | I12: ② 吸収冷凍機では一般に冷媒として水，吸収剤として臭化リチウム溶液が用いられている。 | J12: ③ 遠心冷凍機はターボ冷凍機とも呼ばれ，羽根車の回転による遠心力で冷媒を圧縮するもので，空調用としては大容量の場合に多く用いられている。 | K12: ④ 吸収冷凍の特徴は圧縮機に比べて電力消費量が少なく，騒音・振動も小さい。しかし，形状や重量は大きく，冷却塔の容量も大きくなる。 | L12: ⑤ レシプロ冷凍機は回転型圧縮機の一種で，中・大容量のヒートポンプなどに多く用いられている。 | M12: 空調機器・ダクト・熱源
A13: H28-12 | B13: Ⅲ-12 | C13: 建築環境・設備・建築物衛生管理 | D13: 給排水・防災 | E13: 3 | F13: 開放式/密閉式ポンプ動力、二方弁制御、Darcy-Weisbachの管摩擦係数比例関係およびリバースリターンの正誤判定 | G13: 建築設備の水配管に関する次の記述のうち，最も不適切なものはどれか。 | H13: ① 開放式は必ず摩擦抵抗のほかに押し上げ揚程が加わり，密閉式に比べてポンプ動力が大きくなる。 | I13: ② 二方弁制御は三方弁制御に比べて一般に制御性が良く，ポンプの台数制御などによりポンプの消費電力を節約できる。 | J13: ③ 満水状態で流体が流れる場合の直管部摩擦抵抗は，管の長さと流体の密度及び流速の2乗に比例し，管の内径と管摩擦係数に反比例する。 | K13: ④ リバースリターン方式では，各機器を通る配管長さが等しく，抵抗が同じとなるために，流量が自然に均一になるという特徴がある。 | L13: ⑤ 建築設備の水配管の流速は，流体の種類，配管の材質，口径，経済性，省エネルギー性などを考慮して決められる。 | M13: 給水・給湯
... A36: H28-35 | B36: Ⅲ-35 | C36: 廃棄物管理 | D36: 法制度・リサイクル・循環型社会 | E36: 3 | F36: 生活環境影響調査の全施設義務付け、縦覧・意見聴取手続き、調査事項（悪臭除外は誤り）、地下水調査除外条件および変更許可要件の正誤判定 | G36: 「廃棄物処理施設生活環境影響調査指針」に関する次の記述のうち，最も不適切なものはどれか。 | H36: ① 生活環境影響調査は，許可を要するすべての廃棄物処理施設について実施が義務付けられている。 | I36: ② 廃棄物処理施設のうち，焼却施設及び最終処分場については，申請書提出後，知事により申請書及び生活環境影響調査書が縦覧され，住民，市町村長の意見聴取，専門家の意見聴取等の手続が行われる。 | J36: ③ 生活環境影響調査の対象とする調査事項は，廃棄物処理施設の稼働等に伴って生じる生活環境への影響に関するもので，大気質，騒音，振動，水質及び地下水であり，悪臭は含まれない。 | K36: ④ 地下水の調査については，中間処理施設であって，施設からの排水を適切に処理して河川等の公共用水域に放流し，かつ十分に希釈される場合は不要となることがある。 | L36: ⑤ 生活環境影響調査は，廃棄物処理施設の変更の許可を受ける場合にも必要である。 | M36: 廃棄物処理法・制度・処理施設・その他

Sheet H27(平成27年度)問題・選択肢
A1: 問題ID | B1: 設問番号 | C1: 大分類(ブロック) | D1: サブジャンル | E1: 公式正答 | F1: 問題のテーマ・内容概要 | G1: 問題文 | H1: 選択肢① | I1: 選択肢② | J1: 選択肢③ | K1: 選択肢④ | L1: 選択肢⑤ | M1: 出題論点（細目）
A2: H27-01 | B2: Ⅲ-1 | C2: 建築環境・設備・建築物衛生管理 | D2: 熱・湿気 | E2: 3 | F2: 伝熱・物質伝達(住戸内の絶対湿度はほぼ一様→不適) | G2: 伝熱・物質伝達に関する次の記述のうち，最も不適切なものはどれか。 | H2: ① 全ての物体は，絶対温度でない限りその温度に応じた放射エネルギーを出しており，その放射量は絶対温度の4乗に比例する。 | I2: ② 同一波長に対して放射率と吸収率が等しくなる性質を，キルヒホッフの法則という。 | J2: ③ 濡れた物体表面から周囲空気へ水が蒸発するプロセスは対流熱伝達と相似性があるが，これをフィックの法則という。 | K2: ④ 室内の対流熱伝達率は，暖房時の天井面と冷房時の床面は大きく，冷房時の天井面と暖房時の床面は小さい値が用いられる。 | L2: ⑤ ドアや襖で仕切られていても水蒸気は容易に隣室に拡散するため，住戸内はほぼ一様な絶対湿度になる。 | M2: 伝熱・断熱
A3: H27-02 | B3: Ⅲ-2 | C3: 建築環境・設備・建築物衛生管理 | D3: 光・音 | E3: 2 | F3: 光・色彩(加法混色の三原色は赤・緑・青) | G3: 光・色彩に関する次の記述のうち，最も不適切なものはどれか。 | H3: ① 長年紫外線を浴び続けた結果，高齢者の水晶体は特に500 nm以下の短波長である青色光領域の透過率の低下が著しくなる。 | I3: ② 加法混色の三原色は，青緑，赤紫，黄である。 | J3: ③ JISに採用されているマンセル表色系は，ヒュー（Hue），バリュー（Value），クロマ（Chroma）の3属性で表される。 | K3: ④ 色票を用いた視感による測色は，光源に対する注意や面積効果を排除するなどの注意が必要である。 | L3: ⑤ 赤と緑のように色相が相反していても，明度が同程度に見えにくくなる現象をリープマン効果という。 | M3: 照明・光環境
A4: H27-03 | B4: Ⅲ-3 | C4: 建築環境・設備・建築物衛生管理 | D4: 換気・室内空気 | E4: 3 | F4: トレーサーガス法 | G4: 空間内において，瞬時一様拡散が仮定できる状況下で人為的にガスを発生させ，その濃度を測定するトレーサーガス法に関する次の記述のうち，最も不適切なものはどれか。 | H4: ① トレーサーガスを空間内に一定割合で人為的に連続放出し，その定常状態の濃度を測定することで，換気量を得ることができる。 | I4: ② トレーサーガス法は，トレーサーガスが空間の壁などに吸われたり，付着したりしないことを仮定している。 | J4: ③ トレーサーガス法は，空間の開口部や隙間が数多く分散しており，そこでの空気の流出入が不明確であるような自然換気の測定には用いることができない。 | K4: ④ トレーサーガスを空間内に放出し，均一な濃度分布を達成した後の濃度変化を測定することで，換気量を得ることができる。 | L4: ⑤ トレーサーガスには，空気と比重が比較的近く，濃度測定が簡易なガスが用いられる。 | M4: 換気・通風
A5: H27-04 | B5: Ⅲ-4 | C5: 建築環境・設備・建築物衛生管理 | D5: 熱・湿気 | E5: 4 | F5: 結露防止(非暖房室のみ排気ファン→不適) | G5: 結露防止対策に関する次の記述のうち，最も不適切なものはどれか。 | H5: ① 建物の出隅部分の室内側では，断熱を強化する。 | I5: ② 気密性が高い建物では，機械換気設備などで十分な換気を行う。 | J5: ③ 食堂の換気には，全熱回収型より顕熱回収型換気扇を用いる。 | K5: ④ 非暖房室で表面結露が発生するので，当該空間にのみ排気ファンを設置した。 | L5: ⑤ 外気に接する壁に家具を設置する場合，壁からの距離を確保する。 | M5: 結露・湿気・湿り空気
A6: H27-05 | B6: Ⅲ-5 | C6: 建築環境・設備・建築物衛生管理 | D6: 光・音 | E6: 5 | F6: 採光・照明 | G6: 採光・照明に関連する次の記述のうち，最も不適切なものはどれか。 | H6: ① 蛍光高圧水銀ランプは，白熱電球よりも一般に効率が高い。 | I6: ② 作業周辺部の照度が500 lxのとき，作業面照度は750 lx以上とする。 | J6: ③ 出射する光束の，反射面の単位面積当たり単位立体角当たりの大きさを，輝度という。 | K6: ④ 昼光率は，正確には天空輝度分布の形によって異なるが，屋外の昼光の変動に関わらず，ほぼ一定と考えてよい。 | L6: ⑤ 直射日光の色温度より，曇天光の色温度の方が低い。 | M6: 日照・日射・採光
A7: H27-06 | B7: Ⅲ-6 | C7: 建築環境・設備・建築物衛生管理 | D7: 光・音 | E7: 2 | F7: 残響時間の計算(壁のみ吸音率0.1→0.25) | G7: 間口5 m，奥行き5 m，天井高さ3 m，吸音率0.1の内装で作られた直方体の室がある。この室の残響時間は1.1秒であった。次に，内装のうち壁のみを吸音率0.25の材料に変更した。変更後の室の残響時間はおよそ何秒になるか。 | H7: ① 0.4秒 | I7: ② 0.6秒 | J7: ③ 0.8秒 | K7: ④ 2.4秒 | L7: ⑤ 2.7秒 | M7: 音環境
A8: H27-07 | B8: Ⅲ-7 | C8: 建築環境・設備・建築物衛生管理 | D8: 空調 | E8: 5 | F8: 湿り空気の比エンタルピー差の計算 | G8: 湿り空気の比エンタルピーhは次の式で表せる。 h = 1.0 t + (2500 + 1.8 t) x [kJ/kg(DA)] ただし， t : 乾球温度 [℃] x : 絶対湿度 [kg/kg(DA)] kg(DA) : 乾き空気の質量 乾き空気1000 kg(DA)を含む，乾球温度7 ℃，絶対湿度0.004 kg/kg(DA)の湿り空気を，蒸気で加熱・加湿し，乾球温度36 ℃，絶対湿度0.014 kg/kg(DA)としたときの空気の得た熱量の値として，最も適切なものはどれか。 | H8: ① 26 kJ | I8: ② 29 kJ | J8: ③ 55 kJ | K8: ④ 26 MJ | L8: ⑤ 55 MJ | M8: 空調計算（負荷・空気線図・冷凍サイクル）
A9: H27-08 | B9: Ⅲ-8 | C9: 建築環境・設備・建築物衛生管理 | D9: 給排水・防災 | E9: 2 | F9: 給排水設備 | G9: 給排水設備に関する次の記述のうち，最も不適切なものはどれか。 | H9: ① 給水管の圧力損失は，管内摩擦と形状抵抗の両者によるが，いずれも流速の2乗に比例して増大する。 | I9: ② 大便器に使用する洗浄弁（フラッシュバルブ）の必要圧力は，ゲージ圧で0.7 MPa以上である。 | J9: ③ 受水槽は点検のため，上部には1 m以上，周囲・下部には0.6 m以上のスペースを設けなくてはならない。 | K9: ④ 給水系統への逆サイホン作用による汚染水の逆流を防止するために，洗面器に吐水口空間（エアギャップ）を設ける。 | L9: ⑤ トラップの最小封水深は50 mmが基準となる。 | M9: 排水・通気・衛生器具
A10: H27-09 | B10: Ⅲ-9 | C10: 建築環境・設備・建築物衛生管理 | D10: 空調 | E10: 5 | F10: 省エネ設備機器 | G10: 省エネルギー設備機器に関する次の記述のうち，最も不適切なものはどれか。 | H10: ① 空気調和機に使用する全熱交換器では，外気冷房が可能なときに給排気バイパスなどにより熱交換を回避する。 | I10: ② 夜間電力利用の蓄熱槽システムでは，熱源の夜間運転時間が長いほど，熱源容量は小さくて済む。 | J10: ③ 蓄熱槽は開放水面を有し，配管経路が開放方式となるため，密閉回路方式に比べて，ポンプ動力が一般的に増大する。 | K10: ④ 多結晶シリコン太陽電池は，単結晶シリコン太陽電池と比較して変換効率が低いが，製造が容易で効率とコストのバランスが良いため，よく普及している太陽電池である。 | L10: ⑤ ヒートポンプの冷房時の成績係数（COP）は，圧縮仕事に対する凝縮熱量の比で表す。 | M10: 空調方式・省エネルギー
A11: H27-10 | B11: Ⅲ-10 | C11: 建築環境・設備・建築物衛生管理 | D11: 空調 | E11: 2 | F11: 空調方式(2管式・4管式の定義) | G11: 空調方式に関する次の記述のうち，最も不適切なものはどれか。 | H11: ① 床吹出し空調はダクトレスシステムであり，温度成層を容認して居住地域のみを快適な熱環境にしようとする方式である。 | I11: ② 冷水管と温水管を別々に設け，年間にわたって随時冷房・暖房を可能とするファンコイルユニット方式を2管式という。 | J11: ③ ユニタリ方式の一つであるマルチユニット型ヒートポンプ方式は，1台の室外機で数台の室内機を作動させることができる。 | K11: ④ パーソナル空調の実現には建築と空調とのインテグレーション，家具と建築とのインテグレーションなどの計画が必要となる。 | L11: ⑤ 二重ダクト方式は室に対して冷風ダクトと温風ダクトの二重の給気ダクトを設け，混合ユニットにより冷風と温風を混合して室内に吹出す方式である。 | M11: 空調方式・省エネルギー
A12: H27-11 | B12: Ⅲ-11 | C12: 建築環境・設備・建築物衛生管理 | D12: 空調 | E12: 2 | F12: 吹出口・吸込口(アネモスタット) | G12: 吹出口及び吸込口に関する次の記述のうち，最も不適切なものはどれか。 | H12: ① ノズル形吹出口は，フェースのまったくない形で劇場などにおいて到達距離を増やすために吹出風速を5 m/s以上にして用いることができる。 | I12: ② パン形吹出口は，吹出口の方向を左右，上下に変えることができる首振り形のノズル形吹出口の1つで，厨房などのスポット冷房に適している。 | J12: ③ アネモスタット形吹出口は，吹出口のなかで最も大きな誘引性能を有しており，送風温度と室温との温度差を大きくとることができる。 | K12: ④ スロット形吹出口は，著しくアスペクト比の大きい吹出口で，体裁が良いので意匠を重視する室に多く使用されている。 | L12: ⑤ 固定羽根型吸込口又はユニバーサル型吸込口は，壁付及び天井付の吸込口として最も多く用いられている。 | M12: 空調機器・ダクト・熱源
A13: H27-12 | B13: Ⅲ-12 | C13: 建築環境・設備・建築物衛生管理 | D13: 給排水・防災 | E13: 1 | F13: 消火設備(連結送水管・泡・SP・粉末・ドレンチャ) | G13: 消火設備に関する次の記述のうち，最も不適切なものはどれか。 | H13: ① 連結送水管は，火災時に消防隊による消防活動が困難な地下の消火活動に必要な設備であり，送水口から地階の天井に設置した散水ヘッドに送水する配管設備である。 | I13: ② 泡消火設備は，油火災のように注水による消火方法では火災が拡大するような施設，具体的には駐車場や飛行機の格納庫などに設置される。 | J13: ③ スプリンクラー設備は，火災発生時に火災を感知し，天井面に設置したスプリンクラーヘッドから自動的に散水して初期消火を行うものである。 | K13: ④ 粉末消火設備は，重炭酸ナトリウムなどの粉末を使用した負触媒効果により消火する設備で，消火剤が粉末のため凍結しないので寒冷地に適している。 | L13: ⑤ ドレンチャー消火設備は，建物外部の火災に対し，外壁，屋根，開口部に水幕をつくって延焼を防ぐための設備である。 | M13: 防災・排煙・消火
... A36: H27-35 | B36: Ⅲ-35 | C36: 廃棄物管理 | D36: 最終処分場・浸出水 | E36: 3 | F36: 最終処分場の主な施設(浸出水調整池) | G36: 一般廃棄物最終処分場及び産業廃棄物管理型最終処分場の主な施設に関する次の記述のうち，最も不適切なものはどれか。 | H36: ① 貯留構造物には，コンクリート型式と土堰堤型式などがある。 | I36: ② 遮水工は地下水汚染防止の目的で設置されるものであり，表面遮水工と鉛直遮水工がある。 | J36: ③ 浸出水調整池の容量は降水量をもとに設定するが，調整池の容量が過大にならないように，積極的に埋立地の内部貯留を利用することが望ましい。 | K36: ④ 浸出水集排水施設とは，浸出水を速やかに集水し排水する機能と埋立地内の好気性ゾーンを拡大する機能を持つものである。 | L36: ⑤ 地下水により遮水工が損傷するおそれがある場合には，地下水を有効に集め，排出することができる地下水集排水設備を設ける。 | M36: 最終処分場・浸出水

Sheet H26(平成26年度)問題・選択肢
A1: 問題ID | B1: 設問番号 | C1: 大分類(ブロック) | D1: サブジャンル | E1: 公式正答 | F1: 問題のテーマ・内容概要 | G1: 問題文 | H1: 選択肢① | I1: 選択肢② | J1: 選択肢③ | K1: 選択肢④ | L1: 選択肢⑤ | M1: 出題論点（細目）
A2: H26-01 | B2: Ⅲ-1 | C2: 建築環境・設備・建築物衛生管理 | D2: 光・音 | E2: 1 | F2: 点光源の水平面照度計算(180cd,3m,30°) | G2: 下図に示す点光源に照らされたA点の水平面照度に最も近い値はどれか。ただし，点光源の配光特性は一様なものとし，反射は考慮しないものとする。［図：点光源の光度180cd，床面からの高さ3m，A点は点光源から見て水平面に対し30°の位置］ | H2: ① 2.5 lx | I2: ② 3.3 lx | J2: ③ 4.3 lx | K2: ④ 5.0 lx | L2: ⑤ 20.0 lx | M2: 照明・光環境
A3: H26-02 | B3: Ⅲ-2 | C3: 建築環境・設備・建築物衛生管理 | D3: 温熱・省エネ指標 | E3: 4 | F3: 都市・建築環境(代替フロンはCO2より温室効果が大きい) | G3: 都市・建築環境に関する次の記述のうち，最も不適切なものはどれか。 | H3: ① 都市の緑化は，気温低減，保水による水循環改善，吸音，喧噪感の低減など，多面的な環境改善に役立つ。 | I3: ② 市街地の風の鉛直分布は，地表面の建物，障害物によって変化し，建物が立ち並ぶ街区などの風速は上空風速と比べて小さい。ただし，いわゆるビル風は除くものとする。 | J3: ③ 建築に関わるCO2発生量は，建設時のものだけでなく，運用・解体までのライフサイクル全体を評価する必要がある。 | K3: ④ 代替フロンは自然冷媒である二酸化炭素と比較して，大気中の濃度当たりの温室効果の強さは小さい物質である。 | L3: ⑤ ヒートアイランドは都市域の多大な排熱と，コンクリートジャングルに代表される熱放散の起こりにくい都市構造との相乗効果で発生する。 | M3: 省エネ性能指標・都市建築環境
A4: H26-03 | B4: Ⅲ-3 | C4: 建築環境・設備・建築物衛生管理 | D4: 換気・室内空気 | E4: 3 | F4: 室内微生物(汚染は時間的・空間的変動が大) | G4: 室内空気中の微生物（細菌・真菌）とそれによる汚染に関する次の記述のうち，最も不適切なものはどれか。 | H4: ① 微生物による汚染の程度は，空中濃度，表面汚染量，落下量で表される。 | I4: ② 住宅において真菌（カビ）には，外気の導入に伴って室内に侵入するものと室内に棲みついているものがある。 | J4: ③ 微生物汚染は温湿度環境，空気清浄装置の有無，換気の条件によらず，時間的・空間的な汚染状況の変化は緩やかであり，汚染の程度は年間を通じて一定である。 | K4: ④ 室内における微生物汚染の対象になる細菌，真菌の種類は極めて多い。 | L4: ⑤ 浮遊微生物のサンプリング装置は主に衝突法によるものとフィルタ法によるものがある。 | M4: 室内空気質・健康影響・衛生動物
A5: H26-04 | B5: Ⅲ-4 | C5: 建築環境・設備・建築物衛生管理 | D5: 換気・室内空気 | E5: 2 | F5: 人体と水(女性は脂肪が多く水分割合は低い) | G5: 人体と水に関する次の記述のうち，最も不適切なものはどれか。 | H5: ① 人体の体重当たりの水分の割合は，新生児では体重の約75%，子どもでは約70%，成人では約60〜65%，老人では約50〜55%である。 | I5: ② 一般に女性の方が男性よりも脂肪が多いので，体重当たりの水分の割合が高い傾向がある。 | J5: ③ 体内の水が不足する脱水症状を起こすと，体温を調整する汗が出なくなり，体温が上昇する。 | K5: ④ 代謝水（又は燃焼水）とは，体内でタンパク質や炭水化物，脂肪などが酵素によって分解されるときに排出される水分のことをいう。 | L5: ⑤ 正常な成人が一日に補給すべき必要最低限の水分量は，飲料水など飲み物として約1.3〜1.5リットル/人・日といわれている。 | M5: 室内空気質・健康影響・衛生動物
A6: H26-05 | B6: Ⅲ-5 | C6: 建築環境・設備・建築物衛生管理 | D6: 換気・室内空気 | E6: 2 | F6: ねずみ防除・IPM | G6: 建築物におけるねずみ等の防除に関する次の記述のうち，最も不適切なものはどれか。 | H6: ① 建築物におけるねずみ等の防除は，その発生及び侵入の防止並びに駆除により行う。 | I6: ② ねずみ等の防除のために殺そ剤又は殺虫剤を使用する場合，薬事法の承認を受けた医薬品以外を用いてはならない。 | J6: ③ IPM（総合有害生物管理，以下同じ。）では，的確に発生の実態を把握するため，措置前に生息密度調査法に基づく生息実態調査を実施する。 | K6: ④ IPMでは，調査から得られた捕獲指数などをもとに，該当建築物又は該当場所に「許容水準」「警戒水準」「措置水準」の目標水準を設定する。 | L6: ⑤ IPMでは，標準的な目標水準に照らして，有害生物の密度と防除効果の観点から評価を行う。 | M6: 室内空気質・健康影響・衛生動物
A7: H26-06 | B7: Ⅲ-6 | C7: 建築環境・設備・建築物衛生管理 | D7: 温熱・省エネ指標 | E7: 2 | F7: 省エネ指標(ηAC=冷房期平均日射熱取得率) | G7: 住宅と建築物の省エネルギー性能指標に関する次の記述のうち，最も不適切なものはどれか。 | H7: ① 外皮平均熱貫流率（UA）は，室内外の温度差が1℃のときの建物全体の外皮で生じる総熱損失量を外皮（外壁や窓等）の表面積の合計で除して算出される。 | I7: ② 住宅における冷房期の平均日射熱取得率（ηA）は，冷房期の総日射熱取得量を床面積で除して算出される。 | J7: ③ 外皮基準の指標である従来の年間熱負荷係数（PAL）に対し，年間熱負荷係数（PAL*）は潜熱負荷を含めて評価している。 | K7: ④ 非住宅建築物の暖冷房負荷の算出においては，取入外気の熱についても勘案する必要がある。 | L7: ⑤ 一次エネルギーとは，自然界に存在するままの形でエネルギー源として利用される化石燃料や自然エネルギー等によるエネルギーのことをいう。 | M7: 省エネ性能指標・都市建築環境
A8: H26-07 | B8: Ⅲ-7 | C8: 建築環境・設備・建築物衛生管理 | D8: 温熱・省エネ指標 | E8: 5 | F8: 建物の温熱環境(相当外気温) | G8: 建物の温熱環境に関する次の記述のうち，最も不適切なものはどれか。 | H8: ① 内断熱は蓄熱負荷を小さく抑え，予熱時には，室温及び壁体の室内表面温度を速やかに所定のレベルに到達させることができる。 | I8: ② ナイトパージにより外気を室内に導入し，外気が保持する冷熱を躯体に蓄熱させ，昼間の冷房の用に供することができる。 | J8: ③ 物体間の放射による熱移動量は，それぞれの物体表面の絶対温度の4乗の差に比例する。 | K8: ④ 相当外気温度とは，外壁面に当たる日射量の影響を見込むため，日射量を等価な温度に換算し外気温に加えた温度である。 | L8: ⑤ 高天井のアトリウムの冷房では，空気による熱供給を居住域にとどめることが困難なので，床面からの放射冷房が適している。 | M8: 温熱環境・温熱指標
A9: H26-08 | B9: Ⅲ-8 | C9: 建築環境・設備・建築物衛生管理 | D9: 空調 | E9: 1 | F9: 省エネ(VAV 回転数制御の方が効果大) | G9: 省エネルギーに関する次の記述のうち，最も不適切なものはどれか。 | H9: ① 近代的なオフィスビルで，冷房負荷軽減のためLow-eガラスを複層ガラスの室内側ガラスに採用した。 | I9: ② 全熱交換器の効果は，必要外気量が多い建物ほど期待でき，外気冷房の効果は内部発熱が大きく，必要外気量が少ない建物ほど期待できる。 | J9: ③ ヒートポンプ方式は適当な温度の採熱源さえあれば，暖房負荷より少ない投入エネルギーで暖房ができる。 | K9: ④ 変風量（VAV）方式の風量制御は，ダンパ制御より回転数制御の方が省エネルギー効果が大きい。 | L9: ⑤ 床吹き出し空調方式では，冷房運転時の吹き出し温度が天井吹き出し方式より高いので，冷熱源の運転や外気冷房などが効率的に行える。 | M9: 空調方式・省エネルギー
A10: H26-09 | B10: Ⅲ-9 | C10: 建築環境・設備・建築物衛生管理 | D10: 空調 | E10: 3 | F10: 空気線図の室内負荷 | G10: 下図に示すように，外気冷却コイルで室内空気の湿度を満足させるまで冷却し，還気（加熱又は冷却）コイルで室内温度を満足するように制御して，極力再熱負荷を発生させない空調システムを採用し，さらにCO2制御による外気量制御を採用して省エネルギーを図っている。空気線図上に示す運転状態における室内負荷に最も近い値はどれか。ただし，与条件は以下のとおりとする。 空気の比容積：0.83 m³／kg(DA) 空調吹出し風量：20,000 m³／h 外気風量：4,000 m³／h（定格外気風量：6,000 m³／h，CO2制御） 空調系統：空調系統図参照 空気線図上のポイント：空調系統図参照 システム内発熱（送風機，ダクト断熱）：無視 | H10: ① 60,000 kJ／h | I10: ② 100,000 kJ／h | J10: ③ 145,000 kJ／h | K10: ④ 270,000 kJ／h | L10: ⑤ 315,000 kJ／h | M10: 空調計算（負荷・空気線図・冷凍サイクル）
A11: H26-10 | B11: Ⅲ-10 | C11: 建築環境・設備・建築物衛生管理 | D11: 給排水・防災 | E11: 3 | F11: 給排水設備 最も適切(通気管は排水管に勾配をつけて接続) | G11: 建物の給排水設備に関する次の記述のうち，最も適切なものはどれか。 | H11: ① 給水管のウォーターハンマー（水撃作用）を防止するためには，水栓・弁類を速やかに閉じた方がよい。 | I11: ② 給水管の圧力損失は，管内摩擦と形状抵抗の両者によるが，いずれも平均流速にほぼ比例して増大する。 | J11: ③ 通気管は管内の水滴が自然落下によって排水管に流れるようにし，逆こう配にならないように排水管に接続しなければならない。 | K11: ④ 便器に使用する洗浄弁（フラッシュバルブ）の必要圧力は，ゲージ圧で200 kPa（約2 kgf/cm²）以上必要である。 | L11: ⑤ 自然流下式の排水横管のこう配は流量，管径にかかわらず，1/20とする。 | M11: 排水・通気・衛生器具
A12: H26-11 | B12: Ⅲ-11 | C12: 建築環境・設備・建築物衛生管理 | D12: 給排水・防災 | E12: 4 | F12: 給湯設備(循環管) | G12: 給湯設備の設計・施工に関する次の記述のうち，最も不適切なものはどれか。 | H12: ① 中央給湯方式では，一般に55〜60℃で供給し，用途に応じて水と混合させて使用温度に下げる。 | I12: ② 給湯設備のゾーンは，給水の圧力とのバランスを考慮して，給水設備と同じゾーンにゾーニングする。 | J12: ③ 強制循環式給湯配管の必要循環量は小流量で，給湯配管はこの流量に対しては十分に太いので，循環流量による摩擦損失水頭は無視できる程度であり，リバースリターン方式を採用する意味はない。 | K12: ④ 貯湯タンクなどに設置する逃し管（膨張管）は，単独で立ち上げ，保守用の仕切弁を設ける。 | L12: ⑤ 集合住宅の住戸内への採用が多いヘッダ工法では，他の器具の使用による圧力降下や温度降下の影響が少ない。 | M12: 給水・給湯
A13: H26-12 | B13: Ⅲ-12 | C13: 建築環境・設備・建築物衛生管理 | D13: 給排水・防災 | E13: 2 | F13: 防災設備(排煙・SP・補助散水栓) | G13: 建物の防災設備に関する次の記述のうち，最も適切なものはどれか。 | H13: ① 泡消火設備は，泡消火剤と水の混合液を泡ヘッドなどの発泡器に送り，空気を吸引して発生させた泡を放射して，泡の冷却作用により消火する設備である。 | I13: ② 建築基準法上の排煙設備は避難安全確保を主目的とし，消防法上の排煙設備は消火活動支援を主目的としている。 | J13: ③ 特別避難階段の付室の排煙は，自然排煙方式でなければならない。 | K13: ④ スプリンクラー設備では，天井面や壁面に取り付けたヘッドから散水し，その窒息作用により消火する。 | L13: ⑤ 補助散水栓は，消防法によりスプリンクラーヘッドの設置を免除されている未警戒部分を防護するために設置されるもので，アラーム弁の一次側配管から分岐する。 | M13: 防災・排煙・消火
... A36: H26-35 | B36: Ⅲ-35 | C36: 廃棄物管理 | D36: 最終処分場・浸出水 | E36: 5 | F36: 浸出水処理 | G36: 最終処分場の浸出水処理に関する次の記述のうち，最も不適切なものはどれか。 | H36: ① 浸出水処理施設は取水導水設備，浸出水調整設備，水処理設備，放流設備等から構成される。 | I36: ② 埋立地に降った雨の一部は表面流出し，一部は蒸発し，残りが埋立層内に浸透し，浸出水として一般的に降水量の30〜60%が流出してくる。 | J36: ③ 浸出水水質は埋め立てるごみの形状により異なるが，焼却残さや不燃ごみを埋め立てる場合，最大濃度でBOD250 mg/L程度である。 | K36: ④ 焼却残さに含まれる無機塩類により浸出水はカルシウムイオンや塩化物イオンの濃度が高い傾向にある。 | L36: ⑤ 浸出水処理方法は生物処理と物理化学的処理の組合せにより行われる。CODやSSは接触ばっ気法などの物理化学的処理により処理される。 | M36: 最終処分場・浸出水

Sheet H25(平成25年度)問題・選択肢
A1: 問題ID | B1: 設問番号 | C1: 大分類(ブロック) | D1: サブジャンル | E1: 公式正答 | F1: 問題のテーマ・内容概要 | G1: 問題文 | H1: 選択肢① | I1: 選択肢② | J1: 選択肢③ | K1: 選択肢④ | L1: 選択肢⑤ | M1: 出題論点（細目）
A2: H25-01 | B2: Ⅲ-1 | C2: 建築環境・設備・建築物衛生管理 | D2: 換気・室内空気 | E2: 4 | F2: 住宅の気密測定(ΔPとQは比例しない) | G2: 住宅の気密測定に関する次の記述のうち，最も不適切なものはどれか。 | H2: ① 測定装置の送風機によって給気又は排気し，そのとき生じる室内と屋外の圧力差と測定装置の送風機を通過する通気量を測定する。 | I2: ② 外部風が強いと，気密測定の精度が確保できないため，強風時の測定は避ける必要がある。 | J2: ③ 一般的に，減圧法はサッシのめし合せ部分などが締まる方向に力が加わるため，加圧法にくらべて気密性能が高く測定される傾向がある。 | K2: ④ 室内外差圧ΔPと測定装置の送風機の通気量Qの関係は，常に比例となる。 | L2: ⑤ 測定するときは，室内の間仕切扉は開放し，屋外に面する開口部は閉じる。 | M2: 換気・通風
A3: H25-02 | B3: Ⅲ-2 | C3: 建築環境・設備・建築物衛生管理 | D3: 光・音 | E3: 1 | F3: 日射遮蔽・昼光利用 | G3: 日射遮蔽及び昼光利用に関する次の記述のうち，最も不適切なものはどれか。 | H3: ① 直射光を室内の奥まで導くために，南面の開口部に中庇を設け，中庇の上面は反射率が低い仕上げとした。 | I3: ② 一般的な居室の南面窓について，窓面積を変えずに室内の床面照度の均一性を高めるために，窓の位置を高くした。 | J3: ③ 照り返し防止措置として，窓前のコンクリート床に替えて芝生を植えた。 | K3: ④ 昼光利用のために，屋外床面，内装仕上げを，それぞれコンクリート，白漆喰壁として，導光を図った。 | L3: ⑤ 屋根の日射遮蔽手法として，磨き瓦などのツヤのある材料を用いた。 | M3: 日照・日射・採光
A4: H25-03 | B4: Ⅲ-3 | C4: 建築環境・設備・建築物衛生管理 | D4: 光・音 | E4: 5 | F4: 人工光源の色温度と雰囲気(Kruithof) | G4: 人工光源に関する次の記述のうち，最も不適切なものはどれか。 | H4: ① 白熱電球を用いると，温かみのある雰囲気を出すことができる。 | I4: ② 温白色蛍光ランプを用いると，照度が高い場合に暑苦しい感じになる。 | J4: ③ 白色蛍光ランプを用いると，明視照明では，視対象を正確に認識するのに好ましい照明となる。 | K4: ④ 昼光色蛍光ランプを用いると，すがすがしい雰囲気となる。 | L4: ⑤ 昼光色蛍光ランプを用いると，照度が高い場合に陰気な感じになる。 | M4: 照明・光環境
A5: H25-04 | B5: Ⅲ-4 | C5: 建築環境・設備・建築物衛生管理 | D5: 換気・室内空気 | E5: 4 | F5: 直列開口の合成相当開口面積計算 | G5: 二面開口住戸の通風性能について，風上開口の相当（有効）開口面積α1A1，風下開口の相当（有効）開口面積α2A2が下図に示す値である場合，それらの直列合成による相当（有効）開口面積（合成αA）の値に最も近いものはどれか。［図：α1A1＝10.0 m²，α2A2＝5.0 m²］ | H5: ① 0.6 m² | I5: ② 1.8 m² | J5: ③ 3.3 m² | K5: ④ 4.5 m² | L5: ⑤ 15.0 m² | M5: 換気・通風
A6: H25-05 | B6: Ⅲ-5 | C6: 建築環境・設備・建築物衛生管理 | D6: 熱・湿気 | E6: 3 | F6: 建材の熱伝導率の順(GW<ALC<せっこう<ガラス<Al) | G6: 次の（a）～（e）の建築材料の熱伝導率（W／m･K）について，小さいものから順に並べたものはどれか。 （a）軽量気泡コンクリートパネル （b）フロートガラス （c）せっこうボード （d）住宅用グラスウール断熱材10K （e）アルミニウム合金 | H6: ① d，c，a，e，b | I6: ② d，a，b，c，e | J6: ③ d，a，c，b，e | K6: ④ a，d，c，b，e | L6: ⑤ a，d，b，c，e | M6: 伝熱・断熱
A7: H25-06 | B7: Ⅲ-6 | C7: 建築環境・設備・建築物衛生管理 | D7: 空調 | E7: 4 | F7: 冷却除湿・バイパスファクタ計算(除去熱量・除湿量) | G7: 温度32℃，相対湿度65％の外気10,000m³／hを，冷却コイルに通して，冷却除湿する。コイルの表面温度を10℃，バイパスファクタを10％としたとき，除去される熱量Q，除湿量Lの組合せとして最も適切なものはどれか。ただし，与条件は以下のとおりとする。 空気の比容積（比体積）：0.83 m³／kg′ 外気の全熱量（エンタルピー）：83.5 kJ／kg′，絶対湿度：0.0200 kg／kg′ コイル表面の空気の全熱量（エンタルピー）：29.0 kJ／kg′，絶対湿度：0.0077 kg／kg′ | H7: ① Q：66,000 kJ／h L：15 kg／h | I7: ② Q：491,000 kJ／h L：111 kg／h | J7: ③ Q：545,000 kJ／h L：123 kg／h | K7: ④ Q：591,000 kJ／h L：133 kg／h | L7: ⑤ Q：657,000 kJ／h L：148 kg／h | M7: 空調計算（負荷・空気線図・冷凍サイクル）
A8: H25-07 | B8: Ⅲ-7 | C8: 建築環境・設備・建築物衛生管理 | D8: 空調 | E8: 2 | F8: 冷凍サイクルp-h線図とCOP | G8: 次の記述の，［ ］に入る記号又は数式の組合せとして最も適切なものはどれか。 下図に示す圧縮式冷凍機の冷凍サイクルにおいて，［A］は圧縮過程を，［B］は蒸発過程をそれぞれ示しており，この冷凍サイクルの成績係数は，［C］で表される。［図：p-h線図。1→2は蒸発，2→3は圧縮，3→4は凝縮，4→1は膨張。エンタルピーはh1，h2，h3］ | H8: ① A：1→2 B：2→3 C：(h3－h2)／(h2－h1) | I8: ② A：2→3 B：1→2 C：(h2－h1)／(h3－h2) | J8: ③ A：2→3 B：3→4 C：(h3－h1)／(h3－h2) | K8: ④ A：3→4 B：1→2 C：(h2－h1)／(h3－h1) | L8: ⑤ A：3→4 B：2→3 C：(h3－h2)／(h3－h1) | M8: 空調計算（負荷・空気線図・冷凍サイクル）
A9: H25-08 | B9: Ⅲ-8 | C9: 建築環境・設備・建築物衛生管理 | D9: 空調 | E9: 1 | F9: 空調設備(冷却塔の定義誤り) | G9: 空気調和設備に関する次の記述のうち，最も不適切なものはどれか。 | H9: ① 冷却塔は冷却水を用いて，空気を冷却する装置である。 | I9: ② 全熱交換器の熱交換エレメント保護のため，給気側及び排気側のそれぞれの上流側にエアフィルタを設ける。 | J9: ③ コージェネレーションのガスタービンからの排ガスは，温度が高いので，その排熱は一般的に蒸気の形で回収されることが多い。 | K9: ④ 変流量方式の水量制御には，二方弁が用いられる。 | L9: ⑤ 吸収式冷凍機では，一般に冷媒に水，吸収液に臭化リチウム水溶液を用い，高い真空度を保つ容器内で運転される。 | M9: 空調方式・省エネルギー
A10: H25-09 | B10: Ⅲ-9 | C10: 建築環境・設備・建築物衛生管理 | D10: 空調 | E10: 4 | F10: 空調ダクト(等摩擦法) | G10: 空調ダクトに関する次の記述のうち，最も不適切なものはどれか。 | H10: ① 静圧再取得とは，分岐ダクト取り出し部の後での主ダクトでの静圧上昇をいう。 | I10: ② ダクト風量［m³/h］，目標摩擦損失［Pa/m］を設定すれば，ダクトの摩擦抵抗線図を用いて必要な円ダクトの直径［mm］と断面風速［m/s］を知ることができる。 | J10: ③ 空調換気用ダクトの断面積が等しくても，アスペクト比が異なれば，ダクトの摩擦抵抗は異なる。 | K10: ④ 等摩擦法では送風機から各吹出し口までの経路の長さが異なる場合は，長さの短いダクト断面の縦又は横の寸法を大きくするなどして抵抗を調整する必要がある。 | L10: ⑤ ダクトの断面積の変化に応じて生じる動圧の変化量の絶対値は，静圧の変化量の絶対値に等しい。 | M10: 空調機器・ダクト・熱源
A11: H25-10 | B11: Ⅲ-10 | C11: 建築環境・設備・建築物衛生管理 | D11: 給排水・防災 | E11: 3 | F11: 給排水(吐水口空間は壁面の影響を受ける) | G11: 給排水設備に関する次の記述のうち，最も不適切なものはどれか。 | H11: ① 上水貯水槽への給水管の流入口端は，貯水槽内の横取り出しオーバフロー管下端との間に吐水口空間を設けなければならない。 | I11: ② 上水貯水槽に設置するオーバフロー管や排水管は，間接排水とする。 | J11: ③ 上水の水栓と水受け容器のあふれ縁との間に設ける吐水口空間は，近接する壁面からの距離の影響を受けない。 | K11: ④ 大便器の洗浄弁（フラッシュバルブ）では，給水管内部が負圧になったときに便器内の水の吸い上げを防止するためバキュームブレーカが働く。 | L11: ⑤ 飲料用の給水・給湯系統と雑用水系統や空調設備機器補給水系統などの異なる系統がバルブで接続されるとクロスコネクションのおそれがある。 | M11: 排水・通気・衛生器具
A12: H25-11 | B12: Ⅲ-11 | C12: 建築環境・設備・建築物衛生管理 | D12: 給排水・防災 | E12: 5 | F12: 防火・避難計画 | G12: 建物の防火・避難計画に関する次の記述のうち，最も不適切なものはどれか。 | H12: ① 防災センターは火災の防災拠点であり，煙の侵入などで機能しなくなることがあってはならず，可燃物のある空間などとは完全に区画しておく必要がある。 | I12: ② 避難階段への前室の設置は，避難者の滞留の処理や階段への煙の流入防止の上で有効である。 | J12: ③ 大規模な物品販売店などのように避難者が非常に多い場合は，低層部の屋上広場を一時的な避難場所とする計画も避難安全性を高める効果がある。 | K12: ④ 自然排煙口は直接外気に面し，かつ建築物の他の部分へ悪影響を与えないように配慮する。 | L12: ⑤ 避難階段内の避難流動に支障がないように，階段有効幅よりも階段入口幅が大きくなるように配慮して設計する。 | M12: 防災・排煙・消火
A13: H25-12 | B13: Ⅲ-12 | C13: 建築環境・設備・建築物衛生管理 | D13: 換気・室内空気 | E13: 5 | F13: 室内空気質の測定法(TOC等) | G13: 室内空気質の測定方法に関する次の記述のうち，最も不適切なものはどれか。 | H13: ① ザルツマン法とは，二酸化窒素を吸収発色液に吸収し，発色させて吸光度を測定し，二酸化窒素濃度を求めるものである。 | I13: ② ロウボリウムエアサンプラを用いた浮遊粉じん濃度測定方法は，ろ過材を通して空気を吸引し，ろ過材上に捕集した粉じんの質量を計測して粉じん濃度を求める方法である。 | J13: ③ オゾン濃度の連続測定法には，紫外線吸収法がある。 | K13: ④ ホルムアルデヒド濃度の精密測定には，DNPH含浸カートリッジ・HPLC法が用いられる。 | L13: ⑤ 二酸化炭素濃度を測定する場合，検知管法と化学発光法を利用した測定が最も普及している。 | M13: 室内空気質・健康影響・衛生動物
... A36: H25-35 | B36: Ⅲ-35 | C36: 廃棄物管理 | D36: 法制度・リサイクル・循環型社会 | E36: 3 | F36: リサイクル・3R(リサイクル分類) | G36: リサイクルに関する次の記述のうち，最も不適切なものはどれか。 | H36: ① 「循環型社会基本法」は，天然資源の消費を抑制し，環境への負荷を低減するために，大量消費・大量廃棄型社会から，循環型社会への転換を目指すものである。 | I36: ② 3Rは，発生抑制（リデュース），再使用（リユース），再資源化（リサイクル）の略称である。 | J36: ③ リサイクルという言葉は大変広い範囲で使われているが，一般的にはリユース，マテリアルリサイクル，サーマルリサイクルに分類される。 | K36: ④ リユースは，ビンを洗って使う，古着を利用するなど，原型のまま何度も使うことである。 | L36: ⑤ サーマルリサイクルはエネルギーとして利用するものである。 | M36: リサイクル・循環型社会

Sheet H24(平成24年度)問題・選択肢
A1: 問題ID | B1: 設問番号 | C1: 大分類(ブロック) | D1: サブジャンル | E1: 公式正答 | F1: 問題のテーマ・内容概要 | G1: 問題文 | H1: 選択肢① | I1: 選択肢② | J1: 選択肢③ | K1: 選択肢④ | L1: 選択肢⑤ | M1: 出題論点（細目）
A2: H24-01 | B2: Ⅳ-1 | C2: 建築環境・設備・建築物衛生管理 | D2: 光・音 | E2: 1 | F2: 室内騒音許容値、SN比、環境基準および屈曲振動（コインシデンス効果）に関する正誤判定 | G2: 騒音に関する次の記述のうち，最も不適切なものはどれか。 | H2: ① 室内騒音の許容値は，騒音レベルL_pAで表した場合の値は，NC値より5〜10小さい。 | I2: ② SN比は，測定対象音のレベル（S dB）と暗騒音のレベル（N dB）の差（S-N）によって求めることができる。 | J2: ③ 主として住居の用に供せられる地域に対する騒音の環境基準は，昼間55dB以下，夜間45dB以下とされている。 | K2: ④ 壁体に比較的高周波の音が斜め入射すると，壁体が屈曲振動を起こして透過損失が低下することがある。 | L2: ⑤ 室内騒音の許容値は，レストラン，美術館，音楽教室の順で小さくなる。 | M2: 音環境
A3: H24-02 | B3: Ⅳ-2 | C3: 建築環境・設備・建築物衛生管理 | D3: 光・音 | E3: 4 | F3: 開口部の断熱性能・日射侵入率ηおよびLow-Eガラス特性に関する正誤判定 | G3: 開口部の断熱性能と日射遮蔽性能に関する次の記述のうち，最も不適切なものはどれか。 | H3: ① ガラス面の日射侵入率ηは，普通単板ガラスより普通複層ガラスの方が，また，普通複層ガラスより普通三層複層ガラスの方が小さい。 | I3: ② ガラスと日射遮蔽用付属部品を組み合わせた窓の日射侵入率ηは，レースカーテンの場合よりも紙障子の場合の方が小さい。 | J3: ③ ガラスと日射遮蔽用付属部品を組み合わせた窓の日射侵入率ηは，内付けブラインドの場合よりも外付けブラインドの場合の方が小さい。 | K3: ④ 特殊金属薄膜（低放射：Low-E膜）をコーティングした複層ガラスの日射侵入率ηは，空気層の室内側ガラス表面にコーティングした方が，空気層の室外側ガラス表面にコーティングした場合よりも小さい。 | L3: ⑤ 特殊金属薄膜（低放射：Low-E膜）を空気層の室内側ガラス表面にコーティングした複層ガラスの熱貫流率は，コーティングしていない場合よりも小さい。 | M3: 日照・日射・採光
A4: H24-03 | B4: Ⅳ-3 | C4: 建築環境・設備・建築物衛生管理 | D4: 換気・室内空気 | E4: 3 | F4: 温度差換気量の比計算(開口面積・高さ・温度差) | G4: 図Aに示す建物の換気量をQとするとき，図Bに示す建物の換気量に最も近いものはどれか。ただし，図A，図Bともに室温は20℃で，建物外部は無風，開口部の流量係数は全て等しいとする。図は，それぞれ建物の鉛直断面を示したものである。 | H4: ① √2 Q | I4: ② 2 Q | J4: ③ 4 Q | K4: ④ 8 Q | L4: ⑤ 16 Q | M4: 換気・通風
A5: H24-04 | B5: Ⅳ-4 | C5: 建築環境・設備・建築物衛生管理 | D5: 熱・湿気 | E5: 5 | F5: 熱移動(放射は絶対温度の4乗) | G5: 熱移動に関する次の記述のうち，最も不適切なものはどれか。 | H5: ① 壁の対流熱伝達率は，外気側の方が室内側よりも大きい。 | I5: ② 床面の対流熱伝達率は，暖房時の方が冷房時よりも小さい。 | J5: ③ 放射熱伝達率は，物体表面が艶消しで真っ黒いほど大きくなる。 | K5: ④ 壁の熱貫流は，壁内部では熱伝導，壁の表面では対流及び放射によって行われている。 | L5: ⑤ 完全黒体から放射される熱線のエネルギーは，絶対温度に比例する。 | M5: 伝熱・断熱
A6: H24-05 | B6: Ⅳ-5 | C6: 建築環境・設備・建築物衛生管理 | D6: 光・音 | E6: 2 | F6: 明順応・暗順応、比視感度、直接グレア、基準開口率および明視条件の正誤判定 | G6: 光環境に関する次の記述のうち，最も不適切なものはどれか。 | H6: ① ヒトの視覚において，明順応に比べて，暗順応は時間がかかる。 | I6: ② ヒトの視覚において，暗所視では，比視感度が最大になる波長が長い方にずれる。 | J6: ③ 直接グレアの防止の基本は，前方視野角の30°以内に高輝度光源を露出させないことである。 | K6: ④ 建築基準法における教室及び保育室の採光に有効な窓の基準開口率は，1／5である。 | L6: ⑤ 照明設計における明視の条件には，対象の大きさ，対比の大きさ，明るさが含まれる。 | M6: 照明・光環境
A7: H24-06 | B7: Ⅳ-6 | C7: 建築環境・設備・建築物衛生管理 | D7: 熱・湿気 | E7: 3 | F7: 2層合成壁体（熱伝導率λ1・λ2）および内外表面熱伝達率に基づく熱通過率（熱貫流率U）計算 | G7: 下図に示す2層からなる壁体の熱通過率（熱貫流率）として，最も近い値はどれか。ただし，α_o ＝ 20 W/(m²・K)，α_i ＝ 8 W/(m²・K)，λ_1 ＝ 1.5 W/(m・K)，λ_2 ＝ 0.02 W/(m・K) とする。 | H7: ① 0.03 W/(m²・K) | I7: ② 0.04 W/(m²・K) | J7: ③ 0.13 W/(m²・K) | K7: ④ 0.19 W/(m²・K) | L7: ⑤ 1.59 W/(m²・K) | M7: 伝熱・断熱
A8: H24-07 | B8: Ⅳ-7 | C8: 建築環境・設備・建築物衛生管理 | D8: 温熱・省エネ指標 | E8: 4 | F8: 室内居住域の温度分布、上昇気流、エアフローウィンドウおよび上下温度差基準の正誤判定 | G8: 室内の温度分布に関する次の記述のうち，最も不適切なものはどれか。 | H8: ① 空調・換気設備は，床面より1.8 mまでの居住域を良好な温熱空気環境に保つことが目的であるが，室内に温度分布を生じさせる原因でもある。 | I8: ② 室内には種々の発熱体が存在し，近傍の空気温度を上昇させる。この高温空気は密度が小さいため，浮力により上昇気流を発生させる場合がある。 | J8: ③ エアフローウィンドウは，2枚のガラスの間にブラインドを設けたもので，窓枠下部から室内空気を吸引し，これを窓上部から排気するものである。 | K8: ④ 良好な温熱環境を実現するためには，極端な室内温度分布が生じるのは好ましくないため，床上10 cmから1.1 m間の上下温度分布は5℃以内に抑えるのが好ましい。 | L8: ⑤ 夏期に日射熱が室内へ侵入する場合や外気温が高い場合は，窓側の空気温度は室の奥よりも高くなり，冬期に隙間風が侵入する場合や外気温が低い場合は，窓側の空気温度は低くなる傾向にある。 | M8: 温熱環境・温熱指標
A9: H24-08 | B9: Ⅳ-8 | C9: 建築環境・設備・建築物衛生管理 | D9: 空調 | E9: 5 | F9: 全熱交換器バイパス、蓄熱槽システム、太陽電池（単結晶/多結晶）およびヒートポンプCOPの正誤判定 | G9: 省エネルギー設備機器に関する次の記述のうち，最も不適切なものはどれか。 | H9: ① 空気調和機に使用する全熱交換器では，外気冷房が可能なときに給排気バイパスなどにより熱交換を回避する。 | I9: ② 夜間電力利用の蓄熱槽システムでは，熱源の夜間運転時間が長いほど熱源容量は小さくて済む。 | J9: ③ 蓄熱槽は開放水面を有し，配管経路が開放方式となるため，密閉回路方式に較べて，ポンプ動力が一般的に増大する。 | K9: ④ 多結晶シリコン太陽電池は，単結晶シリコン太陽電池と比較して変換効率が低いが，製造が容易で効率とコストのバランスがよく，現在最も普及している太陽電池である。 | L9: ⑤ ヒートポンプの冷房時の成績係数（COP）は，圧縮仕事に対する凝縮熱量の比で表す。 | M9: 空調方式・省エネルギー
A10: H24-09 | B10: Ⅳ-9 | C10: 建築環境・設備・建築物衛生管理 | D10: 空調 | E10: 4 | F10: 長方形ダクト合流部（浅い流し込み合流）の風速・断面積・局部抵抗係数ζ_Tに基づく局部圧力損失ΔP_T計算 | G10: 下図に示す長方形ダクトの合流部（Ⓐ → Ⓑ）の局部圧力損失として，最も近い値はどれか。ただし，与条件は以下の通りとする。 | H10: ① −8.6 Pa | I10: ② −6.0 Pa | J10: ③ 2.0 Pa | K10: ④ 2.9 Pa | L10: ⑤ 11.9 Pa | M10: 空調計算（負荷・空気線図・冷凍サイクル）
A11: H24-10 | B11: Ⅳ-10 | C11: 建築環境・設備・建築物衛生管理 | D11: 空調 | E11: 4 | F11: 冷却塔制御（三方弁バイパス）、VAV静圧制御およびCAV/VAV温度センサー配置の正誤判定 | G11: 空気調和設備の自動制御に関する次の記述のうち，最も不適切なものはどれか。 | H11: ① 冷却塔の冷却水温度（入口温度）制御には，冷却水を三方弁によりバイパスする方法がある。 | I11: ② 床吹き出し方式の自動制御の特徴は，温度成層を形成させて居住地域空調を行うことである。 | J11: ③ 空気調和の変風量単一ダクト方式の自動制御には，給気ダクト内の静圧信号により空気調和機のファンの容量を制御するものがある。 | K11: ④ 変流量方式の水量制御には，負荷三方弁が用いられる。 | L11: ⑤ 定風量単一ダクト方式では温度制御センサーを室内に，変風量単一ダクト方式では温度制御センサーを給気ダクト内及び室内に設置する。 | M11: 空調方式・省エネルギー
A12: H24-11 | B12: Ⅳ-11 | C12: 建築環境・設備・建築物衛生管理 | D12: 給排水・防災 | E12: 2 | F12: 給水管圧力損失、大便器洗浄弁（フラッシュバルブ）必要圧力、受水槽周囲空間およびエアギャップの正誤判定 | G12: 給排水設備に関する次の記述のうち，最も不適切なものはどれか。 | H12: ① 給水管の圧力損失は，管内摩擦と形状抵抗の両者によるが，いずれも流速の2乗に比例して増大する。 | I12: ② 大便器に使用する洗浄弁（フラッシュバルブ）の必要圧力は，ゲージ圧で0.7 MPa以上である。 | J12: ③ 受水槽は点検のため，上部には1 m以上，周囲・下部には0.6 m以上のスペースを設けなくてはならない。 | K12: ④ 給水系統への逆サイホン作用による汚染水の逆流を防止するために，洗面器に吐水口空間（エアギャップ）を設ける。 | L12: ⑤ 洗面器のSトラップの封水深を7 cmとした。 | M12: 排水・通気・衛生器具
A13: H24-12 | B13: Ⅳ-12 | C13: 建築環境・設備・建築物衛生管理 | D13: 空調 | E13: 1 | F13: 金属バネ・空気バネの固有周波数比較、積層ゴムおよび多孔質防振材の特性に関する正誤判定 | G13: 設備機器の防振に関する次の記述のうち，最も不適切なものはどれか。 | H13: ① 一般的に金属バネは，空気バネに比べ防振系の固有周波数を低く設定できるため，防振効果は大きい。 | I13: ② 一般的に空気バネは，防振ゴムパッドに比べ防振系の固有周波数を低く設定できるため，防振効果が大きい。 | J13: ③ 積層ゴムは，水平方向の振動の絶縁を図る場合の防振材として有用である。 | K13: ④ 高密度の多孔質材料（ロックウール，グラスウール等）は，浮き床など面的防振として多く使用されている。 | L13: ⑤ 防振ゴムは，形に自由度があり据付がしやすいため，建築分野でも多く使用されている防振材料である。 | M13: 空調機器・ダクト・熱源
... A36: H24-35 | B36: Ⅳ-35 | C36: 廃棄物管理 | D36: 災害廃棄物・事業方式・統計・管理票 | E36: 4 | F36: 東日本大震災災害廃棄物マスタープラン（県実行計画、市町村処理、木くず活用等）の正誤判定 | G36: 「東日本大震災に係る災害廃棄物の処理指針（マスタープラン）」（環境省，平成23年5月16日）に関する次の記述のうち，最も不適切なものはどれか。 | H36: ① 県は，具体的処理方法を定めた災害廃棄物処理の実行計画を作成する。 | I36: ② 市町村は，災害廃棄物処理の実行計画を踏まえ，災害廃棄物の処理を実施する。 | J36: ③ 可燃物については，破砕後，できるだけセメント焼成や廃棄物発電等の有効利用を行う。 | K36: ④ 木くずについては，最終処分量の削減のためにも，復興資材等として被災地で活用することが有効である。 | L36: ⑤ 災害廃棄物処理の中間処理・最終処分のスケジュールは，腐敗性等がある廃棄物については，速やかに処分することとしている。 | M36: 災害廃棄物・指定廃棄物

Sheet H23(平成23年度)問題・選択肢
A1: 問題ID | B1: 設問番号 | C1: 大分類(ブロック) | D1: サブジャンル | E1: 公式正答 | F1: 問題のテーマ・内容概要 | G1: 問題文 | H1: 選択肢① | I1: 選択肢② | J1: 選択肢③ | K1: 選択肢④ | L1: 選択肢⑤ | M1: 出題論点（細目）
A2: H23-01 | B2: Ⅳ-1 | C2: 建築環境・設備・建築物衛生管理 | D2: 熱・湿気 | E2: 5 | F2: 床断面の熱橋（木根太）を考慮した熱貫流率（U値）の計算式選定 | G2: 下図に示す外気に接する床断面の熱橋を考慮した熱貫流率の計算方法について，最も適切なものはどれか。ただし，熱伝導率をλ，厚さをdとし，木根太によって生じる熱橋の面積比率（熱橋面積率）を A_HB，室内側熱伝達抵抗を R_i，外気側熱伝達抵抗を R_o とする。また，木根太の厚さ d_3 は，断熱材の厚さ d_2 よりも大きいものとする。 | H2: ① (1 − A_HB) / (R_i + R_o + d_1 / λ_1 + d_2 / λ_2) | I2: ② 1 / (R_i + R_o + d_1 / λ_1 + d_2 / λ_2) | J2: ③ (1 − A_HB) / (R_i + R_o + d_1 / λ_1 + d_2 / λ_2) + A_HB / (R_i + R_o + d_1 / λ_1 + d_3 / λ_3) | K2: ④ (1 − A_HB) / (d_1 / λ_1 + d_2 / λ_2) + A_HB / (d_1 / λ_1 + d_3 / λ_3) | L2: ⑤ (1 − A_HB) / (R_i + R_o + d_1 / λ_1 + d_2 / λ_2) + A_HB / (R_i + R_o + d_1 / λ_1 + d_3 / λ_3) | M2: 伝熱・断熱
A3: H23-02 | B3: Ⅳ-2 | C3: 建築環境・設備・建築物衛生管理 | D3: 光・音 | E3: 3 | F3: 室の残響時間計算、Sabineの式、Eyringの式および音響パワーレベルに関する正誤判定 | G3: 室の残響に関する次の記述のうち，最も不適切なものはどれか。 | H3: ① 残響時間は，室内のエネルギー密度が音源を停止した時点から百万分の１，すなわち 10⁻⁶ になるまでの時間である。 | I3: ② 室内の平均的な音圧レベルは，音源の音響パワーレベルだけではなく，室の等価吸音面積に依存する。 | J3: ③ 空間容積が小さい室では，空気の音響吸収を考慮したEyring−Knudsenの式を用いなければならない。 | K3: ④ 拡散音場を仮定した残響理論に基づくSabineの式では，残響時間は室容積に比例し，室の等価吸音面積に反比例する。 | L3: ⑤ 周壁や椅子による吸音力が大きい室では，室の平均吸音率を考慮したEyringの式を用いる必要がある。 | M3: 音環境
A4: H23-03 | B4: Ⅳ-3 | C4: 建築環境・設備・建築物衛生管理 | D4: 温熱・省エネ指標 | E4: 1 | F4: 住宅居室の冬期室内温熱環境、断熱性能、熱容量および外断熱に関する正誤判定 | G4: 住宅の居室の冬期室内温熱環境及び間欠暖房に関する次の記述のうち，最も不適切なものはどれか。 | H4: ① 居室の断熱性能が低いと，暖房時の室内空気温度と壁の室内側表面温度の差が小さくなる。 | I4: ② 同じ熱容量の場合，断熱性能を向上させると，暖房停止後の室温低下が穏やかとなる。 | J4: ③ 同じ熱容量の場合，断熱性能を向上させると，立上り負荷が小さくなる。 | K4: ④ 居室の断熱性能が低いと，より多量の熱量を投入する必要が生じ，天井付近に高温の空気が停滞して上下温度差がつきやすくなる。 | L4: ⑤ コンクリートなどの熱容量の大きな材料で作られた構造体の蓄熱効果を活用するためには，外断熱でなければならない。 | M4: 温熱環境・温熱指標
A5: H23-04 | B5: Ⅳ-4 | C5: 建築環境・設備・建築物衛生管理 | D5: 光・音 | E5: 4 | F5: 窓位置、照り返し防止、導光計画、中庇反射および屋根日射遮蔽に関する正誤判定 | G5: 日射遮蔽及び昼光利用に関する次の記述のうち，最も不適切なものはどれか。 | H5: ① 一般的な居室の南面窓について，窓面積を変えずに室内の床面照度の均一性を高めるために，窓の位置を高くした。 | I5: ② 照り返し防止措置として，窓前のコンクリート床に替えて芝生を植えた。 | J5: ③ 昼光利用のために，屋外床面，内装仕上げを，それぞれコンクリート，白漆喰壁として，導光を図った。 | K5: ④ 直射光を室内の奥まで導くために，南面の開口部に中庇を設け，中庇の上面は反射率が低い仕上げとした。 | L5: ⑤ 屋根の日射遮蔽手法として，磨き瓦などのツヤのある材料を用いた。 | M5: 日照・日射・採光
A6: H23-05 | B6: Ⅳ-5 | C6: 建築環境・設備・建築物衛生管理 | D6: 換気・室内空気 | E6: 3 | F6: トレーサーガス法による換気量測定の原理、仮定および適用限界に関する正誤判定 | G6: 人為的にガスを発生させ，その濃度を測定することで換気量を明らかにするトレーサーガス法に関する次の記述のうち，最も不適切なものはどれか。 | H6: ① トレーサーガスを空間内に一定割合で人為的に連続放出し，その定常状態の濃度を測定することで，換気量を得ることができる。 | I6: ② トレーサーガス法は，トレーサーガスが空間の壁などに吸われたり，付着したりしないことを仮定している。 | J6: ③ トレーサーガス法は，空間の開口部や隙間が数多く分散しており，そこでの空気の流出入が不明確であるような自然換気の測定には用いることができない。 | K6: ④ トレーサーガスを空間内に放出し，均一な濃度分布を達成した後の濃度変化を測定することで，換気量を得ることができる。 | L6: ⑤ トレーサーガスには，空気と比重が比較的近く，濃度測定が簡易なガスが用いられる。 | M6: 換気・通風
A7: H23-06 | B7: Ⅳ-6 | C7: 建築環境・設備・建築物衛生管理 | D7: 空調 | E7: 1 | F7: 床吹き出し空調、層流クリーンルーム、FCUゾーニング、NC値および空調ゾーニングの正誤判定 | G7: 空調設備に関する次の記述のうち，最も不適切なものはどれか。 | H7: ① 床吹き出し空調方式は，冷房時の吹き出し温度を天井吹き出し方式より低くしなければならないので，熱源の効率運転がしにくい。 | I7: ② 層流式クリーンルームのうち，垂直層流方式と水平層流方式では，一般に垂直層流方式の方が高い空気清浄度を得やすい。 | J7: ③ ホテルの客室空調システムを外調機＋ファンコイルユニット方式とする場合，方位ごとの熱負荷パターンを考慮してファンコイルユニットのゾーニングを行う。 | K7: ④ 許容騒音値がNC−20のコンサートホールの空調機械室は，ホールから十分に離れた位置に設置する。 | L7: ⑤ 病院はその構成部門や室用途により，稼働時間帯，空気清浄度，負荷密度，安全性・信頼性などの要求性能が異なるので，空調ゾーニングを細分化する必要がある。 | M7: 空調方式・省エネルギー
A8: H23-07 | B8: Ⅳ-7 | C8: 建築環境・設備・建築物衛生管理 | D8: 空調 | E8: 5 | F8: ペリメータ負荷低減、排熱回収、BEMS、内部発熱低減およびフリークーリングの組合せ正誤判定 | G8: 空調の省エネルギーに関する次の組合せのうち，最も不適切なものはどれか。 | H8: ① ペリメータ負荷の低減 − エアフローウィンドウ | I8: ② 排熱回収 − 全熱交換器 | J8: ③ ビルエネルギー管理システム − BEMS | K8: ④ 内部発熱負荷の低減 − Hf型照明器具 | L8: ⑤ 外気負荷の低減 − フリークーリング | M8: 空調方式・省エネルギー
A9: H23-08 | B9: Ⅳ-8 | C9: 建築環境・設備・建築物衛生管理 | D9: 空調 | E9: 2 | F9: 空気線図による室内負荷計算(再熱なし) | G9: 下図に示すように，外気冷却コイルで室内空気の湿度を満足させるまで冷却し，還気（加熱又は冷却）コイルで室内温度を満足するように制御して，極力再熱負荷を発生させない空調システムを採用した。室内負荷として最も近い値はどれか。ただし，与条件は以下のとおりとする。 空気の比容積：0.83 m³／kg(DA) 空調吹出し風量：30,000 m³／h 外気風量：10,000 m³／h 空調系統：空調系統図参照 空気線図上のポイント：空調系統図参照 システム内発熱（送風機，ダクト断熱）：無視 | H9: ① 224,000 kJ／h | I9: ② 325,000 kJ／h | J9: ③ 448,000 kJ／h | K9: ④ 602,000 kJ／h | L9: ⑤ 1,337,000 kJ／h | M9: 空調計算（負荷・空気線図・冷凍サイクル）
A10: H23-09 | B10: Ⅳ-9 | C10: 建築環境・設備・建築物衛生管理 | D10: 空調 | E10: 1 | F10: 低温冷風空調、VAV制御、躯体蓄熱、冷却水下限温度制御および冷凍機COPの正誤判定 | G10: 空調設備に関する次の記述のうち，最も不適切なものはどれか。 | H10: ① 低温冷風空調方式は，大温度差送風による搬送エネルギーの低減効果があるが，低湿度環境は実現できない。 | I10: ② VAV方式でも，室内温湿度制御とともに外気量制御が可能である。 | J10: ③ 躯体蓄熱方式は，空調開始時の蓄熱負荷の低減に効果があり，特に冬期の暖房立ち上がり負荷の低減効果が大きい。 | K10: ④ 冷却水の温度制御は，冷凍機の冷却水下限温度保持が目的である。 | L10: ⑤ 冷凍機の成績係数は，一般に電動冷凍機の方が吸収冷凍機より大きい。 | M10: 空調方式・省エネルギー
A11: H23-10 | B11: Ⅳ-10 | C11: 建築環境・設備・建築物衛生管理 | D11: 給排水・防災 | E11: 3 | F11: 蓄煙方式、自然排煙、機械排煙の内圧制御、押し出し排煙および加圧防煙方式の正誤判定 | G11: 煙制御方式に関する次の記述のうち，最も不適切なものはどれか。 | H11: ① 蓄煙方式は，天井が高く空間容積の大きい施設で採用されている。 | I11: ② 自然排煙方式は，高温の煙層による上下の圧力差が生み出す排煙能力に依存するので，火災初期の煙層温度の低い段階では排煙効果が低い。 | J11: ③ 機械排煙方式は，その室の内圧が低くなるために他の室への煙の拡散を抑制する効果は期待できない。 | K11: ④ 押し出し排煙方式は，煙層を乱さないように給気口をできるだけ低い位置に設置することが必要である。 | L11: ⑤ 加圧防煙方式は，遮煙達成目標に応じた排煙量の計画による排煙ダクト面積の削減や，給気を機械にすることによる給気ダクト面積の削減が可能となる。 | M11: 防災・排煙・消火
A12: H23-11 | B12: Ⅳ-11 | C12: 建築環境・設備・建築物衛生管理 | D12: 給排水・防災 | E12: 4 | F12: 雨水利用初期カット、水道直結増圧給水、さや管ヘッダ工法、スプリンクラー予作動式およびCO2排出正誤判定 | G12: 衛生設備に関する次の記述のうち，最も不適切なものはどれか。 | H12: ① 雨水利用において，初期降雨の水質が使用用途の水質に適合しない場合には，降雨量計を設置して初期雨水をカットする。 | I12: ② 中小規模の建物においては，汚染されやすい貯水槽が省略できる水道直結増圧給水方式の採用が増えている。 | J12: ③ 集合住宅の住戸内などで採用されるさや管ヘッダ工法には，可とう性のある配管が採用されている。 | K12: ④ 同一階のスプリンクラー設備であれば，湿式と予作動式の流水検知装置を兼用することができる。 | L12: ⑤ 水の利用は，その浄水から排水処理のそれぞれの過程でエネルギーを消費し，二酸化炭素（CO₂）を放出して地球温暖化の一因になっている。 | M12: 排水・通気・衛生器具
A13: H23-12 | B13: Ⅳ-12 | C13: 建築環境・設備・建築物衛生管理 | D13: 給排水・防災 | E13: 5 | F13: 水道の定義、給水装置、給水方式区分、水道の三要素および末端遊離残留塩素基準の正誤判定 | G13: 水道に関する次の記述のうち，最も不適切なものはどれか。 | H13: ① 水道は，水を人の飲用に適する水として供給する施設の総称である。 | I13: ② 配水管から分岐した給水管，止水栓，量水器及びこれに直結する給水栓などの給水用具を給水装置と呼ぶ。 | J13: ③ 給水方式は，水道直結方式と受水槽方式の2つに区分される。 | K13: ④ 需要者が満足する水量，飲料水の水質基準への適合，適度な水圧の保持を水道に求められる三要素という。 | L13: ⑤ 水道水は，末端給水栓において0.01 mg/L以上の遊離残留塩素を保持していなくてはならない。 | M13: 給水・給湯
... A36: H23-35 | B36: Ⅳ-35 | C36: 廃棄物管理 | D36: 法制度・リサイクル・循環型社会 | E36: 3 | F36: 地球温暖化対策推進法における地方公共団体実行計画、国民の責務、温室効果ガスの種類および京都議定書目標の正誤判定 | G36: 地球温暖化対策の推進に関する法律（温暖化対策法）に関する次の記述のうち，最も不適切なものはどれか。 | H36: ① 温暖化対策法第20条の3では，地方公共団体実行計画等について記載しており，地方公共団体実行計画には，計画期間，実行計画の目標，措置の内容，その他実施に関し必要な事項について定めるものとされている。 | I36: ② 第6条に国民の責務として，日常生活に関し，温室効果ガスの排出の抑制等のための措置を講ずるよう努めるとともに，国及び地方公共団体が実施する温室効果ガスの排出の抑制等のための施策に協力することがあげられている。 | J36: ③ 温室効果ガスとして，二酸化炭素，メタン，塩化水素，ハイドロフルオロカーボンのうち政令で定めるもの，パーフルオロカーボンのうち政令で定めるもの，六ふっ化硫黄が定められている。 | K36: ④ 温暖化対策法は，地球温暖化対策に関し，京都議定書目標達成計画を策定すること，温室効果ガスの排出の抑制等を促進する措置を講ずること等をあげている。 | L36: ⑤ 温暖化対策法では，京都議定書の約束を履行するための必要な目標の達成に関する計画「京都議定書目標達成計画」を定めるものとしている。 | M36: 廃棄物処理法・制度・処理施設・その他

Sheet 過去問マスターDB
A1: 問題ID | B1: 年度 | C1: 設問番号 | D1: 大分類(ブロック) | E1: サブジャンル | F1: 公式正答 | G1: 問題のテーマ・内容概要 | H1: 問題文 | I1: 選択肢① | J1: 選択肢② | K1: 選択肢③ | L1: 選択肢④ | M1: 選択肢⑤ | N1: 出題論点（細目） | O1: 図表
A2: H23-01 | B2: 平成23年度 | C2: Ⅳ-1 | D2: 建築環境・設備・建築物衛生管理 | E2: 熱・湿気 | F2: 5 | G2: 床断面の熱橋（木根太）を考慮した熱貫流率（U値）の計算式選定 | H2: 下図に示す外気に接する床断面の熱橋を考慮した熱貫流率の計算方法について，最も適切なものはどれか。ただし，熱伝導率をλ，厚さをdとし，木根太によって生じる熱橋の面積比率（熱橋面積率）を A_HB，室内側熱伝達抵抗を R_i，外気側熱伝達抵抗を R_o とする。また，木根太の厚さ d_3 は，断熱材の厚さ d_2 よりも大きいものとする。 | I2: ① (1 − A_HB) / (R_i + R_o + d_1 / λ_1 + d_2 / λ_2) | J2: ② 1 / (R_i + R_o + d_1 / λ_1 + d_2 / λ_2) | K2: ③ (1 − A_HB) / (R_i + R_o + d_1 / λ_1 + d_2 / λ_2) + A_HB / (R_i + R_o + d_1 / λ_1 + d_3 / λ_3) | L2: ④ (1 − A_HB) / (d_1 / λ_1 + d_2 / λ_2) + A_HB / (d_1 / λ_1 + d_3 / λ_3) | M2: ⑤ (1 − A_HB) / (R_i + R_o + d_1 / λ_1 + d_2 / λ_2) + A_HB / (R_i + R_o + d_1 / λ_1 + d_3 / λ_3) | N2: 伝熱・断熱 | O2: 図表
A3: H23-02 | B3: 平成23年度 | C3: Ⅳ-2 | D3: 建築環境・設備・建築物衛生管理 | E3: 光・音 | F3: 3 | G3: 室の残響時間計算、Sabineの式、Eyringの式および音響パワーレベルに関する正誤判定 | H3: 室の残響に関する次の記述のうち，最も不適切なものはどれか。 | I3: ① 残響時間は，室内のエネルギー密度が音源を停止した時点から百万分の１，すなわち 10⁻⁶ になるまでの時間である。 | J3: ② 室内の平均的な音圧レベルは，音源の音響パワーレベルだけではなく，室の等価吸音面積に依存する。 | K3: ③ 空間容積が小さい室では，空気の音響吸収を考慮したEyring−Knudsenの式を用いなければならない。 | L3: ④ 拡散音場を仮定した残響理論に基づくSabineの式では，残響時間は室容積に比例し，室の等価吸音面積に反比例する。 | M3: ⑤ 周壁や椅子による吸音力が大きい室では，室の平均吸音率を考慮したEyringの式を用いる必要がある。 | N3: 音環境
A4: H23-03 | B4: 平成23年度 | C4: Ⅳ-3 | D4: 建築環境・設備・建築物衛生管理 | E4: 温熱・省エネ指標 | F4: 1 | G4: 住宅居室の冬期室内温熱環境、断熱性能、熱容量および外断熱に関する正誤判定 | H4: 住宅の居室の冬期室内温熱環境及び間欠暖房に関する次の記述のうち，最も不適切なものはどれか。 | I4: ① 居室の断熱性能が低いと，暖房時の室内空気温度と壁の室内側表面温度の差が小さくなる。 | J4: ② 同じ熱容量の場合，断熱性能を向上させると，暖房停止後の室温低下が穏やかとなる。 | K4: ③ 同じ熱容量の場合，断熱性能を向上させると，立上り負荷が小さくなる。 | L4: ④ 居室の断熱性能が低いと，より多量の熱量を投入する必要が生じ，天井付近に高温の空気が停滞して上下温度差がつきやすくなる。 | M4: ⑤ コンクリートなどの熱容量の大きな材料で作られた構造体の蓄熱効果を活用するためには，外断熱でなければならない。 | N4: 温熱環境・温熱指標
A5: H23-04 | B5: 平成23年度 | C5: Ⅳ-4 | D5: 建築環境・設備・建築物衛生管理 | E5: 光・音 | F5: 4 | G5: 窓位置、照り返し防止、導光計画、中庇反射および屋根日射遮蔽に関する正誤判定 | H5: 日射遮蔽及び昼光利用に関する次の記述のうち，最も不適切なものはどれか。 | I5: ① 一般的な居室の南面窓について，窓面積を変えずに室内の床面照度の均一性を高めるために，窓の位置を高くした。 | J5: ② 照り返し防止措置として，窓前のコンクリート床に替えて芝生を植えた。 | K5: ③ 昼光利用のために，屋外床面，内装仕上げを，それぞれコンクリート，白漆喰壁として，導光を図った。 | L5: ④ 直射光を室内の奥まで導くために，南面の開口部に中庇を設け，中庇の上面は反射率が低い仕上げとした。 | M5: ⑤ 屋根の日射遮蔽手法として，磨き瓦などのツヤのある材料を用いた。 | N5: 日照・日射・採光
A6: H23-05 | B6: 平成23年度 | C6: Ⅳ-5 | D6: 建築環境・設備・建築物衛生管理 | E6: 換気・室内空気 | F6: 3 | G6: トレーサーガス法による換気量測定の原理、仮定および適用限界に関する正誤判定 | H6: 人為的にガスを発生させ，その濃度を測定することで換気量を明らかにするトレーサーガス法に関する次の記述のうち，最も不適切なものはどれか。 | I6: ① トレーサーガスを空間内に一定割合で人為的に連続放出し，その定常状態の濃度を測定することで，換気量を得ることができる。 | J6: ② トレーサーガス法は，トレーサーガスが空間の壁などに吸われたり，付着したりしないことを仮定している。 | K6: ③ トレーサーガス法は，空間の開口部や隙間が数多く分散しており，そこでの空気の流出入が不明確であるような自然換気の測定には用いることができない。 | L6: ④ トレーサーガスを空間内に放出し，均一な濃度分布を達成した後の濃度変化を測定することで，換気量を得ることができる。 | M6: ⑤ トレーサーガスには，空気と比重が比較的近く，濃度測定が簡易なガスが用いられる。 | N6: 換気・通風
A7: H23-06 | B7: 平成23年度 | C7: Ⅳ-6 | D7: 建築環境・設備・建築物衛生管理 | E7: 空調 | F7: 1 | G7: 床吹き出し空調、層流クリーンルーム、FCUゾーニング、NC値および空調ゾーニングの正誤判定 | H7: 空調設備に関する次の記述のうち，最も不適切なものはどれか。 | I7: ① 床吹き出し空調方式は，冷房時の吹き出し温度を天井吹き出し方式より低くしなければならないので，熱源の効率運転がしにくい。 | J7: ② 層流式クリーンルームのうち，垂直層流方式と水平層流方式では，一般に垂直層流方式の方が高い空気清浄度を得やすい。 | K7: ③ ホテルの客室空調システムを外調機＋ファンコイルユニット方式とする場合，方位ごとの熱負荷パターンを考慮してファンコイルユニットのゾーニングを行う。 | L7: ④ 許容騒音値がNC−20のコンサートホールの空調機械室は，ホールから十分に離れた位置に設置する。 | M7: ⑤ 病院はその構成部門や室用途により，稼働時間帯，空気清浄度，負荷密度，安全性・信頼性などの要求性能が異なるので，空調ゾーニングを細分化する必要がある。 | N7: 空調方式・省エネルギー
A8: H23-07 | B8: 平成23年度 | C8: Ⅳ-7 | D8: 建築環境・設備・建築物衛生管理 | E8: 空調 | F8: 5 | G8: ペリメータ負荷低減、排熱回収、BEMS、内部発熱低減およびフリークーリングの組合せ正誤判定 | H8: 空調の省エネルギーに関する次の組合せのうち，最も不適切なものはどれか。 | I8: ① ペリメータ負荷の低減 − エアフローウィンドウ | J8: ② 排熱回収 − 全熱交換器 | K8: ③ ビルエネルギー管理システム − BEMS | L8: ④ 内部発熱負荷の低減 − Hf型照明器具 | M8: ⑤ 外気負荷の低減 − フリークーリング | N8: 空調方式・省エネルギー
A9: H23-08 | B9: 平成23年度 | C9: Ⅳ-8 | D9: 建築環境・設備・建築物衛生管理 | E9: 空調 | F9: 2 | G9: 空気線図による室内負荷計算(再熱なし) | H9: 下図に示すように，外気冷却コイルで室内空気の湿度を満足させるまで冷却し，還気（加熱又は冷却）コイルで室内温度を満足するように制御して，極力再熱負荷を発生させない空調システムを採用した。室内負荷として最も近い値はどれか。ただし，与条件は以下のとおりとする。 空気の比容積：0.83 m³／kg(DA) 空調吹出し風量：30,000 m³／h 外気風量：10,000 m³／h 空調系統：空調系統図参照 空気線図上のポイント：空調系統図参照 システム内発熱（送風機，ダクト断熱）：無視 | I9: ① 224,000 kJ／h | J9: ② 325,000 kJ／h | K9: ③ 448,000 kJ／h | L9: ④ 602,000 kJ／h | M9: ⑤ 1,337,000 kJ／h | N9: 空調計算（負荷・空気線図・冷凍サイクル） | O9: 図表
A10: H23-09 | B10: 平成23年度 | C10: Ⅳ-9 | D10: 建築環境・設備・建築物衛生管理 | E10: 空調 | F10: 1 | G10: 低温冷風空調、VAV制御、躯体蓄熱、冷却水下限温度制御および冷凍機COPの正誤判定 | H10: 空調設備に関する次の記述のうち，最も不適切なものはどれか。 | I10: ① 低温冷風空調方式は，大温度差送風による搬送エネルギーの低減効果があるが，低湿度環境は実現できない。 | J10: ② VAV方式でも，室内温湿度制御とともに外気量制御が可能である。 | K10: ③ 躯体蓄熱方式は，空調開始時の蓄熱負荷の低減に効果があり，特に冬期の暖房立ち上がり負荷の低減効果が大きい。 | L10: ④ 冷却水の温度制御は，冷凍機の冷却水下限温度保持が目的である。 | M10: ⑤ 冷凍機の成績係数は，一般に電動冷凍機の方が吸収冷凍機より大きい。 | N10: 空調方式・省エネルギー
A11: H23-10 | B11: 平成23年度 | C11: Ⅳ-10 | D11: 建築環境・設備・建築物衛生管理 | E11: 給排水・防災 | F11: 3 | G11: 蓄煙方式、自然排煙、機械排煙の内圧制御、押し出し排煙および加圧防煙方式の正誤判定 | H11: 煙制御方式に関する次の記述のうち，最も不適切なものはどれか。 | I11: ① 蓄煙方式は，天井が高く空間容積の大きい施設で採用されている。 | J11: ② 自然排煙方式は，高温の煙層による上下の圧力差が生み出す排煙能力に依存するので，火災初期の煙層温度の低い段階では排煙効果が低い。 | K11: ③ 機械排煙方式は，その室の内圧が低くなるために他の室への煙の拡散を抑制する効果は期待できない。 | L11: ④ 押し出し排煙方式は，煙層を乱さないように給気口をできるだけ低い位置に設置することが必要である。 | M11: ⑤ 加圧防煙方式は，遮煙達成目標に応じた排煙量の計画による排煙ダクト面積の削減や，給気を機械にすることによる給気ダクト面積の削減が可能となる。 | N11: 防災・排煙・消火
A12: H23-11 | B12: 平成23年度 | C12: Ⅳ-11 | D12: 建築環境・設備・建築物衛生管理 | E12: 給排水・防災 | F12: 4 | G12: 雨水利用初期カット、水道直結増圧給水、さや管ヘッダ工法、スプリンクラー予作動式およびCO2排出正誤判定 | H12: 衛生設備に関する次の記述のうち，最も不適切なものはどれか。 | I12: ① 雨水利用において，初期降雨の水質が使用用途の水質に適合しない場合には，降雨量計を設置して初期雨水をカットする。 | J12: ② 中小規模の建物においては，汚染されやすい貯水槽が省略できる水道直結増圧給水方式の採用が増えている。 | K12: ③ 集合住宅の住戸内などで採用されるさや管ヘッダ工法には，可とう性のある配管が採用されている。 | L12: ④ 同一階のスプリンクラー設備であれば，湿式と予作動式の流水検知装置を兼用することができる。 | M12: ⑤ 水の利用は，その浄水から排水処理のそれぞれの過程でエネルギーを消費し，二酸化炭素（CO₂）を放出して地球温暖化の一因になっている。 | N12: 排水・通気・衛生器具
A13: H23-12 | B13: 平成23年度 | C13: Ⅳ-12 | D13: 建築環境・設備・建築物衛生管理 | E13: 給排水・防災 | F13: 5 | G13: 水道の定義、給水装置、給水方式区分、水道の三要素および末端遊離残留塩素基準の正誤判定 | H13: 水道に関する次の記述のうち，最も不適切なものはどれか。 | I13: ① 水道は，水を人の飲用に適する水として供給する施設の総称である。 | J13: ② 配水管から分岐した給水管，止水栓，量水器及びこれに直結する給水栓などの給水用具を給水装置と呼ぶ。 | K13: ③ 給水方式は，水道直結方式と受水槽方式の2つに区分される。 | L13: ④ 需要者が満足する水量，飲料水の水質基準への適合，適度な水圧の保持を水道に求められる三要素という。 | M13: ⑤ 水道水は，末端給水栓において0.01 mg/L以上の遊離残留塩素を保持していなくてはならない。 | N13: 給水・給湯
A14: H23-13 | B14: 平成23年度 | C14: Ⅳ-13 | D14: 建築環境・設備・建築物衛生管理 | E14: 建築物衛生法・レジオネラ | F14: 4 | G14: レジオネラ肺炎、エアロゾル飛散抑制、生物膜生息、50℃維持および浴槽水換気基準の正誤判定 | H14: レジオネラ属菌とその対策に関する次の記述のうち，最も不適切なものはどれか。 | I14: ① レジオネラ症は，レジオネラ属菌による感染症で，そのうちレジオネラ肺炎については，症状のみで他の肺炎と鑑別することは困難である。 | J14: ② レジオネラ症の発生防止対策の基本は，レジオネラ属菌が繁殖しやすい状況を少なくするとともに，これを含むエアロゾルの飛散を抑制することである。 | K14: ③ レジオネラ属菌は，生物膜に生息する微生物等の中で繁殖するため，消毒剤から保護されている。 | L14: ④ 湯温が50 ℃に満たない貯湯槽には，50 ℃以上に保つ能力を有する加熱装置を設置して，レジオネラ属菌の繁殖を抑制する必要がある。 | M14: ⑤ 入浴設備の浴槽水は毎日換えることが原則であり，最低でも1週間に1回以上完全に交換する必要がある。 | N14: レジオネラ・感染症
A15: H23-14 | B15: 平成23年度 | C15: Ⅳ-14 | D15: 建築環境・設備・建築物衛生管理 | E15: 建築物衛生法・レジオネラ | F15: 3 | G15: 特定建築物の定義（病院の扱い、延べ面積2000m²基準、建築物環境衛生管理技術者免状）の正誤判定 | H15: 建築物における衛生的な環境の確保に関する法律（建築物衛生法）に関する次の記述のうち，最も不適切なものはどれか。 | I15: ① 建築物衛生法が定める「特定建築物」に，病院の用に供される建築物は含まれない。 | J15: ② 保健所は，多数の者が使用し，又は利用する建築物の維持管理について，環境衛生上の正しい知識の普及に努めるとともに，環境衛生上の相談に応じ，必要な指導を行う。 | K15: ③ 建築物衛生法が定める「特定建築物」は，定められた用途の用に供される部分の延べ面積が2,000平方メートル以上の建築物である。 | L15: ④ 特定建築物所有者等は，建築物環境衛生管理技術者免状を有する者を建築物環境衛生管理技術者に選任しなければならない。 | M15: ⑤ 建築物環境衛生管理技術者免状は，厚生労働大臣の登録を受けた者が行う講習会の課程を修了したもの又は，建築物環境衛生管理技術者試験に合格した者に対し，厚生労働大臣が交付する。 | N15: 建築物衛生法・衛生基準
A16: H23-15 | B16: 平成23年度 | C16: Ⅳ-15 | D16: 建築環境・設備・建築物衛生管理 | E16: 換気・室内空気 | F16: 2 | G16: ねずみ害虫防除の原則、薬事法承認薬、IPM調査および許容水準目標設定の正誤判定 | H16: 建築物におけるねずみ等の防除に関する次の記述のうち，最も不適切なものはどれか。 | I16: ① 建築物におけるねずみ等の防除は，その発生及び侵入の防止並びに駆除により行う。 | J16: ② ねずみ等の防除のために殺そ剤又は殺虫剤を使用する場合，薬事法の承認を受けた医薬品以外を用いてはならない。 | K16: ③ IPM（総合的有害生物管理，以下同じ）では，的確に発生の実態を把握するため，措置前に生息密度調査法に基づく生息実態調査を実施する。 | L16: ④ IPMでは，調査から得られた捕獲指数などをもとに，該当建築物又は該当場所に「許容水準」「警戒水準」「措置水準」の目標水準を設定する。 | M16: ⑤ IPMでは，標準的な目標水準に照らして，有害生物の密度と防除効果の観点から評価を行う。 | N16: 室内空気質・健康影響・衛生動物
A17: H23-16 | B17: 平成23年度 | C17: Ⅳ-16 | D17: 建築環境・設備・建築物衛生管理 | E17: 空調 | F17: 2 | G17: 気化式・パン形・遠心式・超音波式・スプレー式加湿器の特性とメンテナンスに関する正誤判定 | H17: 加湿器に関する次の記述のうち，最も不適切なものはどれか。 | I17: ① 気化式加湿器には，加湿装置についた残留物の洗浄用に加湿量の1.5〜3倍の給水量が必要である。 | J17: ② パン形加湿器は，スケールは付着するが寿命が長く，大容量の空調機に適する。 | K17: ③ 遠心加湿器は，ダクト内に直接付ける方式が一般的である。 | L17: ④ 超音波加湿器の振動子は水あか等の付着に弱いため，清掃などメンテナンスには留意する必要がある。 | M17: ⑤ スプレー形加湿器は，水や温水噴霧の場合には空気の温度低下を伴う。 | N17: 空調機器・ダクト・熱源
A18: H23-17 | B18: 平成23年度 | C18: Ⅳ-17 | D18: 建築環境・設備・建築物衛生管理 | E18: 温熱・省エネ指標 | F18: 3 | G18: 熱損失係数Q、夏期日射取得係数μ、年間熱負荷係数PAL、CEC/ACおよびCEC/Lの定義正誤判定 | H18: 住宅と建築物の省エネルギー性能指標に関する次の記述のうち，最も不適切なものはどれか。 | I18: ① 熱損失係数（Q）は，室内外の温度差が１℃のときの建物全体の外壁等の躯体で生じる貫流熱損失と，隙間量に応じて生じる換気熱損失の合計を床面積当たりにした値である。 | J18: ② 夏期日射取得係数（μ）は，建物に日射遮蔽措置がない場合に取得される日射熱量に対する，日射遮蔽措置の計画がなされている場合の日射熱量の比である。 | K18: ③ 年間熱負荷係数（PAL）は，ペリメーターゾーンの年間熱負荷を，建物全体の床面積で除して算出される。 | L18: ④ 空調エネルギー消費係数（CEC/AC）は，年間空調消費エネルギー量を，年間仮想空調負荷で除した値である。 | M18: ⑤ 照明エネルギー消費係数（CEC/L）は，年間照明消費エネルギー量を，年間仮想照明消費エネルギー量で除した値である。 | N18: 省エネ性能指標・都市建築環境
A19: H23-18 | B19: 平成23年度 | C19: Ⅳ-18 | D19: 水質管理 | E19: 水質指標・環境基準 | F19: 1 | G19: 平成21年度地下水質測定結果における超過率（硝酸性窒素、ふっ素、ほう素、VOC）の判定 | H19: 地下水汚染に関する次の記述の下線部分のうち，誤っているものはどれか。 平成21年度の地下水質の測定結果において環境基準の超過率が最も高い項目は，施肥，家畜排せつ物，生活排水等が原因と見られる①アンモニア性窒素であり，平成11年度より②ふっ素，③ほう素とともに環境基準に加えられた。④トリクロロエチレン，⑤ベンゼン等のVOC事例もここ数年ある程度の判明数があり，自主的に汚染調査を行う事業者の増加，工場跡地の売却等の際に調査を行う等の最近の傾向に起因していると考えられている。 | I19: ① アンモニア性窒素 | J19: ② ふっ素 | K19: ③ ほう素 | L19: ④ トリクロロエチレン | M19: ⑤ ベンゼン | N19: 水質指標・試験方法・測定
A20: H23-19 | B20: 平成23年度 | C20: Ⅳ-19 | D20: 水質管理 | E20: 水質指標・環境基準 | F20: 1 | G20: 排水処理流量計（電磁式・オリフィス式・ベンチュリー管式・フロート面積式・羽根車式）の固形物影響比較 | H20: 排水処理施設の汚水量を計測する流量計について，水中の固形物の影響が最も少ない方式は次のうちどれか。 | I20: ① 電磁式 | J20: ② オリフィス式 | K20: ③ ベンチュリー管式 | L20: ④ フロート形面積式 | M20: ⑤ 羽根車式 | N20: 水質指標・試験方法・測定
A21: H23-20 | B21: 平成23年度 | C21: Ⅳ-20 | D21: 水質管理 | E21: 水質指標・環境基準 | F21: 1 | G21: 公害対策基本法に基づく水質環境基準（河川・湖沼の健康項目：大腸菌群数、硝酸性窒素、ふっ素、鉛等）の正誤判定 | H21: 公害対策基本法（昭和42年法律第132号）第9条の規定に基づく水質汚濁に係る環境基準のうち，河川・湖沼における人の健康の保護に関する環境基準項目として基準値が設定されていないものは次のうちどれか。 | I21: ① 大腸菌群数 | J21: ② 硝酸性窒素及び亜硝酸性窒素 | K21: ③ ふっ素 | L21: ④ 鉛 | M21: ⑤ テトラクロロエチレン | N21: 環境基準・排水基準
... A38: H24-02 | B38: 平成24年度 | C38: Ⅳ-2 | D38: 建築環境・設備・建築物衛生管理 | E38: 光・音 | F38: 4 | G38: 開口部の断熱性能・日射侵入率ηおよびLow-Eガラス特性に関する正誤判定 | H38: 開口部の断熱性能と日射遮蔽性能に関する次の記述のうち，最も不適切なものはどれか。 | I38: ① ガラス面の日射侵入率ηは，普通単板ガラスより普通複層ガラスの方が，また，普通複層ガラスより普通三層複層ガラスの方が小さい。 | J38: ② ガラスと日射遮蔽用付属部品を組み合わせた窓の日射侵入率ηは，レースカーテンの場合よりも紙障子の場合の方が小さい。 | K38: ③ ガラスと日射遮蔽用付属部品を組み合わせた窓の日射侵入率ηは，内付けブラインドの場合よりも外付けブラインドの場合の方が小さい。 | L38: ④ 特殊金属薄膜（低放射：Low-E膜）をコーティングした複層ガラスの日射侵入率ηは，空気層の室内側ガラス表面にコーティングした方が，空気層の室外側ガラス表面にコーティングした場合よりも小さい。 | M38: ⑤ 特殊金属薄膜（低放射：Low-E膜）を空気層の室内側ガラス表面にコーティングした複層ガラスの熱貫流率は，コーティングしていない場合よりも小さい。 | N38: 日照・日射・採光
A39: H24-03 | B39: 平成24年度 | C39: Ⅳ-3 | D39: 建築環境・設備・建築物衛生管理 | E39: 換気・室内空気 | F39: 3 | G39: 温度差換気量の比計算(開口面積・高さ・温度差) | H39: 図Aに示す建物の換気量をQとするとき，図Bに示す建物の換気量に最も近いものはどれか。ただし，図A，図Bともに室温は20℃で，建物外部は無風，開口部の流量係数は全て等しいとする。図は，それぞれ建物の鉛直断面を示したものである。 | I39: ① √2 Q | J39: ② 2 Q | K39: ③ 4 Q | L39: ④ 8 Q | M39: ⑤ 16 Q | N39: 換気・通風 | O39: 図表
A40: H24-04 | B40: 平成24年度 | C40: Ⅳ-4 | D40: 建築環境・設備・建築物衛生管理 | E40: 熱・湿気 | F40: 5 | G40: 熱移動(放射は絶対温度の4乗) | H40: 熱移動に関する次の記述のうち，最も不適切なものはどれか。 | I40: ① 壁の対流熱伝達率は，外気側の方が室内側よりも大きい。 | J40: ② 床面の対流熱伝達率は，暖房時の方が冷房時よりも小さい。 | K40: ③ 放射熱伝達率は，物体表面が艶消しで真っ黒いほど大きくなる。 | L40: ④ 壁の熱貫流は，壁内部では熱伝導，壁の表面では対流及び放射によって行われている。 | M40: ⑤ 完全黒体から放射される熱線のエネルギーは，絶対温度に比例する。 | N40: 伝熱・断熱
A41: H24-05 | B41: 平成24年度 | C41: Ⅳ-5 | D41: 建築環境・設備・建築物衛生管理 | E41: 光・音 | F41: 2 | G41: 明順応・暗順応、比視感度、直接グレア、基準開口率および明視条件の正誤判定 | H41: 光環境に関する次の記述のうち，最も不適切なものはどれか。 | I41: ① ヒトの視覚において，明順応に比べて，暗順応は時間がかかる。 | J41: ② ヒトの視覚において，暗所視では，比視感度が最大になる波長が長い方にずれる。 | K41: ③ 直接グレアの防止の基本は，前方視野角の30°以内に高輝度光源を露出させないことである。 | L41: ④ 建築基準法における教室及び保育室の採光に有効な窓の基準開口率は，1／5である。 | M41: ⑤ 照明設計における明視の条件には，対象の大きさ，対比の大きさ，明るさが含まれる。 | N41: 照明・光環境
A42: H24-06 | B42: 平成24年度 | C42: Ⅳ-6 | D42: 建築環境・設備・建築物衛生管理 | E42: 熱・湿気 | F42: 3 | G42: 2層合成壁体（熱伝導率λ1・λ2）および内外表面熱伝達率に基づく熱通過率（熱貫流率U）計算 | H42: 下図に示す2層からなる壁体の熱通過率（熱貫流率）として，最も近い値はどれか。ただし，α_o ＝ 20 W/(m²・K)，α_i ＝ 8 W/(m²・K)，λ_1 ＝ 1.5 W/(m・K)，λ_2 ＝ 0.02 W/(m・K) とする。 | I42: ① 0.03 W/(m²・K) | J42: ② 0.04 W/(m²・K) | K42: ③ 0.13 W/(m²・K) | L42: ④ 0.19 W/(m²・K) | M42: ⑤ 1.59 W/(m²・K) | N42: 伝熱・断熱 | O42: 図表
A43: H24-07 | B43: 平成24年度 | C43: Ⅳ-7 | D43: 建築環境・設備・建築物衛生管理 | E43: 温熱・省エネ指標 | F43: 4 | G43: 室内居住域の温度分布、上昇気流、エアフローウィンドウおよび上下温度差基準の正誤判定 | H43: 室内の温度分布に関する次の記述のうち，最も不適切なものはどれか。 | I43: ① 空調・換気設備は，床面より1.8 mまでの居住域を良好な温熱空気環境に保つことが目的であるが，室内に温度分布を生じさせる原因でもある。 | J43: ② 室内には種々の発熱体が存在し，近傍の空気温度を上昇させる。この高温空気は密度が小さいため，浮力により上昇気流を発生させる場合がある。 | K43: ③ エアフローウィンドウは，2枚のガラスの間にブラインドを設けたもので，窓枠下部から室内空気を吸引し，これを窓上部から排気するものである。 | L43: ④ 良好な温熱環境を実現するためには，極端な室内温度分布が生じるのは好ましくないため，床上10 cmから1.1 m間の上下温度分布は5℃以内に抑えるのが好ましい。 | M43: ⑤ 夏期に日射熱が室内へ侵入する場合や外気温が高い場合は，窓側の空気温度は室の奥よりも高くなり，冬期に隙間風が侵入する場合や外気温が低い場合は，窓側の空気温度は低くなる傾向にある。 | N43: 温熱環境・温熱指標
A44: H24-08 | B44: 平成24年度 | C44: Ⅳ-8 | D44: 建築環境・設備・建築物衛生管理 | E44: 空調 | F44: 5 | G44: 全熱交換器バイパス、蓄熱槽システム、太陽電池（単結晶/多結晶）およびヒートポンプCOPの正誤判定 | H44: 省エネルギー設備機器に関する次の記述のうち，最も不適切なものはどれか。 | I44: ① 空気調和機に使用する全熱交換器では，外気冷房が可能なときに給排気バイパスなどにより熱交換を回避する。 | J44: ② 夜間電力利用の蓄熱槽システムでは，熱源の夜間運転時間が長いほど熱源容量は小さくて済む。 | K44: ③ 蓄熱槽は開放水面を有し，配管経路が開放方式となるため，密閉回路方式に較べて，ポンプ動力が一般的に増大する。 | L44: ④ 多結晶シリコン太陽電池は，単結晶シリコン太陽電池と比較して変換効率が低いが，製造が容易で効率とコストのバランスがよく，現在最も普及している太陽電池である。 | M44: ⑤ ヒートポンプの冷房時の成績係数（COP）は，圧縮仕事に対する凝縮熱量の比で表す。 | N44: 空調方式・省エネルギー
A45: H24-09 | B45: 平成24年度 | C45: Ⅳ-9 | D45: 建築環境・設備・建築物衛生管理 | E45: 空調 | F45: 4 | G45: 長方形ダクト合流部（浅い流し込み合流）の風速・断面積・局部抵抗係数ζ_Tに基づく局部圧力損失ΔP_T計算 | H45: 下図に示す長方形ダクトの合流部（Ⓐ → Ⓑ）の局部圧力損失として，最も近い値はどれか。ただし，与条件は以下の通りとする。 | I45: ① −8.6 Pa | J45: ② −6.0 Pa | K45: ③ 2.0 Pa | L45: ④ 2.9 Pa | M45: ⑤ 11.9 Pa | N45: 空調計算（負荷・空気線図・冷凍サイクル） | O45: 図表
A46: H24-10 | B46: 平成24年度 | C46: Ⅳ-10 | D46: 建築環境・設備・建築物衛生管理 | E46: 空調 | F46: 4 | G46: 冷却塔制御（三方弁バイパス）、VAV静圧制御およびCAV/VAV温度センサー配置の正誤判定 | H46: 空気調和設備の自動制御に関する次の記述のうち，最も不適切なものはどれか。 | I46: ① 冷却塔の冷却水温度（入口温度）制御には，冷却水を三方弁によりバイパスする方法がある。 | J46: ② 床吹き出し方式の自動制御の特徴は，温度成層を形成させて居住地域空調を行うことである。 | K46: ③ 空気調和の変風量単一ダクト方式の自動制御には，給気ダクト内の静圧信号により空気調和機のファンの容量を制御するものがある。 | L46: ④ 変流量方式の水量制御には，負荷三方弁が用いられる。 | M46: ⑤ 定風量単一ダクト方式では温度制御センサーを室内に，変風量単一ダクト方式では温度制御センサーを給気ダクト内及び室内に設置する。 | N46: 空調方式・省エネルギー
A47: H24-11 | B47: 平成24年度 | C47: Ⅳ-11 | D47: 建築環境・設備・建築物衛生管理 | E47: 給排水・防災 | F47: 2 | G47: 給水管圧力損失、大便器洗浄弁（フラッシュバルブ）必要圧力、受水槽周囲空間およびエアギャップの正誤判定 | H47: 給排水設備に関する次の記述のうち，最も不適切なものはどれか。 | I47: ① 給水管の圧力損失は，管内摩擦と形状抵抗の両者によるが，いずれも流速の2乗に比例して増大する。 | J47: ② 大便器に使用する洗浄弁（フラッシュバルブ）の必要圧力は，ゲージ圧で0.7 MPa以上である。 | K47: ③ 受水槽は点検のため，上部には1 m以上，周囲・下部には0.6 m以上のスペースを設けなくてはならない。 | L47: ④ 給水系統への逆サイホン作用による汚染水の逆流を防止するために，洗面器に吐水口空間（エアギャップ）を設ける。 | M47: ⑤ 洗面器のSトラップの封水深を7 cmとした。 | N47: 排水・通気・衛生器具
A48: H24-12 | B48: 平成24年度 | C48: Ⅳ-12 | D48: 建築環境・設備・建築物衛生管理 | E48: 空調 | F48: 1 | G48: 金属バネ・空気バネの固有周波数比較、積層ゴムおよび多孔質防振材の特性に関する正誤判定 | H48: 設備機器の防振に関する次の記述のうち，最も不適切なものはどれか。 | I48: ① 一般的に金属バネは，空気バネに比べ防振系の固有周波数を低く設定できるため，防振効果は大きい。 | J48: ② 一般的に空気バネは，防振ゴムパッドに比べ防振系の固有周波数を低く設定できるため，防振効果が大きい。 | K48: ③ 積層ゴムは，水平方向の振動の絶縁を図る場合の防振材として有用である。 | L48: ④ 高密度の多孔質材料（ロックウール，グラスウール等）は，浮き床など面的防振として多く使用されている。 | M48: ⑤ 防振ゴムは，形に自由度があり据付がしやすいため，建築分野でも多く使用されている防振材料である。 | N48: 空調機器・ダクト・熱源
A49: H24-13 | B49: 平成24年度 | C49: Ⅳ-13 | D49: 建築環境・設備・建築物衛生管理 | E49: 温熱・省エネ指標 | F49: 1 | G49: WBGT（湿球黒球温度）の適用範囲、屋外・屋内測定算出式（乾球/湿球/グローブ温度）の正誤判定 | H49: WBGT（湿球黒球温度，Wet-Bulb Globe Temperature）に関する次の記述のうち，最も不適切なものはどれか。 | I49: ① WBGTは，暑熱あるいは寒冷環境下の熱ストレスを評価する指数としてJISに規格化されている。 | J49: ② WBGTは，労働環境の評価や熱中症予防のための運動指針に広く利用されている。 | K49: ③ WBGT基準値は，人体の熱の収支にかかわる環境の4要素のうち，気温，湿度，輻射（放射）熱の3要素により算出されるが，気流の影響も間接的に反映されている。 | L49: ④ 屋外に用いる場合のWBGTは，乾球温度，湿球温度，グローブ温度を重みづけ平均して算出される。 | M49: ⑤ 屋内に用いる場合のWBGTは，湿球温度とグローブ温度を重みづけ平均して算出される。 | N49: 温熱環境・温熱指標
A50: H24-14 | B50: 平成24年度 | C50: Ⅳ-14 | D50: 建築環境・設備・建築物衛生管理 | E50: 熱・湿気 | F50: 5 | G50: 絶対湿度低下、防湿層設置、空気よどみ、夏季小屋裏結露および気密性・換気量と結露の正誤判定 | H50: 室内結露に関する次の記述のうち，最も不適切なものはどれか。 | I50: ① 室内空気の絶対湿度を下げることは，結露防止において重要である。 | J50: ② 躯（く）体の室内側に防湿層を設けることは，冬季の内部結露防止に有効である。 | K50: ③ 家具などによる空気のよどみが家具裏の壁体の表面結露の一因である。 | L50: ④ 夏季でも，小屋裏部材や壁面などに結露が起きる場合がある。 | M50: ⑤ 冬季の表面結露防止法として，室の気密性を高め，換気量を少なくすることは効果的である。 | N50: 結露・湿気・湿り空気
A51: H24-15 | B51: 平成24年度 | C51: Ⅳ-15 | D51: 建築環境・設備・建築物衛生管理 | E51: 換気・室内空気 | F51: 3 | G51: 室内空気中の細菌・真菌（カビ）発生源、時間的・空間的変動特性および日和見感染の正誤判定 | H51: 室内空気中の微生物（細菌・真菌）とその汚染に関する次の記述のうち，最も不適切なものはどれか。 | I51: ① 微生物による汚染の程度は，空中菌濃度あるいは表面汚染濃度により評価される。 | J51: ② 住宅における真菌（カビ）の主な発生源は外界の土壌菌と植物寄生菌であり，風や人体に付着して室内に持ち込まれて定着・増殖する。 | K51: ③ 微生物による汚染は，多くの種類の菌がかかわるが，時間的・空間的な変動は穏やかである。 | L51: ④ 事務所建築の室内空気中の細菌の主な発生源は，外気取り入れに伴う侵入，居住者からの発生，空調設備や室内に棲みついているものに分類される。 | M51: ⑤ 真菌（カビ）は日和見感染症が多く，肺真菌症やアスペルギルス肺炎などの要因菌である。 | N51: 室内空気質・健康影響・衛生動物
A52: H24-16 | B52: 平成24年度 | C52: Ⅳ-16 | D52: 建築環境・設備・建築物衛生管理 | E52: 温熱・省エネ指標 | F52: 3 | G52: 空気齢測定、熱電対、放射温度計補正、熱線風速計および検知管法の原理に関する正誤判定 | H52: 温熱・空気環境に関する次の記述のうち，最も不適切なものはどれか。 | I52: ① 空気齢は，トレーサーガスの濃度減衰の測定結果などから求めることができる。 | J52: ② 熱電対は，異種金属が接した場合に生じる起電力と周囲温度との対応関係に応用したものである。 | K52: ③ 放射温度計は，物体表面測定時に物体の種類による補正の必要がなく，熱橋部などの調査に有効である。 | L52: ④ 熱線風速計は，細い白金線などに通電した際の，電圧値と風速との対応関係に応用したものである。 | M52: ⑤ 検知管法は，各種のガスと反応して着色する検知剤を充填した検知管の一方から一定量の空気を吸引し，着色の度合いや長さによってガス濃度の概算値を求める方法である。 | N52: 温熱環境・温熱指標
A53: H24-17 | B53: 平成24年度 | C53: Ⅳ-17 | D53: 建築環境・設備・建築物衛生管理 | E53: 温熱・省エネ指標 | F53: 5 | G53: 建築物ライフサイクルCO2評価、フロンガス、ヒートアイランド現象および都市気候特性の正誤判定 | H53: 都市・建築環境に関する次の記述のうち，最も不適切なものはどれか。 | I53: ① 建築に関わるCO2発生量は建設時のものだけでなく，解体までのライフサイクル全体で評価する必要がある。 | J53: ② 建築において，フロンガスは主に冷凍機，断熱発熱材などの環境調整に関わる分野で用いられている。 | K53: ③ ヒートアイランドは都市域の多大な排熱と，コンクリートジャングルに代表される熱放散の起こりにくい都市構造との相乗効果で発生する。 | L53: ④ 都市の緑化は，気温低減，保水による水循環改善，吸音，喧噪感の低減など，多面的な環境改善に役立つ。 | M53: ⑤ 都市は郊外と異なり，自然風の速度が大きい，上昇気流の発生で雲・降水量が多い，などの特徴を持つ。 | N53: 省エネ性能指標・都市建築環境
A54: H24-18 | B54: 平成24年度 | C54: Ⅳ-18 | D54: 建築環境・設備・建築物衛生管理 | E54: 換気・室内空気 | F54: 2 | G54: 室容積・換気回数・内外気濃度・放散速度に基づくホルムアルデヒド放散建材面積の定型計算 | H54: 室内において，ホルムアルデヒドが単一の材料から放散するとき，下記の条件におけるホルムアルデヒドを放散する材料の放散面積に最も近いものはどれか。ただし，発生したホルムアルデヒドは，瞬時に一様拡散し，吸着・分解せず，室内濃度に変動はなく安定しているものとする。 条件 （1）室の容積：30 m³ （2）室の換気回数：0.5 回/h （3）外気中のホルムアルデヒド濃度：6 μg/m³ （4）室内空気中のホルムアルデヒド定常濃度：20 μg/m³ （5）ホルムアルデヒド放散速度：15 μg/m²h | I54: ① 8 m² | J54: ② 14 m² | K54: ③ 20 m² | L54: ④ 28 m² | M54: ⑤ 34 m² | N54: ホルムアルデヒド放散速度・面積
A55: H24-19 | B55: 平成24年度 | C55: Ⅳ-19 | D55: 水質管理 | E55: 活性汚泥・浄化槽 | F55: 2 | G55: 膜分離（MF/UF）、膜素材（酢酸セルロース等）および膜分離活性汚泥法（MBR）の特徴に関する正誤判定 | H55: 汚水処理における膜分離に関する次の記述のうち，最も不適切なものはどれか。 | I55: ① 膜分離は，微小な孔（ポア）を有する膜を使用する方法であり，微生物のような懸濁性物質から溶解性物質までを除去できる膜がある。 | J55: ② MF膜（Microfiltration Membrane）は，海水を淡水にすることができる。 | K55: ③ UF膜（Ultrafiltration Membrane）は，水溶性の高分子物質などの除去を目的に用いられる。 | L55: ④ 膜の素材は，酢酸セルロース，ポリアミド，ポリスルホン，ポリイミド，ポリオレフィンなどさまざまなものが開発されている。 | M55: ⑤ 膜分離活性汚泥法では，高濃度の活性汚泥を反応槽内に保持できることが特長である。 | N55: 活性汚泥・生物処理
A56: H24-20 | B56: 平成24年度 | C56: Ⅳ-20 | D56: 水質管理 | E56: 高度処理・消毒 | F56: 3 | G56: 高度処理装置（活性炭吸着・凝集分離・砂ろ過）の除去対象物質および維持管理に関する正誤判定 | H56: 中・大規模な汚水処理施設に適用される高度処理装置に関する次の記述のうち，最も不適切なものはどれか。 | I56: ① 活性炭吸着装置はCOD，色度及び臭気の除去を目的としている。 | J56: ② 凝集分離装置はリン，浮遊物質及びBODの除去を目的としている。 | K56: ③ 砂ろ過装置はコロイド粒子及び溶解性物質の除去を目的としている。 | L56: ④ 活性炭吸着装置では，吸着飽和状態に達した場合，活性炭の交換が必要である。 | M56: ⑤ 砂ろ過装置では，タイマー又はろ層の損失圧力の計測などにより，ろ材の自動水洗浄が行われる。 | N56: 高度処理・消毒
A57: H24-21 | B57: 平成24年度 | C57: Ⅳ-21 | D57: 水質管理 | E57: BOD負荷・汚泥計算 | F57: 3 | G57: 流入水量・BOD濃度・除去率・汚泥転換率・含水率に基づく長時間ばっ気浄化槽の汚泥発生量計算 | H57: 下記に示す条件の長時間ばっ気方式の浄化槽における汚泥発生量として，最も近い値はどれか。 流入汚水量：200 m³/日，流入水BOD濃度：200 mg/L， 放流水BOD濃度：20 mg/L，汚泥転換率：50 %， 汚泥の含水率（湿量基準）：98 %，汚泥の比重：1.0 | I57: ① 0.02 m³/日 | J57: ② 0.1 m³/日 | K57: ③ 0.9 m³/日 | L57: ④ 1.0 m³/日 | M57: ⑤ 5.0 m³/日 | N57: BOD負荷・汚泥計算
... A74: H25-03 | B74: 平成25年度 | C74: Ⅲ-3 | D74: 建築環境・設備・建築物衛生管理 | E74: 光・音 | F74: 5 | G74: 人工光源の色温度と雰囲気(Kruithof) | H74: 人工光源に関する次の記述のうち，最も不適切なものはどれか。 | I74: ① 白熱電球を用いると，温かみのある雰囲気を出すことができる。 | J74: ② 温白色蛍光ランプを用いると，照度が高い場合に暑苦しい感じになる。 | K74: ③ 白色蛍光ランプを用いると，明視照明では，視対象を正確に認識するのに好ましい照明となる。 | L74: ④ 昼光色蛍光ランプを用いると，すがすがしい雰囲気となる。 | M74: ⑤ 昼光色蛍光ランプを用いると，照度が高い場合に陰気な感じになる。 | N74: 照明・光環境
A75: H25-04 | B75: 平成25年度 | C75: Ⅲ-4 | D75: 建築環境・設備・建築物衛生管理 | E75: 換気・室内空気 | F75: 4 | G75: 直列開口の合成相当開口面積計算 | H75: 二面開口住戸の通風性能について，風上開口の相当（有効）開口面積α1A1，風下開口の相当（有効）開口面積α2A2が下図に示す値である場合，それらの直列合成による相当（有効）開口面積（合成αA）の値に最も近いものはどれか。［図：α1A1＝10.0 m²，α2A2＝5.0 m²］ | I75: ① 0.6 m² | J75: ② 1.8 m² | K75: ③ 3.3 m² | L75: ④ 4.5 m² | M75: ⑤ 15.0 m² | N75: 換気・通風 | O75: 図表
A76: H25-05 | B76: 平成25年度 | C76: Ⅲ-5 | D76: 建築環境・設備・建築物衛生管理 | E76: 熱・湿気 | F76: 3 | G76: 建材の熱伝導率の順(GW<ALC<せっこう<ガラス<Al) | H76: 次の（a）～（e）の建築材料の熱伝導率（W／m･K）について，小さいものから順に並べたものはどれか。 （a）軽量気泡コンクリートパネル （b）フロートガラス （c）せっこうボード （d）住宅用グラスウール断熱材10K （e）アルミニウム合金 | I76: ① d，c，a，e，b | J76: ② d，a，b，c，e | K76: ③ d，a，c，b，e | L76: ④ a，d，c，b，e | M76: ⑤ a，d，b，c，e | N76: 伝熱・断熱
A77: H25-06 | B77: 平成25年度 | C77: Ⅲ-6 | D77: 建築環境・設備・建築物衛生管理 | E77: 空調 | F77: 4 | G77: 冷却除湿・バイパスファクタ計算(除去熱量・除湿量) | H77: 温度32℃，相対湿度65％の外気10,000m³／hを，冷却コイルに通して，冷却除湿する。コイルの表面温度を10℃，バイパスファクタを10％としたとき，除去される熱量Q，除湿量Lの組合せとして最も適切なものはどれか。ただし，与条件は以下のとおりとする。 空気の比容積（比体積）：0.83 m³／kg′ 外気の全熱量（エンタルピー）：83.5 kJ／kg′，絶対湿度：0.0200 kg／kg′ コイル表面の空気の全熱量（エンタルピー）：29.0 kJ／kg′，絶対湿度：0.0077 kg／kg′ | I77: ① Q：66,000 kJ／h L：15 kg／h | J77: ② Q：491,000 kJ／h L：111 kg／h | K77: ③ Q：545,000 kJ／h L：123 kg／h | L77: ④ Q：591,000 kJ／h L：133 kg／h | M77: ⑤ Q：657,000 kJ／h L：148 kg／h | N77: 空調計算（負荷・空気線図・冷凍サイクル）
A78: H25-07 | B78: 平成25年度 | C78: Ⅲ-7 | D78: 建築環境・設備・建築物衛生管理 | E78: 空調 | F78: 2 | G78: 冷凍サイクルp-h線図とCOP | H78: 次の記述の，［ ］に入る記号又は数式の組合せとして最も適切なものはどれか。 下図に示す圧縮式冷凍機の冷凍サイクルにおいて，［A］は圧縮過程を，［B］は蒸発過程をそれぞれ示しており，この冷凍サイクルの成績係数は，［C］で表される。［図：p-h線図。1→2は蒸発，2→3は圧縮，3→4は凝縮，4→1は膨張。エンタルピーはh1，h2，h3］ | I78: ① A：1→2 B：2→3 C：(h3－h2)／(h2－h1) | J78: ② A：2→3 B：1→2 C：(h2－h1)／(h3－h2) | K78: ③ A：2→3 B：3→4 C：(h3－h1)／(h3－h2) | L78: ④ A：3→4 B：1→2 C：(h2－h1)／(h3－h1) | M78: ⑤ A：3→4 B：2→3 C：(h3－h2)／(h3－h1) | N78: 空調計算（負荷・空気線図・冷凍サイクル） | O78: 図表
A79: H25-08 | B79: 平成25年度 | C79: Ⅲ-8 | D79: 建築環境・設備・建築物衛生管理 | E79: 空調 | F79: 1 | G79: 空調設備(冷却塔の定義誤り) | H79: 空気調和設備に関する次の記述のうち，最も不適切なものはどれか。 | I79: ① 冷却塔は冷却水を用いて，空気を冷却する装置である。 | J79: ② 全熱交換器の熱交換エレメント保護のため，給気側及び排気側のそれぞれの上流側にエアフィルタを設ける。 | K79: ③ コージェネレーションのガスタービンからの排ガスは，温度が高いので，その排熱は一般的に蒸気の形で回収されることが多い。 | L79: ④ 変流量方式の水量制御には，二方弁が用いられる。 | M79: ⑤ 吸収式冷凍機では，一般に冷媒に水，吸収液に臭化リチウム水溶液を用い，高い真空度を保つ容器内で運転される。 | N79: 空調方式・省エネルギー
A80: H25-09 | B80: 平成25年度 | C80: Ⅲ-9 | D80: 建築環境・設備・建築物衛生管理 | E80: 空調 | F80: 4 | G80: 空調ダクト(等摩擦法) | H80: 空調ダクトに関する次の記述のうち，最も不適切なものはどれか。 | I80: ① 静圧再取得とは，分岐ダクト取り出し部の後での主ダクトでの静圧上昇をいう。 | J80: ② ダクト風量［m³/h］，目標摩擦損失［Pa/m］を設定すれば，ダクトの摩擦抵抗線図を用いて必要な円ダクトの直径［mm］と断面風速［m/s］を知ることができる。 | K80: ③ 空調換気用ダクトの断面積が等しくても，アスペクト比が異なれば，ダクトの摩擦抵抗は異なる。 | L80: ④ 等摩擦法では送風機から各吹出し口までの経路の長さが異なる場合は，長さの短いダクト断面の縦又は横の寸法を大きくするなどして抵抗を調整する必要がある。 | M80: ⑤ ダクトの断面積の変化に応じて生じる動圧の変化量の絶対値は，静圧の変化量の絶対値に等しい。 | N80: 空調機器・ダクト・熱源
A81: H25-10 | B81: 平成25年度 | C81: Ⅲ-10 | D81: 建築環境・設備・建築物衛生管理 | E81: 給排水・防災 | F81: 3 | G81: 給排水(吐水口空間は壁面の影響を受ける) | H81: 給排水設備に関する次の記述のうち，最も不適切なものはどれか。 | I81: ① 上水貯水槽への給水管の流入口端は，貯水槽内の横取り出しオーバフロー管下端との間に吐水口空間を設けなければならない。 | J81: ② 上水貯水槽に設置するオーバフロー管や排水管は，間接排水とする。 | K81: ③ 上水の水栓と水受け容器のあふれ縁との間に設ける吐水口空間は，近接する壁面からの距離の影響を受けない。 | L81: ④ 大便器の洗浄弁（フラッシュバルブ）では，給水管内部が負圧になったときに便器内の水の吸い上げを防止するためバキュームブレーカが働く。 | M81: ⑤ 飲料用の給水・給湯系統と雑用水系統や空調設備機器補給水系統などの異なる系統がバルブで接続されるとクロスコネクションのおそれがある。 | N81: 排水・通気・衛生器具
A82: H25-11 | B82: 平成25年度 | C82: Ⅲ-11 | D82: 建築環境・設備・建築物衛生管理 | E82: 給排水・防災 | F82: 5 | G82: 防火・避難計画 | H82: 建物の防火・避難計画に関する次の記述のうち，最も不適切なものはどれか。 | I82: ① 防災センターは火災の防災拠点であり，煙の侵入などで機能しなくなることがあってはならず，可燃物のある空間などとは完全に区画しておく必要がある。 | J82: ② 避難階段への前室の設置は，避難者の滞留の処理や階段への煙の流入防止の上で有効である。 | K82: ③ 大規模な物品販売店などのように避難者が非常に多い場合は，低層部の屋上広場を一時的な避難場所とする計画も避難安全性を高める効果がある。 | L82: ④ 自然排煙口は直接外気に面し，かつ建築物の他の部分へ悪影響を与えないように配慮する。 | M82: ⑤ 避難階段内の避難流動に支障がないように，階段有効幅よりも階段入口幅が大きくなるように配慮して設計する。 | N82: 防災・排煙・消火
A83: H25-12 | B83: 平成25年度 | C83: Ⅲ-12 | D83: 建築環境・設備・建築物衛生管理 | E83: 換気・室内空気 | F83: 5 | G83: 室内空気質の測定法(TOC等) | H83: 室内空気質の測定方法に関する次の記述のうち，最も不適切なものはどれか。 | I83: ① ザルツマン法とは，二酸化窒素を吸収発色液に吸収し，発色させて吸光度を測定し，二酸化窒素濃度を求めるものである。 | J83: ② ロウボリウムエアサンプラを用いた浮遊粉じん濃度測定方法は，ろ過材を通して空気を吸引し，ろ過材上に捕集した粉じんの質量を計測して粉じん濃度を求める方法である。 | K83: ③ オゾン濃度の連続測定法には，紫外線吸収法がある。 | L83: ④ ホルムアルデヒド濃度の精密測定には，DNPH含浸カートリッジ・HPLC法が用いられる。 | M83: ⑤ 二酸化炭素濃度を測定する場合，検知管法と化学発光法を利用した測定が最も普及している。 | N83: 室内空気質・健康影響・衛生動物
A84: H25-13 | B84: 平成25年度 | C84: Ⅲ-13 | D84: 建築環境・設備・建築物衛生管理 | E84: 換気・室内空気 | F84: 2 | G84: 室内空気汚染(空気齢) | H84: 室内空気汚染に関する次の記述のうち，最も不適切なものはどれか。 | I84: ① 事務所建築における室内空気中の細菌の主な発生源は，外気の導入に伴って室内へ侵入するもの，居住者から発生するもの，空調設備や室内に棲みついているものに分類される。 | J84: ② 空気齢とは，建築物に入った所定量の外気が，室内のある地点に到達するまでに経過する平均時間のことであり，空気齢が小さいほど，その地点に供給される空気が汚染されている可能性が高い。 | K84: ③ 一酸化炭素は，無味，無臭，無色，無刺激な気体であり，炭素を含む物質の不完全燃焼により生成する。 | L84: ④ 粉じんは人間活動，喫煙，燃焼により発生し，粒径0.5〜2.0μmのものが肺胞内に沈着しやすく，じん肺症の原因となる。 | M84: ⑤ 室内汚染物質の濃度を許容値以下に抑える方法として換気による希釈が広く採用されるが，ろ過や吸着による除去が併用されることもある。 | N84: 室内空気質・健康影響・衛生動物
A85: H25-14 | B85: 平成25年度 | C85: Ⅲ-14 | D85: 建築環境・設備・建築物衛生管理 | E85: 換気・室内空気 | F85: 1 | G85: 空気清浄機の原理(吸着法はCOに無効) | H85: 空気清浄機の清浄原理に関する次の記述のうち，最も不適切なものはどれか。 | I85: ① 吸着法は活性炭などのように表面積の大きな吸着剤により吸着除去する方式で，一酸化炭素に対して効果がある。 | J85: ② 衝突粘着式は粘着剤を塗布した金網・金属板などに粉じんを慣性力で衝突させて除去する方式で，比較的大きな粉じんを対象とする。 | K85: ③ 静電式は高圧電界による荷電及び吸引付着力により粉じんを除去する方式で，比較的微細な粉じんを対象とする。 | L85: ④ ろ過式は，繊維などによる多孔質空間の中を粉じんが通過するとき，衝突・さえぎり・拡散などによって粉じんを捕集する。粗粉じん用から微細粉じん用まで種類が多く，一般に最も多く利用されている。 | M85: ⑤ 吸収法は水又は薬液などによって有害ガスを吸収させる方式で，特定のガスに対して効果的である。 | N85: 室内空気質・健康影響・衛生動物
A86: H25-15 | B86: 平成25年度 | C86: Ⅲ-15 | D86: 建築環境・設備・建築物衛生管理 | E86: 換気・室内空気 | F86: 4 | G86: CO2濃度から換気回数計算 | H86: 機械換気が行われている床面積64m²，天井高2.5mの居室内に36人の在室者がいるとき，室内二酸化炭素濃度は900ppmに維持されていた。この居室で行われている機械換気の換気回数に最も近いものはどれか。ただし，その居室に取り入れられる外気の二酸化炭素濃度は400ppm，1人当たりの二酸化炭素発生量は20L/hとする。 | I86: ① 0.11 | J86: ② 0.5 | K86: ③ 5.0 | L86: ④ 9.0 | M86: ⑤ 11.0 | N86: 換気・通風
A87: H25-16 | B87: 平成25年度 | C87: Ⅲ-16 | D87: 建築環境・設備・建築物衛生管理 | E87: 光・音 | F87: 3 | G87: 空気音・床衝撃音遮断性能(L値は小さい方が高性能) | H87: 空気音遮断性能及び床衝撃音遮断性能の測定及び評価に関する次の記述のうち，最も不適切なものはどれか。 | I87: ① 空気音遮断性能の測定によって得られた室間音圧レベル差（Dr）が大きいほど，空気音遮断性能が高い。 | J87: ② 空気音遮断性能の測定では，2室の一方にノイズ音源を置き，2室の平均音圧レベル差の周波数特性を測定する。 | K87: ③ 床衝撃音レベルL-45の床は，L-65の床よりも，床衝撃に対する遮音性能は低い。 | L87: ④ 重量床衝撃音レベルの測定では，上階でタイヤ落下などによる加振装置を用いて振動を発生させ，下階の音圧レベルを測定する。 | M87: ⑤ 軽量床衝撃音レベルの測定では，上階でタッピングマシンを用いて振動を発生させ，下階の63Hzから4kHzのオクターブバンド音圧レベルを測定する。 | N87: 音環境
A88: H25-17 | B88: 平成25年度 | C88: Ⅲ-17 | D88: 建築環境・設備・建築物衛生管理 | E88: 温熱・省エネ指標 | F88: 1 | G88: 温冷感指標 PMV/MRT/OT/ET*/clo | H88: 温冷感に関する次の記述のうち，最も不適切なものはどれか。 | I88: ① PMV（予測平均温冷感申告）は，膨大な被験者実験によって作られた指標であり，PMV＝0の環境条件では，全ての人の温冷感は満足した結果となる。 | J88: ② 風が吹いていない室内環境でのグローブ温度は，近似的に気温とMRT（平均放射温度）の平均温度となる。 | K88: ③ 作用温度は気温と放射の影響を考慮した指標である。 | L88: ④ 新有効温度ET*は，生理学の理論に基づく人体の数値モデルで導かれた体感温度指標であり，気温，湿度，気流，放射，着衣量，代謝量の温熱環境6要素の全てを考慮している。 | M88: ⑤ 着衣量は，皮膚の表面から衣服の外表面までの熱抵抗値で表し，単位は0.155 m²・K/Wを1 clo（クロ）として表す。男性でいえば，冬用の三つぞろえスーツを着ている場合が1 clo程度である。 | N88: 温熱環境・温熱指標
A89: H25-18 | B89: 平成25年度 | C89: Ⅲ-18 | D89: 水質管理 | E89: BOD負荷・汚泥計算 | F89: 4 | G89: BOD容積負荷・BOD-MLSS負荷計算 | H89: 流入水量1,200 m³/日，流入水のBOD濃度200 mg/Lの汚水を有効容量400 m³のばっ気槽で処理している。ばっ気槽のMLSS濃度が3,000 mg/Lのとき，ばっ気槽のBOD容積負荷とBOD-MLSS負荷の組合せとして，最も適切なものはどれか。 | I89: ① 0.2 / 0.1 | J89: ② 0.3 / 0.1 | K89: ③ 0.3 / 0.2 | L89: ④ 0.6 / 0.2 | M89: ⑤ 0.6 / 0.3 | N89: BOD負荷・汚泥計算
A90: H25-19 | B90: 平成25年度 | C90: Ⅲ-19 | D90: 水質管理 | E90: 高度処理・消毒 | F90: 1 | G90: リン除去技術でないもの | H90: 次のうち，生活排水処理におけるリン除去技術として用いられないものはどれか。 | I90: ① 不連続点塩素処理法 | J90: ② 嫌気・好気法 | K90: ③ 生物・化学的同時処理法 | L90: ④ 凝集沈殿法 | M90: ⑤ 晶析（接触）脱リン法 | N90: 高度処理・消毒
... A106: H25-35 | B106: 平成25年度 | C106: Ⅲ-35 | D106: 廃棄物管理 | E106: 法制度・リサイクル・循環型社会 | F106: 3 | G106: リサイクル・3R(リサイクル分類) | H106: リサイクルに関する次の記述のうち，最も不適切なものはどれか。 | I106: ① 「循環型社会基本法」は，天然資源の消費を抑制し，環境への負荷を低減するために，大量消費・大量廃棄型社会から，循環型社会への転換を目指すものである。 | J106: ② 3Rは，発生抑制（リデュース），再使用（リユース），再資源化（リサイクル）の略称である。 | K106: ③ リサイクルという言葉は大変広い範囲で使われているが，一般的にはリユース，マテリアルリサイクル，サーマルリサイクルに分類される。 | L106: ④ リユースは，ビンを洗って使う，古着を利用するなど，原型のまま何度も使うことである。 | M106: ⑤ サーマルリサイクルはエネルギーとして利用するものである。 | N106: リサイクル・循環型社会
A107: H26-01 | B107: 平成26年度 | C107: Ⅲ-1 | D107: 建築環境・設備・建築物衛生管理 | E107: 光・音 | F107: 1 | G107: 点光源の水平面照度計算(180cd,3m,30°) | H107: 下図に示す点光源に照らされたA点の水平面照度に最も近い値はどれか。ただし，点光源の配光特性は一様なものとし，反射は考慮しないものとする。［図：点光源の光度180cd，床面からの高さ3m，A点は点光源から見て水平面に対し30°の位置］ | I107: ① 2.5 lx | J107: ② 3.3 lx | K107: ③ 4.3 lx | L107: ④ 5.0 lx | M107: ⑤ 20.0 lx | N107: 照明・光環境 | O107: 図表
A108: H26-02 | B108: 平成26年度 | C108: Ⅲ-2 | D108: 建築環境・設備・建築物衛生管理 | E108: 温熱・省エネ指標 | F108: 4 | G108: 都市・建築環境(代替フロンはCO2より温室効果が大きい) | H108: 都市・建築環境に関する次の記述のうち，最も不適切なものはどれか。 | I108: ① 都市の緑化は，気温低減，保水による水循環改善，吸音，喧噪感の低減など，多面的な環境改善に役立つ。 | J108: ② 市街地の風の鉛直分布は，地表面の建物，障害物によって変化し，建物が立ち並ぶ街区などの風速は上空風速と比べて小さい。ただし，いわゆるビル風は除くものとする。 | K108: ③ 建築に関わるCO2発生量は，建設時のものだけでなく，運用・解体までのライフサイクル全体を評価する必要がある。 | L108: ④ 代替フロンは自然冷媒である二酸化炭素と比較して，大気中の濃度当たりの温室効果の強さは小さい物質である。 | M108: ⑤ ヒートアイランドは都市域の多大な排熱と，コンクリートジャングルに代表される熱放散の起こりにくい都市構造との相乗効果で発生する。 | N108: 省エネ性能指標・都市建築環境
A109: H26-03 | B109: 平成26年度 | C109: Ⅲ-3 | D109: 建築環境・設備・建築物衛生管理 | E109: 換気・室内空気 | F109: 3 | G109: 室内微生物(汚染は時間的・空間的変動が大) | H109: 室内空気中の微生物（細菌・真菌）とそれによる汚染に関する次の記述のうち，最も不適切なものはどれか。 | I109: ① 微生物による汚染の程度は，空中濃度，表面汚染量，落下量で表される。 | J109: ② 住宅において真菌（カビ）には，外気の導入に伴って室内に侵入するものと室内に棲みついているものがある。 | K109: ③ 微生物汚染は温湿度環境，空気清浄装置の有無，換気の条件によらず，時間的・空間的な汚染状況の変化は緩やかであり，汚染の程度は年間を通じて一定である。 | L109: ④ 室内における微生物汚染の対象になる細菌，真菌の種類は極めて多い。 | M109: ⑤ 浮遊微生物のサンプリング装置は主に衝突法によるものとフィルタ法によるものがある。 | N109: 室内空気質・健康影響・衛生動物
A110: H26-04 | B110: 平成26年度 | C110: Ⅲ-4 | D110: 建築環境・設備・建築物衛生管理 | E110: 換気・室内空気 | F110: 2 | G110: 人体と水(女性は脂肪が多く水分割合は低い) | H110: 人体と水に関する次の記述のうち，最も不適切なものはどれか。 | I110: ① 人体の体重当たりの水分の割合は，新生児では体重の約75%，子どもでは約70%，成人では約60〜65%，老人では約50〜55%である。 | J110: ② 一般に女性の方が男性よりも脂肪が多いので，体重当たりの水分の割合が高い傾向がある。 | K110: ③ 体内の水が不足する脱水症状を起こすと，体温を調整する汗が出なくなり，体温が上昇する。 | L110: ④ 代謝水（又は燃焼水）とは，体内でタンパク質や炭水化物，脂肪などが酵素によって分解されるときに排出される水分のことをいう。 | M110: ⑤ 正常な成人が一日に補給すべき必要最低限の水分量は，飲料水など飲み物として約1.3〜1.5リットル/人・日といわれている。 | N110: 室内空気質・健康影響・衛生動物
A111: H26-05 | B111: 平成26年度 | C111: Ⅲ-5 | D111: 建築環境・設備・建築物衛生管理 | E111: 換気・室内空気 | F111: 2 | G111: ねずみ防除・IPM | H111: 建築物におけるねずみ等の防除に関する次の記述のうち，最も不適切なものはどれか。 | I111: ① 建築物におけるねずみ等の防除は，その発生及び侵入の防止並びに駆除により行う。 | J111: ② ねずみ等の防除のために殺そ剤又は殺虫剤を使用する場合，薬事法の承認を受けた医薬品以外を用いてはならない。 | K111: ③ IPM（総合有害生物管理，以下同じ。）では，的確に発生の実態を把握するため，措置前に生息密度調査法に基づく生息実態調査を実施する。 | L111: ④ IPMでは，調査から得られた捕獲指数などをもとに，該当建築物又は該当場所に「許容水準」「警戒水準」「措置水準」の目標水準を設定する。 | M111: ⑤ IPMでは，標準的な目標水準に照らして，有害生物の密度と防除効果の観点から評価を行う。 | N111: 室内空気質・健康影響・衛生動物
A112: H26-06 | B112: 平成26年度 | C112: Ⅲ-6 | D112: 建築環境・設備・建築物衛生管理 | E112: 温熱・省エネ指標 | F112: 2 | G112: 省エネ指標(ηAC=冷房期平均日射熱取得率) | H112: 住宅と建築物の省エネルギー性能指標に関する次の記述のうち，最も不適切なものはどれか。 | I112: ① 外皮平均熱貫流率（UA）は，室内外の温度差が1℃のときの建物全体の外皮で生じる総熱損失量を外皮（外壁や窓等）の表面積の合計で除して算出される。 | J112: ② 住宅における冷房期の平均日射熱取得率（ηA）は，冷房期の総日射熱取得量を床面積で除して算出される。 | K112: ③ 外皮基準の指標である従来の年間熱負荷係数（PAL）に対し，年間熱負荷係数（PAL*）は潜熱負荷を含めて評価している。 | L112: ④ 非住宅建築物の暖冷房負荷の算出においては，取入外気の熱についても勘案する必要がある。 | M112: ⑤ 一次エネルギーとは，自然界に存在するままの形でエネルギー源として利用される化石燃料や自然エネルギー等によるエネルギーのことをいう。 | N112: 省エネ性能指標・都市建築環境
A113: H26-07 | B113: 平成26年度 | C113: Ⅲ-7 | D113: 建築環境・設備・建築物衛生管理 | E113: 温熱・省エネ指標 | F113: 5 | G113: 建物の温熱環境(相当外気温) | H113: 建物の温熱環境に関する次の記述のうち，最も不適切なものはどれか。 | I113: ① 内断熱は蓄熱負荷を小さく抑え，予熱時には，室温及び壁体の室内表面温度を速やかに所定のレベルに到達させることができる。 | J113: ② ナイトパージにより外気を室内に導入し，外気が保持する冷熱を躯体に蓄熱させ，昼間の冷房の用に供することができる。 | K113: ③ 物体間の放射による熱移動量は，それぞれの物体表面の絶対温度の4乗の差に比例する。 | L113: ④ 相当外気温度とは，外壁面に当たる日射量の影響を見込むため，日射量を等価な温度に換算し外気温に加えた温度である。 | M113: ⑤ 高天井のアトリウムの冷房では，空気による熱供給を居住域にとどめることが困難なので，床面からの放射冷房が適している。 | N113: 温熱環境・温熱指標
A114: H26-08 | B114: 平成26年度 | C114: Ⅲ-8 | D114: 建築環境・設備・建築物衛生管理 | E114: 空調 | F114: 1 | G114: 省エネ(VAV 回転数制御の方が効果大) | H114: 省エネルギーに関する次の記述のうち，最も不適切なものはどれか。 | I114: ① 近代的なオフィスビルで，冷房負荷軽減のためLow-eガラスを複層ガラスの室内側ガラスに採用した。 | J114: ② 全熱交換器の効果は，必要外気量が多い建物ほど期待でき，外気冷房の効果は内部発熱が大きく，必要外気量が少ない建物ほど期待できる。 | K114: ③ ヒートポンプ方式は適当な温度の採熱源さえあれば，暖房負荷より少ない投入エネルギーで暖房ができる。 | L114: ④ 変風量（VAV）方式の風量制御は，ダンパ制御より回転数制御の方が省エネルギー効果が大きい。 | M114: ⑤ 床吹き出し空調方式では，冷房運転時の吹き出し温度が天井吹き出し方式より高いので，冷熱源の運転や外気冷房などが効率的に行える。 | N114: 空調方式・省エネルギー
A115: H26-09 | B115: 平成26年度 | C115: Ⅲ-9 | D115: 建築環境・設備・建築物衛生管理 | E115: 空調 | F115: 3 | G115: 空気線図の室内負荷 | H115: 下図に示すように，外気冷却コイルで室内空気の湿度を満足させるまで冷却し，還気（加熱又は冷却）コイルで室内温度を満足するように制御して，極力再熱負荷を発生させない空調システムを採用し，さらにCO2制御による外気量制御を採用して省エネルギーを図っている。空気線図上に示す運転状態における室内負荷に最も近い値はどれか。ただし，与条件は以下のとおりとする。 空気の比容積：0.83 m³／kg(DA) 空調吹出し風量：20,000 m³／h 外気風量：4,000 m³／h（定格外気風量：6,000 m³／h，CO2制御） 空調系統：空調系統図参照 空気線図上のポイント：空調系統図参照 システム内発熱（送風機，ダクト断熱）：無視 | I115: ① 60,000 kJ／h | J115: ② 100,000 kJ／h | K115: ③ 145,000 kJ／h | L115: ④ 270,000 kJ／h | M115: ⑤ 315,000 kJ／h | N115: 空調計算（負荷・空気線図・冷凍サイクル） | O115: 図表
A116: H26-10 | B116: 平成26年度 | C116: Ⅲ-10 | D116: 建築環境・設備・建築物衛生管理 | E116: 給排水・防災 | F116: 3 | G116: 給排水設備 最も適切(通気管は排水管に勾配をつけて接続) | H116: 建物の給排水設備に関する次の記述のうち，最も適切なものはどれか。 | I116: ① 給水管のウォーターハンマー（水撃作用）を防止するためには，水栓・弁類を速やかに閉じた方がよい。 | J116: ② 給水管の圧力損失は，管内摩擦と形状抵抗の両者によるが，いずれも平均流速にほぼ比例して増大する。 | K116: ③ 通気管は管内の水滴が自然落下によって排水管に流れるようにし，逆こう配にならないように排水管に接続しなければならない。 | L116: ④ 便器に使用する洗浄弁（フラッシュバルブ）の必要圧力は，ゲージ圧で200 kPa（約2 kgf/cm²）以上必要である。 | M116: ⑤ 自然流下式の排水横管のこう配は流量，管径にかかわらず，1/20とする。 | N116: 排水・通気・衛生器具
A117: H26-11 | B117: 平成26年度 | C117: Ⅲ-11 | D117: 建築環境・設備・建築物衛生管理 | E117: 給排水・防災 | F117: 4 | G117: 給湯設備(循環管) | H117: 給湯設備の設計・施工に関する次の記述のうち，最も不適切なものはどれか。 | I117: ① 中央給湯方式では，一般に55〜60℃で供給し，用途に応じて水と混合させて使用温度に下げる。 | J117: ② 給湯設備のゾーンは，給水の圧力とのバランスを考慮して，給水設備と同じゾーンにゾーニングする。 | K117: ③ 強制循環式給湯配管の必要循環量は小流量で，給湯配管はこの流量に対しては十分に太いので，循環流量による摩擦損失水頭は無視できる程度であり，リバースリターン方式を採用する意味はない。 | L117: ④ 貯湯タンクなどに設置する逃し管（膨張管）は，単独で立ち上げ，保守用の仕切弁を設ける。 | M117: ⑤ 集合住宅の住戸内への採用が多いヘッダ工法では，他の器具の使用による圧力降下や温度降下の影響が少ない。 | N117: 給水・給湯
A118: H26-12 | B118: 平成26年度 | C118: Ⅲ-12 | D118: 建築環境・設備・建築物衛生管理 | E118: 給排水・防災 | F118: 2 | G118: 防災設備(排煙・SP・補助散水栓) | H118: 建物の防災設備に関する次の記述のうち，最も適切なものはどれか。 | I118: ① 泡消火設備は，泡消火剤と水の混合液を泡ヘッドなどの発泡器に送り，空気を吸引して発生させた泡を放射して，泡の冷却作用により消火する設備である。 | J118: ② 建築基準法上の排煙設備は避難安全確保を主目的とし，消防法上の排煙設備は消火活動支援を主目的としている。 | K118: ③ 特別避難階段の付室の排煙は，自然排煙方式でなければならない。 | L118: ④ スプリンクラー設備では，天井面や壁面に取り付けたヘッドから散水し，その窒息作用により消火する。 | M118: ⑤ 補助散水栓は，消防法によりスプリンクラーヘッドの設置を免除されている未警戒部分を防護するために設置されるもので，アラーム弁の一次側配管から分岐する。 | N118: 防災・排煙・消火
A119: H26-13 | B119: 平成26年度 | C119: Ⅲ-13 | D119: 建築環境・設備・建築物衛生管理 | E119: 換気・室内空気 | F119: 3 | G119: 水蒸気発生量から換気量計算 | H119: 室内水蒸気発生量が500 g/hのとき，室内絶対湿度を8 g/kg(DA)に保つための換気量に最も近いものはどれか。ただし，建材や除湿機等の室内の吸放湿・除湿はなく，室温・外気温とも20℃，外気絶対湿度を3 g/kg(DA)，空気密度ρ＝1.2 kg(DA)/m³とする。 | I119: ① 52 m³/h | J119: ② 63 m³/h | K119: ③ 83 m³/h | L119: ④ 100 m³/h | M119: ⑤ 120 m³/h | N119: 換気・通風
A120: H26-14 | B120: 平成26年度 | C120: Ⅲ-14 | D120: 建築環境・設備・建築物衛生管理 | E120: 温熱・省エネ指標 | F120: 1 | G120: 温熱快適性(ET*はGaggeら) | H120: 温熱快適性の評価に関する次の記述のうち，最も不適切なものはどれか。 | I120: ① ET（有効温度）はイェール大学ピアス研究所のGagge博士らにより1971年に発表された理論に基づく体感温度で，人体のぬれ率と平均皮膚温度に基礎を置いている。 | J120: ② 1957年にYaglouとMinardにより提案されたWBGT指数（湿球グローブ温度）は，乾球温度，自然換気状態の湿球温度，グローブ温度より算出され，ET（有効温度）よりも暑熱環境下の熱ストレスの評価に適している。 | K120: ③ ISOでは，室内上下温度による不満足者率が5%以下となるように，くるぶし（床上0.1m）と頭（床上1.1m）との温度差が3℃以内とすることを推奨している。 | L120: ④ 室内のドラフト評価ではADPI（空気拡散性能指数）がよく使用され，その値は大きいほど居住域の快適域が広く，気流分布が良好であることを示す。 | M120: ⑤ ISOでは，快適なPMV（予想平均温冷感申告）とPPD（予想不満足者率）の値として，−0.5＜PMV＜＋0.5，PPD＜10%を推奨している。 | N120: 温熱環境・温熱指標
A121: H26-15 | B121: 平成26年度 | C121: Ⅲ-15 | D121: 建築環境・設備・建築物衛生管理 | E121: 光・音 | F121: 4 | G121: 照明(光束発散度rlx, 逐点法) | H121: 照明に関する次の記述のうち，最も不適切なものはどれか。 | I121: ① 出射する光束の密度を光束発散度［rlx］という。 | J121: ② 光束は，単位時間当たりの光の放射エネルギーに標準比視感度を乗じて求めた値である。 | K121: ③ 窓や照明器具など光源からの直接光による直接照度と，壁や家具での反射を経た間接光による間接照度をそれぞれ計算し，両者の和を全照度とする計算方法を逐点法という。 | L121: ④ 高圧水銀ランプのランプ効率［lm/W］は，ハロゲンランプのランプ効率［lm/W］よりも低い。 | M121: ⑤ 平均演色評価数Raは，15試験色のうち，1から8番目の試験色に関する特殊演色評価数の平均値で表される。 | N121: 照明・光環境
A122: H26-16 | B122: 平成26年度 | C122: Ⅲ-16 | D122: 建築環境・設備・建築物衛生管理 | E122: 光・音 | F122: 3 | G122: 室の残響 | H122: 室の残響に関する次の記述のうち，最も不適切なものはどれか。 | I122: ① 残響時間は，室内のエネルギー密度が音源を停止した時点から百万分の1，すなわち10⁻⁶になるまでの時間である。 | J122: ② 室内の平均的な音圧レベルは，音源の音響パワーレベルだけではなく，室の等価吸音面積に依存する。 | K122: ③ 空間容積が小さい室では，空気の音響吸収を考慮したEyring-Knudsenの式を用いなければならない。 | L122: ④ ロックウールやグラスウール，軟質繊維板などの繊維系材料の吸音特性は，一般に高周波数域で大きく，低周波数域で小さい。 | M122: ⑤ 壁どうしあるいは天井と床のあいだなどの堅くて平行した面の間などで，反射音が次々と時間的に一定の間隔で到来してくる現象を鳴竜（flutter echo）という。 | N122: 音環境
A123: H26-17 | B123: 平成26年度 | C123: Ⅲ-17 | D123: 建築環境・設備・建築物衛生管理 | E123: 換気・室内空気 | F123: 5 | G123: 換気(中性帯は小さい開口部に近づく) | H123: 換気に関する次の記述のうち，最も不適切なものはどれか。 | I123: ① 換気は，居住者の健康を保持するために，室内で発生する汚染物質を希釈あるいは除去することを目的としている。 | J123: ② 第3種換気方式は室内を負圧に保つため，汚染源の拡散防止に有効な方法である。 | K123: ③ 第1種換気方式は給気装置と排気装置の両方を備えたシステムである。 | L123: ④ 燃焼器具等を使用する室の換気設備等に関しては，建築基準法に規定されている。 | M123: ⑤ 上下に大きさの異なる2つの開口部がある室において，無風の条件で温度差換気を行う場合，中性帯の位置は一般に大きい開口部よりも小さい開口部の方に近づく。 | N123: 換気・通風
A124: H26-18 | B124: 平成26年度 | C124: Ⅲ-18 | D124: 建築環境・設備・建築物衛生管理 | E124: 空調 | F124: 4 | G124: パッシブソーラー(熱伝導率が大きい材料は不適) | H124: パッシブソーラーシステムに関する次の記述のうち，最も不適切なものはどれか。 | I124: ① パッシブソーラーシステムに求められる性能は，日射熱取得性能，断熱・気密性能，蓄熱性能である。 | J124: ② 壁を蓄熱部位とするとき，容積が一定である場合には，厚さよりも面積を確保する方が，蓄熱性がより高くなる。 | K124: ③ 壁の蓄熱部位に，容積比熱が大きく，熱伝導率が高い材料を選ぶと蓄熱性が高くなる。 | L124: ④ 直接蓄熱方式とは，居住空間に属している付設温室型，屋根面に独立している空気集熱型などのように，集熱部と蓄熱部を分離して，その間で熱の輸送を行う方式である。 | M124: ⑤ 蓄熱性能を高めると，日中のオーバーヒートを抑制して夜間の室内温度低下を抑えることができる。 | N124: 空調方式・省エネルギー
A125: H26-19 | B125: 平成26年度 | C125: Ⅲ-19 | D125: 水質管理 | E125: 活性汚泥・浄化槽 | F125: 5 | G125: 接触ばっ気槽の影響因子(汚泥返送量は無関係) | H125: 次のうち，接触ばっ気槽の処理機能に影響を与える因子として最も不適切なものはどれか。 | I125: ① BOD容積負荷 | J125: ② 滞留時間 | K125: ③ ばっ気強度 | L125: ④ 接触材充填率 | M125: ⑤ 汚泥返送量 | N125: 活性汚泥・生物処理
A126: H26-20 | B126: 平成26年度 | C126: Ⅲ-20 | D126: 水質管理 | E126: 高度処理・消毒 | F126: 3 | G126: 高度処理装置 | H126: 中・大規模な汚水処理施設に適用される高度処理装置に関する次の記述のうち，最も不適切なものはどれか。 | I126: ① 活性炭吸着装置はCOD，色度及び臭気の除去を目的としている。 | J126: ② 凝集分離装置はリン，浮遊物質及びBODの除去を目的としている。 | K126: ③ 砂ろ過装置はコロイド粒子及び溶解性物質の除去を目的としている。 | L126: ④ 活性炭吸着装置では，吸着飽和状態に達した場合，活性炭の交換が必要である。 | M126: ⑤ 砂ろ過装置では，タイマー又はろ層の損失圧力の計測などにより，ろ材の自動水洗浄が行われる。 | N126: 高度処理・消毒
A127: H26-21 | B127: 平成26年度 | C127: Ⅲ-21 | D127: 水質管理 | E127: 水質指標・環境基準 | F127: 1 | G127: 汚水流量計 | H127: 排水処理施設の汚水量を計測する流量計について，水中の固形物の影響が最も少ない方式は次のうちどれか。 | I127: ① 電磁式 | J127: ② オリフィス式 | K127: ③ ベンチュリー管式 | L127: ④ フロート形面積式 | M127: ⑤ 羽根車式 | N127: 水質指標・試験方法・測定
A128: H26-22 | B128: 平成26年度 | C128: Ⅲ-22 | D128: 水質管理 | E128: 活性汚泥・浄化槽 | F128: 4 | G128: 生物学的有機性排水処理(硝化は好気条件) | H128: 生物学的有機性排水に関する次の記述のうち，最も不適切なものはどれか。 | I128: ① 好気的な活性汚泥法では，有機物が最終的に二酸化炭素，アンモニア，水に分解される。本法の利点は嫌気的な生物処理に比べて処理時間が短いことである。 | J128: ② 好気的な活性汚泥法の欠点は，生成する活性汚泥量が嫌気的な生物処理法と比べて多いことである。 | K128: ③ 嫌気的処理法では，有機物は最終的にメタン，二酸化炭素，アミンなどに分解される。本法の利点は，生成するメタンを燃料として再利用できることである。 | L128: ④ 有機物中の窒素は，さまざまな微生物によりアンモニアに分解され，アンモニアは，Nitrosomonas属，Nitrobacter属などの硝化菌により嫌気条件下で硝酸塩に酸化される。 | M128: ⑤ 生成した硝酸塩は，Pseudomonas属などの脱窒菌により嫌気条件下でN₂に還元され，大気中に放出される。 | N128: 活性汚泥・生物処理
A129: H26-23 | B129: 平成26年度 | C129: Ⅲ-23 | D129: 水質管理 | E129: 活性汚泥・浄化槽 | F129: 1 | G129: 嫌気ろ床接触ばっ気方式浄化槽 | H129: 下図に示す嫌気ろ床接触ばっ気方式の小型浄化槽に関する次の記述のうち，最も不適切なものはどれか。 | I129: ① 流入水は嫌気ろ床槽第1室のろ床を通過し，流入水中の浮遊物質は浮上して蓄積される。 | J129: ② 嫌気ろ床第1室で捕捉されなかった浮遊物質は第2室において捕捉される。 | K129: ③ 接触ばっ気槽においては接触材に付着した好気性微生物膜によって水中の有機物が除去される。 | L129: ④ 沈殿槽で処理水と汚泥に分離された後，消毒される。 | M129: ⑤ はく離した生物膜は汚泥として嫌気ろ床槽に戻される。 | N129: 浄化槽 | O129: 図表
A130: H26-24 | B130: 平成26年度 | C130: Ⅲ-24 | D130: 廃棄物管理 | E130: 災害廃棄物・事業方式・統計・管理票 | F130: 3 | G130: H24一般廃棄物排出量(4.5千万t, 1.0kg) | H130: 平成24年度における全国の一般廃棄物の排出状況に関する次の記述の，［ア］［イ］に入る数値の組合せとして最も適切なものはどれか。 ごみ総排出量は，年間約［ア］千万トンであり，1人1日当たりに換算すれば，約［イ］キログラムである。 | I130: ① 3.5 / 0.8 | J130: ② 3.5 / 1.0 | K130: ③ 4.5 / 1.0 | L130: ④ 4.5 / 1.2 | M130: ⑤ 5.5 / 1.2 | N130: 排出量・処理状況の統計
A131: H26-25 | B131: 平成26年度 | C131: Ⅲ-25 | D131: 廃棄物管理 | E131: 法制度・リサイクル・循環型社会 | F131: 5 | G131: 廃棄物処理・リサイクル(EPR) | H131: 廃棄物処理，リサイクルに関する次の記述のうち，最も適切なものはどれか。 | I131: ① 一般廃棄物とは産業廃棄物以外の廃棄物をいい，その処理責任は排出者である個々の市民や事務所等にある。 | J131: ② 産業廃棄物とは事業活動に伴って発生するすべての廃棄物をいい，その処理責任は事業者にある。 | K131: ③ 3Rについて，今後は，特に3番目のRであるRepair（修理して長く使い続ける）に力を置くべきである。 | L131: ④ 「排出者責任」とは，廃棄物を排出する者がその適正処理に責任を負うべき，との考え方であるが，汚染者負担原則（PPP）と矛盾するものである。 | M131: ⑤ 「拡大生産者責任（EPR）」とは，生産者は，その生産した製品が使用され，廃棄された後においても，当該製品の適切なリユース，リサイクルや処分に一定の責任を負う，という考え方である。 | N131: リサイクル・循環型社会
A132: H26-26 | B132: 平成26年度 | C132: Ⅲ-26 | D132: 廃棄物管理 | E132: 法制度・リサイクル・循環型社会 | F132: 4 | G132: 第3次循環基本計画の2020年度目標にない指標 | H132: 次に示す指標のうち，平成25年5月策定の第3次循環型社会形成推進基本計画において，2020年度の数値目標に定められていないものはどれか。 | I132: ① 1人1日当たりの家庭系ごみ排出量 | J132: ② 事業系ごみ排出量 | K132: ③ 産業廃棄物の最終処分量 | L132: ④ 産業廃棄物処理業者数 | M132: ⑤ 循環利用率 | N132: リサイクル・循環型社会
A133: H26-27 | B133: 平成26年度 | C133: Ⅲ-27 | D133: 廃棄物管理 | E133: 法制度・リサイクル・循環型社会 | F133: 2 | G133: リサイクル関連法(家電リサイクル法の役割分担) | H133: リサイクル関連法に関する次の記述のうち，最も不適切なものはどれか。 | I133: ① 建設リサイクル法では，建設工事の受注者等に対して分別解体等及び再資源化等の実施を義務付けているが，対象となるのは一定規模以上の工事である。 | J133: ② 容器包装廃棄物のリサイクルに必要な費用は，分別収集と保管の経費も含めて，容器包装の製造・利用事業者が負担している。 | K133: ③ 家電リサイクル法では，廃家電4品目について，小売業者に収集・運搬の義務を，製造業者等にリサイクルの義務を課し，消費者（排出者）がそのための費用を負担するという役割分担を定めている。 | L133: ④ 食品リサイクル法は，食品廃棄物の発生抑制と減量化により最終処分量を減少させるとともに，食品関連事業者による食品循環資源の再生利用等を促進するものである。 | M133: ⑤ 資源有効利用促進法では，使用済み物品等及び副産物の発生の抑制並びに再生資源及び再生部品の利用の促進のために必要な措置を講ずることとしている。 | N133: リサイクル・循環型社会
A134: H26-28 | B134: 平成26年度 | C134: Ⅲ-28 | D134: 廃棄物管理 | E134: 焼却・ごみ質・熱回収 | F134: 3 | G134: 廃棄物焼却(ストーカ・流動床) | H134: 廃棄物の焼却に関する次の記述のうち，最も適切なものはどれか。 | I134: ① ストーカ式燃焼設備では，投入されたごみが階段状のストーカ上で，乾燥・燃焼・後燃焼・ガス化の順で処理が進む。 | J134: ② 流動床式燃焼設備は，流動用押し込み空気により流動層を形成している高温流動媒体の中で，ごみの乾燥・燃焼を行うものである。ストーカ式燃焼設備よりも燃焼時間が短く炉も小さくて済むが，間欠運転に向かない。 | K134: ③ 回転式燃焼設備は，円筒形の燃焼炉本体を連続して緩やかに回転させ，その回転により送りと攪拌の作用を的確に行って乾燥，燃焼あるいは後燃焼を行うものである。 | L134: ④ 通常，燃焼室内温度は800〜900℃程度に保たれているが，環境対策にはさらに高温であることが望ましい。 | M134: ⑤ 排ガスは電気集じん装置やバグフィルターでHClやSOx，NOxが取り除かれ，その後は湿式充填塔やベンチュリスクラバなどの排ガス洗浄装置で主にばいじんが除去され，煙突から大気に拡散される。 | N134: 焼却・熱回収・ダイオキシン
A135: H26-29 | B135: 平成26年度 | C135: Ⅲ-29 | D135: 廃棄物管理 | E135: 法制度・リサイクル・循環型社会 | F135: 2 | G135: 破砕・圧縮・選別 | H135: 廃棄物の破砕・圧縮・選別に関する次の記述のうち，最も適切なものはどれか。 | I135: ① 一般家庭から排出されるごみのうち，燃えるごみとして集められたものは焼却施設へ，粗大ごみは破砕施設へ搬入される。これらの残渣の全ては，そのまま最終処分場で埋立処分される。 | J135: ② 畳，布団などの可燃性粗大物は回転式破砕機では処理できないので，せん断式破砕機を用いる。 | K135: ③ スチール缶，アルミ缶，プラスチックボトルが混在している場合，これらをこの3素材に分けるためには，磁力・磁場を用いるだけではなく，手選別が必須である。 | L135: ④ 破砕施設においては，万が一の危険物の爆発に備え，爆風圧を逃さないよう，室内を密閉する。 | M135: ⑤ 使用済み自動車の処理においては，有用な金属・部品等が取り除かれ，最後にシュレッダーダストが残るが，大部分はプラスチックであり，安定型の最終処分場で埋立処分される。 | N135: 廃棄物処理法・制度・処理施設・その他
A136: H26-30 | B136: 平成26年度 | C136: Ⅲ-30 | D136: 廃棄物管理 | E136: 法制度・リサイクル・循環型社会 | F136: 1 | G136: 自動車リサイクル法 | H136: 使用済み自動車のリサイクル・適正処理をはかるために，「使用済自動車の再資源化等に関する法律（自動車リサイクル法）」が施行された。次の（ア）〜（エ）の記述の正誤の組合せとして，最も適切なものはどれか。 （ア）拡大生産者責任の考えに基づいて自動車製造業者が引き取り等を行わなければならないのは，シュレッダーダストとフロン類の2つである。 （イ）引き取り・リサイクル等の実施義務を負うのは，自動車製造業者のみであり，輸入業者には義務付けられていない。 （ウ）フロン類回収業者は，自動車リサイクル法上の登録を行えば，廃棄物処理法上の許可は不要である。 （エ）解体業者，破砕業者は，都道府県知事等の許可が必要である。 | I136: ① 誤 / 誤 / 正 / 正 | J136: ② 誤 / 正 / 正 / 誤 | K136: ③ 正 / 誤 / 正 / 正 | L136: ④ 誤 / 誤 / 正 / 誤 | M136: ⑤ 正 / 誤 / 誤 / 正 | N136: リサイクル・循環型社会
A137: H26-31 | B137: 平成26年度 | C137: Ⅲ-31 | D137: 廃棄物管理 | E137: 災害廃棄物・事業方式・統計・管理票 | F137: 4 | G137: 災害廃棄物マスタープラン | H137: 「東日本大震災に係る災害廃棄物の処理指針（マスタープラン）」（環境省，平成23年5月16日）に関する次の記述のうち，最も不適切なものはどれか。 | I137: ① 県は，具体的処理方法を定めた災害廃棄物処理の実行計画を作成する。 | J137: ② 市町村は，災害廃棄物処理の実行計画を踏まえ，災害廃棄物の処理を実施する。 | K137: ③ 可燃物については，破砕後，できるだけセメント焼成や廃棄物発電等の有効利用を行う。 | L137: ④ 木くずについては，最終処分量の削減のためにも，復興資材等として被災地で活用することが有効である。 | M137: ⑤ 災害廃棄物処理の中間処理・最終処分のスケジュールは，腐敗性等がある廃棄物については，速やかに処分することとしている。 | N137: 災害廃棄物・指定廃棄物
A138: H26-32 | B138: 平成26年度 | C138: Ⅲ-32 | D138: 廃棄物管理 | E138: 焼却・ごみ質・熱回収 | F138: 4 | G138: 廃棄物の炭化 | H138: 廃棄物の炭化に関する次の記述のうち，最も適切なものはどれか。 | I138: ① 排ガス量や飛灰発生量は炭化の方が焼却より多い。 | J138: ② 炭化物は石炭に比べて塩素含有量が低い。 | K138: ③ 炭化炉内で廃棄物は十分な酸素が存在する条件の下で加熱酸化される。 | L138: ④ 炭化炉で生じる熱分解ガスの熱量を，廃棄物の乾燥や熱分解に利用できる。 | M138: ⑤ 炭化で分離回収される金属は酸化状態で取り出されるため，リサイクル性が低い。 | N138: 焼却・熱回収・ダイオキシン
A139: H26-33 | B139: 平成26年度 | C139: Ⅲ-33 | D139: 廃棄物管理 | E139: 最終処分場・浸出水 | F139: 1 | G139: 安定型処分場に受入可能なもの | H139: 我が国の産業廃棄物最終処分場は，遮断型，管理型，安定型に分類されている。安定型最終処分場が受け入れできる廃棄物は廃プラスチック類，ゴムくず，金属くず，ガラスくず及び陶磁器くず，工作物の除去に伴って生じたコンクリート破片などであるが，除外品目が指定されている。次のうち，安定型最終処分場に受け入れできるもの（すなわち除外品目ではないもの）はどれか。 | I139: ① 廃タイヤ | J139: ② 自動車等破砕物（シュレッダーダスト） | K139: ③ 鉛を含むはんだを使用している廃プリント配線板 | L139: ④ 有機物（例えば食品，油等の有機性の汚濁の原因となる物質）の付着した廃容器包装 | M139: ⑤ 廃ブラウン管側面部 | N139: 最終処分場・浸出水
A140: H26-34 | B140: 平成26年度 | C140: Ⅲ-34 | D140: 廃棄物管理 | E140: 最終処分場・浸出水 | F140: 2 | G140: 埋立処分 | H140: 廃棄物の埋立処分に関する次の記述のうち，最も不適切なものはどれか。 | I140: ① 単にごみを積み上げる，あるいは窪地に埋めることをオープン・ダンプと呼ぶ。 | J140: ② 生ごみなどの有機物は，空気があると嫌気性微生物によって最終的に水と二酸化炭素になる。 | K140: ③ アメリカではラブキャナル事件をきっかけに，スーパーファンド法（包括的環境対処補償責任法）が作られた。 | L140: ④ 最終処分場は立地場所によって，平地，山間，水面・海面に分類される。日本では平地は住民の反対によって土地の確保が難しいため，一般廃棄物の最終処分場は山間が多い。 | M140: ⑤ 準好気性埋立とは，浸出水集排水管とガス抜き管を接続して端部を外部に開放し，自然対流により内部へ空気を侵入させる構造を標準としている。 | N140: 最終処分場・浸出水
A141: H26-35 | B141: 平成26年度 | C141: Ⅲ-35 | D141: 廃棄物管理 | E141: 最終処分場・浸出水 | F141: 5 | G141: 浸出水処理 | H141: 最終処分場の浸出水処理に関する次の記述のうち，最も不適切なものはどれか。 | I141: ① 浸出水処理施設は取水導水設備，浸出水調整設備，水処理設備，放流設備等から構成される。 | J141: ② 埋立地に降った雨の一部は表面流出し，一部は蒸発し，残りが埋立層内に浸透し，浸出水として一般的に降水量の30〜60%が流出してくる。 | K141: ③ 浸出水水質は埋め立てるごみの形状により異なるが，焼却残さや不燃ごみを埋め立てる場合，最大濃度でBOD250 mg/L程度である。 | L141: ④ 焼却残さに含まれる無機塩類により浸出水はカルシウムイオンや塩化物イオンの濃度が高い傾向にある。 | M141: ⑤ 浸出水処理方法は生物処理と物理化学的処理の組合せにより行われる。CODやSSは接触ばっ気法などの物理化学的処理により処理される。 | N141: 最終処分場・浸出水
... A154: H27-13 | B154: 平成27年度 | C154: Ⅲ-13 | D154: 建築環境・設備・建築物衛生管理 | E154: 換気・室内空気 | F154: 4 | G154: 室内環境と健康(クロルピリホス:建築基準法で使用禁止) | H154: 室内環境と健康影響に関する次の記述のうち，最も不適切なものはどれか。 | I154: ① 一酸化炭素（CO）は，化学的には窒息性のガスであり，その赤血球のヘモグロビンへの親和力は，酸素の200〜250倍であるため血液の酸素保持能力を著しく低下させる。 | J154: ② 有機リン殺虫剤の一種であるクロルピリホスは，建築基準法施行令において，建築材料に添加することは禁止されている。 | K154: ③ シックハウス症候群は，建材などから発生するホルムアルデヒド，VOCs（Volatile Organic Compounds）などにより生じる。このためホルムアルデヒド発散建材に関わる規制基準がJIS及びJASにより制定された。 | L154: ④ 1976年にフィラデルフィアで開催された在郷軍人大会で，劇症肺炎の集団感染が生じた。これは土壌菌の一種であるクラドスポリウムが冷却塔を経由して室内に侵入し，この汚染空気を在室者が吸入したことにより生じたものとされている。 | M154: ⑤ 厚生労働省はシックハウス問題解決のために，TVOC（Total Volatile Organic Compounds）については，室内暫定目標値を400 μg/m³以下とするように定めた。 | N154: 室内空気質・健康影響・衛生動物
A155: H27-14 | B155: 平成27年度 | C155: Ⅲ-14 | D155: 建築環境・設備・建築物衛生管理 | E155: 空調 | F155: 3 | G155: 送風機全圧・静圧の分布図 | H155: 下図は，送風機の吹出し側，吸込み側に，それぞれ円形ダクトを取り付け，送風機を運転している状況におけるダクトの全圧，静圧の分布を示したものである。送風機全圧を図中の矢印で示すa, b, c, dの圧力を用いて表すとすれば，最も適切なものは次のうちどれか。ただし，a, b, c, dの値は絶対値である。 | I155: ① a + b + c | J155: ② b + c | K155: ③ b + c + d | L155: ④ c | M155: ⑤ a + b | N155: 空調計算（負荷・空気線図・冷凍サイクル） | O155: 図表
A156: H27-15 | B156: 平成27年度 | C156: Ⅲ-15 | D156: 建築環境・設備・建築物衛生管理 | E156: 光・音 | F156: 3 | G156: 可聴周波数範囲(20〜20,000Hz) | H156: 健常者が聞くことのできる音の周波数範囲として，最も適切なものは次のうちどれか。 | I156: ① 5〜500 Hz | J156: ② 10〜10,000 Hz | K156: ③ 20〜20,000 Hz | L156: ④ 50〜30,000 Hz | M156: ⑤ 100〜30,000 Hz | N156: 音環境
A157: H27-16 | B157: 平成27年度 | C157: Ⅲ-16 | D157: 建築環境・設備・建築物衛生管理 | E157: 換気・室内空気 | F157: 4 | G157: 紫外線の作用(熱中症は赤外線) | H157: 次のうち，紫外線の作用として最も不適切なものはどれか。 | I157: ① 体内のビタミンDの生成 | J157: ② 皮膚の紅斑の出現 | K157: ③ 皮膚のシミやしわ，良性又は悪性腫瘍の出現 | L157: ④ 熱中症の発症 | M157: ⑤ 殺菌作用 | N157: 室内空気質・健康影響・衛生動物
A158: H27-17 | B158: 平成27年度 | C158: Ⅲ-17 | D158: 建築環境・設備・建築物衛生管理 | E158: 換気・室内空気 | F158: 1 | G158: 二面開口の風力換気量計算 | H158: 下図に示す二面開口住戸の風力換気量に最も近い値はどれか。ただし，外部風速（v），各開口部の風圧係数（C），実効面積（αA）は下図に示す値とする。 | I158: ① 6.2 m³/s | J158: ② 6.8 m³/s | K158: ③ 8.8 m³/s | L158: ④ 12.4 m³/s | M158: ⑤ 13.6 m³/s | N158: 換気・通風 | O158: 図表
A159: H27-18 | B159: 平成27年度 | C159: Ⅲ-18 | D159: 水質管理 | E159: 高度処理・消毒 | F159: 1 | G159: リン除去でないもの(不連続点塩素処理=アンモニア除去) | H159: 次の処理法のうち，生活排水処理におけるリン除去技術として用いられないものはどれか。 | I159: ① 不連続点塩素処理法 | J159: ② 嫌気・好気法 | K159: ③ 生物・化学的同時処理法 | L159: ④ 凝集沈殿法 | M159: ⑤ 晶析（接触）脱リン法 | N159: 高度処理・消毒
...

Sheet ジャンル別出題傾向
A1: 技術士一次試験 衛生工学部門 分野別・ジャンル別過去問出題傾向分析
A2: 全16回（H23〜R7、R1本・再を含む）560問の区分別出題状況。数値は「過去問マスターDB」から自動集計。
A4: 大分類(ブロック) | B4: 区分 | C4: 主要出題論点（細目） | D4: 出題特徴 / 傾向 | E4: 問題数（16回計） | F4: 出題された試験回数（16回中） | G4: 1回あたり平均問題数 | H4: 学習優先度 | J4: 年度リスト（集計用）
A5: 建築環境・設備・建築物衛生管理 | B5: 換気・室内空気 | C5: 開口面積・濃度・換気回数・水蒸気発生量の計算、トレーサーガス法、ホルムアルデヒド、ねずみ・IPM、空気清浄機、臭気、微生物 | D5: 計算問題が多く、型が固定。トレーサーガス法・IPMは再出題 | E5: =COUNTIFS(過去問マスターDB!$E$2:$E$561,$B5) -> 69 | F5: =SUMPRODUCT(--(COUNTIFS(過去問マスターDB!$B$2:$B$561,$J$5:$J$20,過去問マスターDB!$E$2:$E$561,$B5)>0)) -> 16 | G5: =E5/COUNTA($J$5:$J$20) -> 4.3125 | H5: =IF(G5>=3,"S (最優先)",IF(G5>=2,"A (高)","B (中)")) -> S (最優先) | J5: 平成23年度
A6: 建築環境・設備・建築物衛生管理 | B6: 空調 | C6: 空調方式・省エネ設備、吹出口・ダクト・ポンプ・ボイラー、冷却除湿・顕熱潜熱負荷・冷凍サイクル | D6: 方式・機器の比較と、冷却除湿・負荷の計算が定番 | E6: =COUNTIFS(過去問マスターDB!$E$2:$E$561,$B6) -> 53 | F6: =SUMPRODUCT(--(COUNTIFS(過去問マスターDB!$B$2:$B$561,$J$5:$J$20,過去問マスターDB!$E$2:$E$561,$B6)>0)) -> 16 | G6: =E6/COUNTA($J$5:$J$20) -> 3.3125 | H6: =IF(G6>=3,"S (最優先)",IF(G6>=2,"A (高)","B (中)")) -> S (最優先) | J6: 平成24年度
A7: 建築環境・設備・建築物衛生管理 | B7: 光・音 | C7: 点光源の照度・光束法の計算、日射遮蔽・昼光利用、残響時間・音圧レベル、遮音・吸音 | D7: 照度・残響などの計算は定型。日射遮蔽・昼光利用は文が使い回される | E7: =COUNTIFS(過去問マスターDB!$E$2:$E$561,$B7) -> 49 | F7: =SUMPRODUCT(--(COUNTIFS(過去問マスターDB!$B$2:$B$561,$J$5:$J$20,過去問マスターDB!$E$2:$E$561,$B7)>0)) -> 16 | G7: =E7/COUNTA($J$5:$J$20) -> 3.0625 | H7: =IF(G7>=3,"S (最優先)",IF(G7>=2,"A (高)","B (中)")) -> S (最優先) | J7: 平成25年度
A8: 建築環境・設備・建築物衛生管理 | B8: 給排水・防災 | C8: 給水圧力・流速・受水槽、給湯、通気管径、トラップ封水、洗浄弁0.07MPa、排煙・消火設備 | D8: 数値と技術基準の正誤判定。洗浄弁の圧力は繰り返し出題 | E8: =COUNTIFS(過去問マスターDB!$E$2:$E$561,$B8) -> 39 | F8: =SUMPRODUCT(--(COUNTIFS(過去問マスターDB!$B$2:$B$561,$J$5:$J$20,過去問マスターDB!$E$2:$E$561,$B8)>0)) -> 16 | G8: =E8/COUNTA($J$5:$J$20) -> 2.4375 | H8: =IF(G8>=3,"S (最優先)",IF(G8>=2,"A (高)","B (中)")) -> A (高) | J8: 平成26年度
A9: 建築環境・設備・建築物衛生管理 | B9: 熱・湿気 | C9: 熱貫流率・熱伝導率の順位、熱移動、間欠暖房、結露防止、湿り空気、比エンタルピー差 | D9: 熱貫流率・熱伝導率の並べ替えは数値を変えて再出題 | E9: =COUNTIFS(過去問マスターDB!$E$2:$E$561,$B9) -> 29 | F9: =SUMPRODUCT(--(COUNTIFS(過去問マスターDB!$B$2:$B$561,$J$5:$J$20,過去問マスターDB!$E$2:$E$561,$B9)>0)) -> 15 | G9: =E9/COUNTA($J$5:$J$20) -> 1.8125 | H9: =IF(G9>=3,"S (最優先)",IF(G9>=2,"A (高)","B (中)")) -> B (中) | J9: 平成27年度
A10: 建築環境・設備・建築物衛生管理 | B10: 温熱・省エネ指標 | C10: PMV・WBGT・作用温度・ET*、上下温度差、UA値・ηA、PAL*、ヒートアイランド | D10: 指標の定義の正誤判定。WBGT・省エネ指標は複数年で出題 | E10: =COUNTIFS(過去問マスターDB!$E$2:$E$561,$B10) -> 25 | F10: =SUMPRODUCT(--(COUNTIFS(過去問マスターDB!$B$2:$B$561,$J$5:$J$20,過去問マスターDB!$E$2:$E$561,$B10)>0)) -> 13 | G10: =E10/COUNTA($J$5:$J$20) -> 1.5625 | H10: =IF(G10>=3,"S (最優先)",IF(G10>=2,"A (高)","B (中)")) -> B (中) | J10: 平成28年度
A11: 建築環境・設備・建築物衛生管理 | B11: 建築物衛生法・レジオネラ | C11: 空気環境の調整基準、特定建築物の定義、レジオネラ対策（貯湯槽60℃） | D11: 数値暗記で得点しやすい。貯湯槽の温度は同じ誤りが繰り返し出る | E11: =COUNTIFS(過去問マスターDB!$E$2:$E$561,$B11) -> 15 | F11: =SUMPRODUCT(--(COUNTIFS(過去問マスターDB!$B$2:$B$561,$J$5:$J$20,過去問マスターDB!$E$2:$E$561,$B11)>0)) -> 8 | G11: =E11/COUNTA($J$5:$J$20) -> 0.9375 | H11: =IF(G11>=3,"S (最優先)",IF(G11>=2,"A (高)","B (中)")) -> B (中) | J11: 平成29年度
A12: 水質管理 | B12: 活性汚泥・浄化槽 | C12: 各種活性汚泥法、MBR、硝化・脱窒、沈殿槽・ばっ気槽の維持管理、浄化槽の構造基準・処理方式 | D12: 原理・運転条件の正誤判定。浄化槽は直近年度で厚め | E12: =COUNTIFS(過去問マスターDB!$E$2:$E$561,$B12) -> 37 | F12: =SUMPRODUCT(--(COUNTIFS(過去問マスターDB!$B$2:$B$561,$J$5:$J$20,過去問マスターDB!$E$2:$E$561,$B12)>0)) -> 15 | G12: =E12/COUNTA($J$5:$J$20) -> 2.3125 | H12: =IF(G12>=3,"S (最優先)",IF(G12>=2,"A (高)","B (中)")) -> A (高) | J12: 平成30年度
A13: 水質管理 | B13: 水質指標・環境基準 | C13: BOD・COD・DOの測定、JIS K 0102、流量計、環境基準・排水基準項目、達成率、大腸菌数 | D13: 達成率は河川＞海域＞湖沼。令和4年度から大腸菌数に変更 | E13: =COUNTIFS(過去問マスターDB!$E$2:$E$561,$B13) -> 36 | F13: =SUMPRODUCT(--(COUNTIFS(過去問マスターDB!$B$2:$B$561,$J$5:$J$20,過去問マスターDB!$E$2:$E$561,$B13)>0)) -> 15 | G13: =E13/COUNTA($J$5:$J$20) -> 2.25 | H13: =IF(G13>=3,"S (最優先)",IF(G13>=2,"A (高)","B (中)")) -> A (高) | J13: 令和元年度(本試験)
A14: 水質管理 | B14: 高度処理・消毒 | C14: リン・窒素除去、膜処理、活性炭・砂ろ過、塩素・オゾン・紫外線消毒 | D14: リン除去でないもの（不連続点塩素処理）が再出題 | E14: =COUNTIFS(過去問マスターDB!$E$2:$E$561,$B14) -> 18 | F14: =SUMPRODUCT(--(COUNTIFS(過去問マスターDB!$B$2:$B$561,$J$5:$J$20,過去問マスターDB!$E$2:$E$561,$B14)>0)) -> 14 | G14: =E14/COUNTA($J$5:$J$20) -> 1.125 | H14: =IF(G14>=3,"S (最優先)",IF(G14>=2,"A (高)","B (中)")) -> B (中) | J14: 令和元年度(再試験)
A15: 水質管理 | B15: BOD負荷・汚泥計算 | C15: BOD容積負荷・BOD-MLSS負荷、汚泥発生量、含水率・濃縮、SVI | D15: 定型計算。数値を変えて再出題 | E15: =COUNTIFS(過去問マスターDB!$E$2:$E$561,$B15) -> 15 | F15: =SUMPRODUCT(--(COUNTIFS(過去問マスターDB!$B$2:$B$561,$J$5:$J$20,過去問マスターDB!$E$2:$E$561,$B15)>0)) -> 13 | G15: =E15/COUNTA($J$5:$J$20) -> 0.9375 | H15: =IF(G15>=3,"S (最優先)",IF(G15>=2,"A (高)","B (中)")) -> B (中) | J15: 令和2年度
A16: 廃棄物管理 | B16: 法制度・リサイクル・循環型社会 | C16: 廃棄物処理法、循環型社会形成推進基本法・基本計画、リサイクル各法、プラスチック、特別管理廃棄物、生活環境影響調査 | D16: 循環基本法の定義問題（循環資源）が再出題。制度の改正に注意 | E16: =COUNTIFS(過去問マスターDB!$E$2:$E$561,$B16) -> 70 | F16: =SUMPRODUCT(--(COUNTIFS(過去問マスターDB!$B$2:$B$561,$J$5:$J$20,過去問マスターDB!$E$2:$E$561,$B16)>0)) -> 16 | G16: =E16/COUNTA($J$5:$J$20) -> 4.375 | H16: =IF(G16>=3,"S (最優先)",IF(G16>=2,"A (高)","B (中)")) -> S (最優先) | J16: 令和3年度
... A19: 廃棄物管理 | B19: 災害廃棄物・事業方式・統計・管理票 | C19: 災害廃棄物処理指針、指定廃棄物、PFI・DBO、一般廃棄物の排出量統計、産廃マニフェスト | D19: 文が使い回される論点が多い。統計は最新年度に更新される | E19: =COUNTIFS(過去問マスターDB!$E$2:$E$561,$B19) -> 27 | F19: =SUMPRODUCT(--(COUNTIFS(過去問マスターDB!$B$2:$B$561,$J$5:$J$20,過去問マスターDB!$E$2:$E$561,$B19)>0)) -> 16 | G19: =E19/COUNTA($J$5:$J$20) -> 1.6875 | H19: =IF(G19>=3,"S (最優先)",IF(G19>=2,"A (高)","B (中)")) -> B (中) | J19: 令和6年度
J20: 令和7年度
A21: 注記
A22: 区分は1問につき1つ。細かい論点は、マスターDBと各年度シートの「出題論点（細目）」列（v16までのサブジャンル）で確認できる。
A23: 問題数：その区分に分類された問題数。出題された試験回数：その区分が1問以上出た試験回数（R1本・R1再は別の回）。ほとんどの区分が毎回出るため、優先度には使っていない。
A24: 学習優先度：1回あたり平均問題数が3問以上＝S、2問以上＝A、それ未満＝B（目安）。

Sheet 正答一覧マトリクス
A1: 衛生工学部門 過去問 16回分 正答番号一覧マトリクス表
A2: 縦軸：設問番号 (問1〜問35) / 横軸：実施年度 (平成23年度〜令和7年度)
A4: 設問番号 | B4: H23 (平成23) | C4: H24 (平成24) | D4: H25 (平成25) | E4: H26 (平成26) | F4: H27 (平成27) | G4: H28 (平成28) | H4: H29 (平成29) | I4: H30 (平成30) | J4: R1本 (令和元年) | K4: R1再 (令和元年) | L4: R2 (令和2年) | M4: R3 (令和3年) | N4: R4 (令和4年) | O4: R5 (令和5年) | P4: R6 (令和6年) | Q4: R7 (令和7年)
A5: 問 1 | B5: 5 | C5: 1 | D5: 4 | E5: 1 | F5: 3 | G5: 5 | H5: 2 | I5: 1 | J5: 1 | K5: 4 | L5: 4 | M5: 4 | N5: 4 | O5: 4 | P5: 4 | Q5: 3
A6: 問 2 | B6: 3 | C6: 4 | D6: 1 | E6: 4 | F6: 2 | G6: 2 | H6: 3 | I6: 1 | J6: 1 | K6: 2 | L6: 5 | M6: 5 | N6: 5 | O6: 3 | P6: 3 | Q6: 5
A7: 問 3 | B7: 1 | C7: 3 | D7: 5 | E7: 3 | F7: 3 | G7: 2 | H7: 1 | I7: 2 | J7: 2 | K7: 1 | L7: 2 | M7: 5 | N7: 3 | O7: 1 | P7: 5 | Q7: 4
A8: 問 4 | B8: 4 | C8: 5 | D8: 4 | E8: 2 | F8: 4 | G8: 4 | H8: 4 | I8: 3 | J8: 1 | K8: 5 | L8: 3 | M8: 2 | N8: 2 | O8: 5 | P8: 2 | Q8: 2
A9: 問 5 | B9: 3 | C9: 2 | D9: 3 | E9: 2 | F9: 5 | G9: 2 | H9: 4 | I9: 1 | J9: 3 | K9: 3 | L9: 1 | M9: 1 | N9: 2 | O9: 3 | P9: 1 | Q9: 2
A10: 問 6 | B10: 1 | C10: 3 | D10: 4 | E10: 2 | F10: 2 | G10: 1 | H10: 1 | I10: 2 | J10: 4 | K10: 4 | L10: 5 | M10: 3 | N10: 3 | O10: 5 | P10: 3 | Q10: 1
A11: 問 7 | B11: 5 | C11: 4 | D11: 2 | E11: 5 | F11: 5 | G11: 2 | H11: 2 | I11: 5 | J11: 3 | K11: 1 | L11: 4 | M11: 4 | N11: 2 | O11: 1 | P11: 5 | Q11: 3
A12: 問 8 | B12: 2 | C12: 5 | D12: 1 | E12: 1 | F12: 2 | G12: 5 | H12: 2 | I12: 4 | J12: 5 | K12: 3 | L12: 2 | M12: 4 | N12: 1 | O12: 2 | P12: 2 | Q12: 2
A13: 問 9 | B13: 1 | C13: 4 | D13: 4 | E13: 3 | F13: 5 | G13: 4 | H13: 2 | I13: 2 | J13: 1 | K13: 2 | L13: 5 | M13: 3 | N13: 5 | O13: 4 | P13: 3 | Q13: 4
A14: 問 10 | B14: 3 | C14: 4 | D14: 3 | E14: 3 | F14: 2 | G14: 5 | H14: 2 | I14: 2 | J14: 5 | K14: 4 | L14: 2 | M14: 5 | N14: 4 | O14: 3 | P14: 4 | Q14: 3
A15: 問 11 | B15: 4 | C15: 2 | D15: 5 | E15: 4 | F15: 2 | G15: 5 | H15: 3 | I15: 5 | J15: 4 | K15: 1 | L15: 3 | M15: 2 | N15: 1 | O15: 4 | P15: 1 | Q15: 2
A16: 問 12 | B16: 5 | C16: 1 | D16: 5 | E16: 2 | F16: 1 | G16: 3 | H16: 1 | I16: 3 | J16: 3 | K16: 2 | L16: 4 | M16: 1 | N16: 3 | O16: 5 | P16: 1 | Q16: 2
... A39: 問 35 | B39: 3 | C39: 4 | D39: 3 | E39: 5 | F39: 3 | G39: 3 | H39: 5 | I39: 4 | J39: 5 | K39: 5 | L39: 2 | M39: 1 | N39: 4 | O39: 4 | P39: 5 | Q39: 5

Sheet 修正履歴
A1: 問題ID | B1: 修正項目 | C1: 修正前 | D1: 修正後 | E1: 根拠
A2: H23-02 | B2: 選択肢⑤ | C2: 周壁や椅子による吸向力が大きい室では，室の平均吸音率を考慮したEyringの式を用いる必要がある。 | D2: 周壁や椅子による吸音力が大きい室では，室の平均吸音率を考慮したEyringの式を用いる必要がある。 | E2: 各年度の問題PDF
A3: H23-04 | B3: 選択肢④ | C3: 直達光を室内の奥まで導くために，南面の開口部に中庭を設け，中庭の上面は反射率が低い仕上げとした。 | D3: 直射光を室内の奥まで導くために，南面の開口部に中庇を設け，中庇の上面は反射率が低い仕上げとした。 | E3: 各年度の問題PDF
A4: H23-08 | B4: 問題文 | C4: 省エネルギー設備機器に関する次の記述のうち，最も不適切なものはどれか。 | D4: 下図に示すように，外気冷却コイルで室内空気の湿度を満足させるまで冷却し，還気（加熱又は冷却）コイルで室内温度を満足するよ… | E4: 各年度の問題PDF
A5: H23-08 | B5: 選択肢① | C5: 空気調和機に使用する全熱交換器では，外気冷房が可能なときに給排気バイパスなどにより熱交換を回避する。 | D5: 224,000 kJ／h | E5: 各年度の問題PDF
A6: H23-08 | B6: 選択肢② | C6: 夜間電力利用の蓄熱槽システムでは，熱源の夜間運転時間が長いほど熱源容量は小さくて済む。 | D6: 325,000 kJ／h | E6: 各年度の問題PDF
A7: H23-08 | B7: 選択肢③ | C7: 蓄熱槽は開放水面を有し，配管経路が開放方式となるため，密閉回路方式に較べて，ポンプ動力が一般的に増大する。 | D7: 448,000 kJ／h | E7: 各年度の問題PDF
A8: H23-08 | B8: 選択肢④ | C8: 多結晶シリコン太陽電池は，単結晶シリコン太陽電池と比較して変換効率が低いが，製造が容易で効率とコストのバランスが良い。 | D8: 602,000 kJ／h | E8: 各年度の問題PDF
A9: H23-08 | B9: 選択肢⑤ | C9: ヒートポンプの冷房時の成績係数（COP）は，圧縮仕事に対する凝縮熱量の比で表す。 | D9: 1,337,000 kJ／h | E9: 各年度の問題PDF
A10: H25-04 | B10: 問題文 | C10: 建築音響・遮音性能に関する次の記述のうち，最も不適切なものはどれか。 | D10: 二面開口住戸の通風性能について，風上開口の相当（有効）開口面積α1A1，風下開口の相当（有効）開口面積α2A2が下図に示… | E10: 各年度の問題PDF
A11: H25-04 | B11: 選択肢① | C11: 単層壁の空気音遮音性能（透過損失）は，壁の面密度と周波数の積の対数に概ね比例する（質量則）。 | D11: 0.6 m² | E11: 各年度の問題PDF
A12: H25-04 | B12: 選択肢② | C12: コインシデンス効果が生じると，特定の周波数帯で壁の透過損失が低下する。 | D12: 1.8 m² | E12: 各年度の問題PDF
... A123: R4-04 | B123: 選択肢② | C123: 予測平均温冷感申告PMVは新有効温度ET*よりも暑暑環境評価を正確に行うことができると考えられている。 | D123: 予測平均温冷感申告PMVは新有効温度ET*よりも暑熱環境評価を正確に行うことができると考えられている。 | E123: 各年度の問題PDF
A124: R4-06 | B124: 公式正答 | C124: 2 | D124: 3 | E124: 解答.pdf（公式正答表）
A125: R4-29 | B125: 問題文 | C125: 厚生省通達「一般廃棄物処理事業に対する指導に伴う留意事項について（昭和52年環整95号、平成2年環環境22号改定）」に示… | D125: 厚生省通達「一般廃棄物処理事業に対する指導に伴う留意事項について（昭和52年環整95号、平成2年衛環22号改定）」に示さ… | E125: 各年度の問題PDF
A126: R5-13 | B126: 選択肢② | C126: 衝突粘着式は，粘着剤を塗布した金網・金属板などに粉じんを慣性力で衝突させて除去する方式で，比較的大きな粉じんを対象とする… | D126: 衝突粘着式は，粘着剤を塗布した金網・金属板などに粉じんを慣性力で衝突させて除去する方式で，粗じん用から微細じん用まで種類… | E126: 各年度の問題PDF
A127: 全体 | B127: サブジャンル（再付与） | C127: 128種類のラベル | D127: 33区分に統一（v28でさらに15区分に集約）（551行を変更） | E127: 問題の主題に基づき再分類。巡回的に付与されていた行（H25〜H27、R1本ほか）を是正
A128: 全体 | B128: 問題のテーマ・内容概要 | C128: 汎用文・不一致を含む | D128: 161行を問題の主題に合わせて書き換え | E128: 問題文との照合（H25〜H27、R1本は全行を書き換え）
A129: 全体 | B129: 選択肢の体裁 | C129: R4・R6は①〜⑤の記号なし | D129: 全年度で「① 本文」形式に統一
A130: 全体 | B130: ジャンル別出題傾向シート | C130: 手入力の回数（概算）・優先度 | D130: 「過去問マスターDB」から自動集計（COUNTIFS等の数式） | E130: v15の回数は実際の出題数と合っていなかった
A131: 全体 | B131: 概要シート | C131: R7〜R4のみ完全収録、18サブジャンル | D131: 全16回収録、33区分に更新
A132: 全体 | B132: シート順 | C132: H29が末尾 | D132: 年度の逆順（R7→H23）に整列
A133: R7-08 | B133: 問題文 | C133: 乾球温度7℃，絶対湿度0.004 | D133: 乾球温度10℃，絶対湿度0.004 | E133: 問題PDF（R7）：加熱前10℃・加熱後42℃。v15は他年度の数値（7℃→36℃）で、選択肢の答え58MJと整合しなかった
A134: R7-08 | B134: 問題文 | C134: 乾球温度36℃，絶対湿度0.014 | D134: 乾球温度42℃，絶対湿度0.014
A135: H28-18 | B135: 選択肢⑤ | C135: 尿・便使 | D135: 尿・糞便 | E135: 問題PDF（H28）
A136: H28-18 | B136: 選択肢⑤ | C136: 必要最小量 | D136: 必要最少量 | E136: 問題PDF（H28）
A137: H23-04 | B137: 問題のテーマ・内容概要 | C137: 中庭反射 | D137: 中庇反射 | E137: 問題PDF（H23）
A138: H23-05 | B138: 選択肢① | C138: 正常状態 | D138: 定常状態 | E138: 問題PDF（H23）
A139: H28-31 | B139: 選択肢② | C139: 破砕・粉砕されてから | D139: 破袋・破砕されてから | E139: 問題PDF（H28）
A140: R2-35 | B140: 選択肢① | C140: 二次仮置場 | D140: 一次仮置場 | E140: 問題PDF（R2）
A141: R3-07 | B141: 選択肢④ | C141: 避難安全確保を目的とし，消防法上の排煙設備は消火活動支援を目的としている | D141: 避難安全確保を主目的とし，消防法上の排煙設備は消火活動支援を主目的としている | E141: 問題PDF（R3）
A142: R3-27 | B142: 選択肢① | C142: 充分に | D142: 十分に | E142: 問題PDF（R3）
A143: R4-14 | B143: 選択肢⑤ | C143: 厨房等の処理がきちん行われて | D143: 厨芥等の処理がきちんと行われて | E143: 問題PDF（R4）
A144: R6-31 | B144: 選択肢① | C144: 高熱に維持 | D144: 高温に維持 | E144: 問題PDF（R6）
A145: H27-13 | B145: 選択肢④ | C145: 在郷軍大会合 | D145: 在郷軍人大会 | E145: 問題PDF（H27）
A146: H27-16 | B146: 選択肢③ | C146: シミもしわ | D146: シミやしわ | E146: 問題PDF（H27）
... A193: 全体 | B193: サブジャンル（15区分に集約） | C193: v16の33区分 | D193: 15区分に集約し、旧サブジャンルは新設の「出題論点（細目）」列に保存 | E193: 33区分では3〜8問の区分が7つあり細かすぎたため
